Workbook

Sheet Membresia - ppta
K1: Markup y costo de la operación
A2: Costos | D2: A encontrar | G2: Con quien competimos? | H2: Jumbo | I2: Frest | K2: Markup | L2: Desc. Jumbo | M2: Desc. Frest | N2: mínimo - cubre picking+pasarela | O2: costo operación | P2: minimo cubre delivery | Q2: operación (+delivery) | U2: 0.12 | V2: % markup (PVP) | Y2: La Vega al Costo
A3: delivery | B3: 2400 | D3: x | E3: % markup (PVP) | G3: precio delivery | H3: 4990 | I3: 3990 | K3: 0.05 | L3: 0.28 | M3: 0.32 | N3: 29000 | O3: =N3-N3/(1+K3)-0.02*N3-800 -> 0.95238095 | U3: 15000 | V3: Mínimo de compra | Y3: - Productos de La Vega de 1° calidad (mucho mejor que el super) al costo
A4: picking | B4: 800 | D4: y | E4: Mínimo de compra | G4: delivery gratis? | H4: Prime, sobre 22K | I4: No | K4: 0.06 | L4: 0.27 | M4: 0.32 | N4: 21900 | O4: =N4-N4/(1+K4)-0.02*N4-800 -> 1.6226415 | U4: 38000 | V4: Monto delivery gratis | W4: ----------------------------------------> | Y4: - 23% menos que el jumbo y 28% menos que frest siempre ("30% menos que verdulerias")
A5: pasarela | B5: 0.02 | D5: z | E5: Mínimo delivery gratis | G5: plazo delivery | H5: desde 30 minutos | I5: desde 90 minutos | K5: 0.07 | L5: 0.26 | M5: 0.31 | N5: 17600 | O5: =N5-N5/(1+K5)-0.02*N5-800 -> -0.59813084 | P5: 72000 | Q5: =P5-P5/(1+K5)-0.02*P5-3200 -> 70.280374 | U5: 2990 | V5: delivery | Y5: - Delivery gratis ilimitado (sobre $35000)
D6: d | E6: Delivery | G6: certeza delivery | H6: ventanas de 2 horas | I6: ventanas de 3 hrs | K6: 0.08 | L6: 0.25 | M6: 0.3 | N6: 14800 | O6: =N6-N6/(1+K6)-0.02*N6-800 -> 0.2962963 | P6: 60000 | Q6: =P6-P6/(1+K6)-0.02*P6-3200 -> 44.444444 | U6: 5500 | V6: monto suscripcion mensual
D7: s | E7: Monto suscripcion mensual | G7: cobertura delivery | H7: RM | I7: No todo RM | K7: 0.1 | L7: 0.24 | M7: 0.29 | N7: 11300 | O7: =N7-N7/(1+K7)-0.02*N7-800 -> 1.2727273 | P7: 46000 | Q7: =P7-P7/(1+K7)-0.02*P7-3200 -> 61.818182 | Y7: Comparación | Z7: Jumbo | AA7: Jumbo Prime | AB7: Frest | AC7: GoodFresh
G8: Mix | H8: Individuales | I8: packs + unitarios | K8: 0.12 | L8: 0.23 | M8: 0.28 | N8: 9200 | O8: =N8-N8/(1+K8)-0.02*N8-800 -> 1.7142857 | P8: 37000 | Q8: =P8-P8/(1+K8)-0.02*P8-3200 -> 24.285714 | Y8: precio productos | Z8: Mercado oriente | AA8: Mercado oriente | AB8: Sobre mercado | AC8: Al costo
G9: Formato | H9: Bolsas | I9: Bolsas | Y9: Diferenciador | Z9: one-stop-shop | AA9: one-stop-shop + delivery gratis | AB9: Calidad | AC9: Calidad + Precio
G10: Diferenciador | H10: one-stop-shop | I10: Calidad | K10: Ahorro del usuario en productos (8% markup) | Y10: precio delivery | Z10: 4990 | AA10: 0 sobre 22 | AB10: 3990 | AC10: 2990
G11: Suscripción | H11: 30.000 6 meses (5.000 mensual ) | I11: no | K11: 0.08 | L11: =L6 -> 0.25 | O11: =M6 -> 0.3 | Y11: plazo delivery | Z11: desde 30 minutos | AA11: desde 30 minutos | AB11: desde 90 minutos | AC11: Nex day
G12: qué incluye | H12: delivery gratis sobre 22.000 | K12: Carro | L12: Ahorro/carro jumbo | M12: 2 ped/mes | N12: 4 ped/mes | O12: Ahorro/carroFrest | P12: 2 ped/mes | Q12: 4 ped/mes | T12: Precio suscripción | U12: N | V12: revenue/ mes | W12: revenue/ año | Y12: certeza delivery | Z12: ventanas de 2 horas | AA12: ventanas de 2 horas | AB12: ventanas de 3 hrs | AC12: Nex day
G13: Precios | I13: más caro que supermercado | K13: 15000 | L13: =K13*$L$11 -> 3750 | M13: =L13*2 -> 7500 | N13: =L13*4 -> 15000 | O13: =K13*$O$11 -> 4500 | P13: =O13*2 -> 9000 | Q13: =O13*4 -> 18000 | T13: 4990 | U13: 2000 | V13: =U13*$T$13 -> 9980000 | W13: =V13*10 -> 99800000 | Y13: cobertura delivery | Z13: RM | AA13: RM | AB13: No todo RM | AC13: RM
K14: 20000 | L14: =K14*$L$11 -> 5000 | M14: =L14*2 -> 10000 | N14: =L14*4 -> 20000 | O14: =K14*$O$11 -> 6000 | P14: =O14*2 -> 12000 | Q14: =O14*4 -> 24000 | U14: 3000 | V14: =U14*$T$13 -> 14970000 | W14: =V14*10 -> 149700000 | Y14: Mix productos | Z14: Individuales - estándar | AA14: Individuales - estándar | AB14: packs + unitarios / más premium o nicho | AC14: packs + unitarios / estaciones
K15: 30000 | L15: =K15*$L$11 -> 7500 | M15: =L15*2 -> 15000 | N15: =L15*4 -> 30000 | O15: =K15*$O$11 -> 9000 | P15: =O15*2 -> 18000 | Q15: =O15*4 -> 36000 | U15: 5000 | V15: =U15*$T$13 -> 24950000 | W15: =V15*10 -> 249500000 | Y15: Formato | Z15: Bolsas | AA15: Bolsas | AB15: Bolsas | AC15: Cajas
G16: Jumo prime | K16: Ahorro del usuario en productos (12% markup) | U16: 6000 | V16: =U16*$T$13 -> 29940000 | W16: =V16*10 -> 299400000 | Y16: Diferenciador | Z16: one-stop-shop | AA16: one-stop-shop + delivery gratis | AB16: Calidad | AC16: Calidad + Precio
G17: "me sale 5000 cada delivery y la sucripcion 5000 por delivery gratis" | K17: 0.12 | L17: =L8 -> 0.23 | O17: =M8 -> 0.28 | U17: 8000 | V17: =U17*$T$13 -> 39920000 | W17: =V17*10 -> 399200000 | Y17: Costo suscripción (mes) | AA17: 5000 | AC17: 4990
G18: comunicación: "delivery gratis ilimitado" | K18: Carro | L18: Ahorro/carro jumbo | M18: 2 ped/mes | N18: 4 ped/mes | O18: Ahorro/carroFrest | P18: 2 ped/mes | Q18: 4 ped/mes | U18: 10000 | V18: =U18*$T$13 -> 49900000 | W18: =V18*10 -> 499000000
G19: letra chica: sobre 22.000 | K19: 15000 | L19: =K19*$L$17 -> 3450 | M19: =L19*2 -> 6900 | N19: =L19*4 -> 13800 | O19: =K19*$O$17 -> 4200 | P19: =O19*2 -> 8400 | Q19: =O19*4 -> 16800
K20: 20000 | L20: =K20*$L$17 -> 4600 | M20: =L20*2 -> 9200 | N20: =L20*4 -> 18400 | O20: =K20*$O$17 -> 5600 | P20: =O20*2 -> 11200 | Q20: =O20*4 -> 22400 | T20: 50000
K21: 30000 | L21: =K21*$L$17 -> 6900 | M21: =L21*2 -> 13800 | N21: =L21*4 -> 27600 | O21: =K21*$O$17 -> 8400 | P21: =O21*2 -> 16800 | Q21: =O21*4 -> 33600
K23: Delivery | L23: 1 pedido | M23: 2 ped/mes | N23: 4 ped/mes
L24: 2990 | M24: =L24*2 -> 5980 | N24: =M24*4 -> 23920

Sheet PPTA
B2: Con quien competimos? | C2: Jumbo | D2: Frest | G2: Objetivo de esta tienda
B3: precio delivery | C3: 4990 | D3: 3990 | G3: Salir del descuento
B4: delivery gratis? | C4: Prime, sobre 22K | D4: No | G4: Controlar stock
B5: plazo delivery | C5: desde 30 minutos | D5: desde 90 minutos | G5: Recurrencia
B6: certeza delivery | C6: ventanas de 2 horas | D6: ventanas de 3 hrs | G6: Que nuestros buyers compren más
B7: cobertura delivery | C7: RM | D7: No todo RM
B8: Mix | C8: Individuales | D8: packs + unitarios
B9: Formato | C9: Bolsas | D9: Bolsas
B10: Diferenciador | C10: one-stop-shop | D10: Calidad
B11: Margen GF igualando precios (Bruto) | C11: 0.31 | D11: 0.32
C14: Propuesta GF Membresía
B15: Margen | C15: 0-10%
B16: Estrategia pricing | C16: Costo + 12%
B17: Mix productos | C17: packs + unitarios
B18: Formato | C18: Cajas
B19: Packaging | C19: Caja que se devuelve
B20: Plazo entrega | C20: Next day
B21: Diferenciador | C21: Calidad y Precio
B22: Beneficio | C22: -23% jumbo -28 frest -15% lider
B23: Costo delivery | C23: 2990
B24: Membresía acceso

Sheet Listado de precios
A1: Producto | B1: Unidad | C1: Cantidad | D1: Precio Distribuidor C/IVA | E1: PVP | F1: Margen | G1: PVP suscripción (+12%) | H1: PVP (+8%) | I1: Lider | J1: Frest | K1: Jumbo | L1: Margen PVP frest | M1: Margen PVP Jumbo | N1: Juan esparraguito | O1: Dif vs lider % | P1: Dif vs Jumbo % | Q1: Link foto | R1: Otro | U1: PVP sus / Lider | V1: PVP sus /Jumbo (12%) | W1: PVP suscipcion - frest (12%) | X1: costo - jumbo | Y1: PVP sus /Jumbo (8%) | Z1: PVP suscipcion - frest (8%)
A2: Acelga | B2: Paquete | C2: 1 | D2: 850 | E2: 1590 | F2: =(E2-D2)/E2 -> 0.46540881 | G2: =D2*1.12 -> 952 | H2: =D2*1.08 -> 918 | I2: 1490 | J2: 1290 | K2: 1590 | L2: =(J2-D2)/J2 -> 0.34108527 | M2: =(K2-D2)/K2 -> 0.46540881 | O2: =(E2-I2)/E2 -> 0.062893082 | P2: =(E2-K2)/E2 -> 0 | Q2: https://cdn.shopify.com/s/files/1/0733/7318/8148/files/acelga.jpg?v=1762371793 | S2: =VLOOKUP(A2,'precios semana 2906'!A:B,2,0) -> 850 | T2: =(S2/D2)-1 -> 0 | U2: =G2/I2-1 -> -0.36107383 | V2: =G2/K2-1 -> -0.40125786 | W2: =G2/J2-1 -> -0.2620155 | X2: =G2-K2 -> -638 | Y2: =(H2/K2)-1 -> -0.42264151 | Z2: =(H2/J2)-1 -> -0.28837209
A3: Ají amarillo (peruano) | B3: Kilo | C3: 0.1 | D3: 700 | E3: 1390 | F3: =(E3-D3)/E3 -> 0.49640288 | G3: =D3*1.12 -> 784 | H3: =D3*1.08 -> 756 | J3: 1196 | L3: =(J3-D3)/J3 -> 0.41471572 | N3: 1390 | O3: =(E3-I3)/E3 -> 1 | P3: =(E3-K3)/E3 -> 1 | Q3: https://cdn.shopify.com/s/files/1/0733/7318/8148/files/ajiamarillo.jpg?v=1762286889 | R3: 1390 | S3: =VLOOKUP(A3,'precios semana 2906'!A:B,2,0) -> 700 | T3: =(S3/D3)-1 -> 0 | W3: =G3/J3-1 -> -0.34448161 | Y3: =(H3/K3)-1 -> #DIV/0! | Z3: =(H3/J3)-1 -> -0.36789298
A4: Ají verde (infierno) | B4: Kilo | C4: 0.2 | D4: 800 | E4: 1100 | F4: =(E4-D4)/E4 -> 0.27272727 | G4: =D4*1.12 -> 896 | H4: =D4*1.08 -> 864 | I4: 1078 | J4: 1112 | K4: 1158 | L4: =(J4-D4)/J4 -> 0.28057554 | M4: =(K4-D4)/K4 -> 0.30915371 | N4: 590 | O4: =(E4-I4)/E4 -> 0.02 | P4: =(E4-K4)/E4 -> -0.052727273 | Q4: https://cdn.shopify.com/s/files/1/0733/7318/8148/files/ajiverde.png?v=1762371744 | S4: =VLOOKUP(A4,'precios semana 2906'!A:B,2,0) -> 800 | T4: =(S4/D4)-1 -> 0 | U4: =G4/I4-1 -> -0.16883117 | V4: =G4/K4-1 -> -0.22625216 | W4: =G4/J4-1 -> -0.1942446 | X4: =G4-K4 -> -262 | Y4: =(H4/K4)-1 -> -0.25388601 | Z4: =(H4/J4)-1 -> -0.22302158
A5: Ajo | B5: Unidad | C5: 1 | D5: 200 | E5: 350 | F5: =(E5-D5)/E5 -> 0.42857143 | G5: =D5*1.12 -> 224 | H5: =D5*1.08 -> 216 | I5: 363 | J5: 300 | K5: 397 | L5: =(J5-D5)/J5 -> 0.33333333 | M5: =(K5-D5)/K5 -> 0.49622166 | N5: 1200 | O5: =(E5-I5)/E5 -> -0.037142857 | P5: =(E5-K5)/E5 -> -0.13428571 | Q5: https://cdn.shopify.com/s/files/1/0733/7318/8148/files/ajo.jpg?v=1762371704 | S5: =VLOOKUP(A5,'precios semana 2906'!A:B,2,0) -> 200 | T5: =(S5/D5)-1 -> 0 | U5: =G5/I5-1 -> -0.38292011 | V5: =G5/K5-1 -> -0.43576826 | W5: =G5/J5-1 -> -0.25333333 | X5: =G5-K5 -> -173 | Y5: =(H5/K5)-1 -> -0.4559194 | Z5: =(H5/J5)-1 -> -0.28
A6: Albahaca | B6: Kilo | C6: 0.05 | D6: 600 | E6: 1490 | F6: =(E6-D6)/E6 -> 0.59731544 | G6: =D6*1.12 -> 672 | H6: =D6*1.08 -> 648 | I6: 1590 | J6: 1490 | K6: 1590 | L6: =(J6-D6)/J6 -> 0.59731544 | M6: =(K6-D6)/K6 -> 0.62264151 | N6: 1690 | O6: =(E6-I6)/E6 -> -0.067114094 | P6: =(E6-K6)/E6 -> -0.067114094 | Q6: https://cdn.shopify.com/s/files/1/0733/7318/8148/files/zoomfotonoticia-129.jpg?v=1762371661 | R6: 845 | S6: =VLOOKUP(A6,'precios semana 2906'!A:B,2,0) -> 600 | T6: =(S6/D6)-1 -> 0 | U6: =G6/I6-1 -> -0.57735849 | V6: =G6/K6-1 -> -0.57735849 | W6: =G6/J6-1 -> -0.54899329 | X6: =G6-K6 -> -918 | Y6: =(H6/K6)-1 -> -0.59245283 | Z6: =(H6/J6)-1 -> -0.56510067
A7: Apio | B7: Unidad | C7: 1 | D7: 1500 | E7: 1990 | F7: =(E7-D7)/E7 -> 0.24623116 | G7: =D7*1.12 -> 1680 | H7: =D7*1.08 -> 1620 | I7: 1000 | J7: 1990 | K7: 1490 | L7: =(J7-D7)/J7 -> 0.24623116 | M7: =(K7-D7)/K7 -> -0.0067114094 | N7: 1990 | O7: =(E7-I7)/E7 -> 0.49748744 | P7: =(E7-K7)/E7 -> 0.25125628 | Q7: https://cdn.shopify.com/s/files/1/0733/7318/8148/files/apio.jpg?v=1762371609 | R7: 1990 | S7: =VLOOKUP(A7,'precios semana 2906'!A:B,2,0) -> 1400 | T7: =(S7/D7)-1 -> -0.066666667 | U7: =G7/I7-1 -> 0.68 | V7: =G7/K7-1 -> 0.12751678 | W7: =G7/J7-1 -> -0.15577889 | X7: =G7-K7 -> 190 | Y7: =(H7/K7)-1 -> 0.087248322 | Z7: =(H7/J7)-1 -> -0.18592965
A8: Alcachofas españolas | B8: Unidad | C8: 1 | D8: 800 | E8: 1390 | F8: =(E8-D8)/E8 -> 0.42446043 | G8: =D8*1.12 -> 896 | H8: =D8*1.08 -> 864 | I8: 790 | J8: 1390 | K8: 790 | L8: =(J8-D8)/J8 -> 0.42446043 | M8: =(K8-D8)/K8 -> -0.012658228 | N8: 1290 | O8: =(E8-I8)/E8 -> 0.43165468 | P8: =(E8-K8)/E8 -> 0.43165468 | Q8: https://cdn.shopify.com/s/files/1/0733/7318/8148/files/alcachofa_espaola_1ce9f8da-7a49-4ca2-9f3c-dad8035d9680.jpg?v=1762273270 | R8: 1290 | S8: =VLOOKUP(A8,'precios semana 2906'!A:B,2,0) -> 800 | T8: =(S8/D8)-1 -> 0 | U8: =G8/I8-1 -> 0.13417722 | V8: =G8/K8-1 -> 0.13417722 | W8: =G8/J8-1 -> -0.35539568 | X8: =G8-K8 -> 106 | Y8: =(H8/K8)-1 -> 0.093670886 | Z8: =(H8/J8)-1 -> -0.37841727
A9: Berenjena | B9: Unidad | C9: 1 | D9: 600 | E9: 890 | F9: =(E9-D9)/E9 -> 0.3258427 | G9: =D9*1.12 -> 672 | H9: =D9*1.08 -> 648 | I9: 790 | J9: 790 | K9: 790 | L9: =(J9-D9)/J9 -> 0.24050633 | M9: =(K9-D9)/K9 -> 0.24050633 | N9: 890 | O9: =(E9-I9)/E9 -> 0.11235955 | P9: =(E9-K9)/E9 -> 0.11235955 | Q9: https://cdn.shopify.com/s/files/1/0733/7318/8148/files/berenjena.jpg?v=1762371565 | R9: 890 | S9: =VLOOKUP(A9,'precios semana 2906'!A:B,2,0) -> 600 | T9: =(S9/D9)-1 -> 0 | U9: =G9/I9-1 -> -0.14936709 | V9: =G9/K9-1 -> -0.14936709 | W9: =G9/J9-1 -> -0.14936709 | X9: =G9-K9 -> -118 | Y9: =(H9/K9)-1 -> -0.17974684 | Z9: =(H9/J9)-1 -> -0.17974684
A10: Berros | B10: Kilo | C10: 0.05 | D10: 700 | E10: 1050 | F10: =(E10-D10)/E10 -> 0.33333333 | G10: =D10*1.12 -> 784 | H10: =D10*1.08 -> 756 | I10: 423 | J10: 663 | K10: 1050 | L10: =(J10-D10)/J10 -> -0.055806938 | M10: =(K10-D10)/K10 -> 0.33333333 | N10: 2690 | O10: =(E10-I10)/E10 -> 0.59714286 | P10: =(E10-K10)/E10 -> 0 | Q10: https://cdn.shopify.com/s/files/1/0733/7318/8148/files/berro.png?v=1762371522 | S10: =VLOOKUP(A10,'precios semana 2906'!A:B,2,0) -> 700 | T10: =(S10/D10)-1 -> 0 | U10: =G10/I10-1 -> 0.8534279 | V10: =G10/K10-1 -> -0.25333333 | W10: =G10/J10-1 -> 0.18250377 | X10: =G10-K10 -> -266 | Y10: =(H10/K10)-1 -> -0.28 | Z10: =(H10/J10)-1 -> 0.14027149
A11: Betarraga | B11: Paquete | C11: 1 | D11: 1000 | E11: 2250 | F11: =(E11-D11)/E11 -> 0.55555556 | G11: =D11*1.12 -> 1120 | H11: =D11*1.08 -> 1080 | I11: 1390 | J11: 2250 | K11: 1490 | L11: =(J11-D11)/J11 -> 0.55555556 | M11: =(K11-D11)/K11 -> 0.32885906 | N11: 2190 | O11: =(E11-I11)/E11 -> 0.38222222 | P11: =(E11-K11)/E11 -> 0.33777778 | Q11: https://cdn.shopify.com/s/files/1/0733/7318/8148/files/betarraga.jpg?v=1762371470 | R11: 2190 | S11: =VLOOKUP(A11,'precios semana 2906'!A:B,2,0) -> 1000 | T11: =(S11/D11)-1 -> 0 | U11: =G11/I11-1 -> -0.1942446 | V11: =G11/K11-1 -> -0.24832215 | W11: =G11/J11-1 -> -0.50222222 | X11: =G11-K11 -> -370 | Y11: =(H11/K11)-1 -> -0.27516779 | Z11: =(H11/J11)-1 -> -0.52
A12: Brocoli | B12: Unidad | C12: 1 | D12: 1400 | E12: 1990 | F12: =(E12-D12)/E12 -> 0.29648241 | G12: =D12*1.12 -> 1568 | H12: =D12*1.08 -> 1512 | I12: 1590 | J12: 1990 | K12: 1590 | L12: =(J12-D12)/J12 -> 0.29648241 | M12: =(K12-D12)/K12 -> 0.11949686 | N12: 1990 | O12: =(E12-I12)/E12 -> 0.20100503 | P12: =(E12-K12)/E12 -> 0.20100503 | Q12: https://cdn.shopify.com/s/files/1/0733/7318/8148/files/brocoli.jpg?v=1762371426 | R12: 1990 | S12: =VLOOKUP(A12,'precios semana 2906'!A:B,2,0) -> 1400 | T12: =(S12/D12)-1 -> 0 | U12: =G12/I12-1 -> -0.013836478 | V12: =G12/K12-1 -> -0.013836478 | W12: =G12/J12-1 -> -0.2120603 | X12: =G12-K12 -> -22 | Y12: =(H12/K12)-1 -> -0.049056604 | Z12: =(H12/J12)-1 -> -0.24020101
A13: Bruselas | B13: Kilo | C13: 0.5 | D13: 1200 | E13: 3690 | F13: =(E13-D13)/E13 -> 0.67479675 | G13: =D13*1.12 -> 1344 | H13: =D13*1.08 -> 1296 | I13: 3190 | J13: 3690 | K13: 3290 | L13: =(J13-D13)/J13 -> 0.67479675 | M13: =(K13-D13)/K13 -> 0.63525836 | N13: 2490 | O13: =(E13-I13)/E13 -> 0.13550136 | P13: =(E13-K13)/E13 -> 0.10840108 | Q13: https://cdn.shopify.com/s/files/1/0733/7318/8148/files/brusela_7ad88d5e-8c5a-44de-b1b8-f5077d48c88a.jpg?v=1770824864 | S13: =VLOOKUP(A13,'precios semana 2906'!A:B,2,0) -> 1200 | T13: =(S13/D13)-1 -> 0 | U13: =G13/I13-1 -> -0.57868339 | V13: =G13/K13-1 -> -0.59148936 | W13: =G13/J13-1 -> -0.63577236 | X13: =G13-K13 -> -1946 | Y13: =(H13/K13)-1 -> -0.60607903 | Z13: =(H13/J13)-1 -> -0.64878049
A14: Camote Morado | B14: Kilo | C14: 0.5 | D14: 1000 | E14: 1545 | F14: =(E14-D14)/E14 -> 0.35275081 | G14: =D14*1.12 -> 1120 | H14: =D14*1.08 -> 1080 | I14: 1545 | J14: 1495 | K14: 1545 | L14: =(J14-D14)/J14 -> 0.33110368 | M14: =(K14-D14)/K14 -> 0.35275081 | N14: 1395 | O14: =(E14-I14)/E14 -> 0 | P14: =(E14-K14)/E14 -> 0 | Q14: https://cdn.shopify.com/s/files/1/0733/7318/8148/files/camotemorado.jpg?v=1762371378 | S14: =VLOOKUP(A14,'precios semana 2906'!A:B,2,0) -> 1000 | T14: =(S14/D14)-1 -> 0 | U14: =G14/I14-1 -> -0.27508091 | V14: =G14/K14-1 -> -0.27508091 | W14: =G14/J14-1 -> -0.25083612 | X14: =G14-K14 -> -425 | Y14: =(H14/K14)-1 -> -0.30097087 | Z14: =(H14/J14)-1 -> -0.27759197
A15: Cebolla | B15: Unidad | C15: 1 | D15: 250 | E15: 450 | F15: =(E15-D15)/E15 -> 0.44444444 | G15: =D15*1.12 -> 280 | H15: =D15*1.08 -> 270 | I15: =1690/3.5 -> 482.85714 | J15: 430 | K15: =1690/3.5 -> 482.85714 | L15: =(J15-D15)/J15 -> 0.41860465 | M15: =(K15-D15)/K15 -> 0.48224852 | N15: 795 | O15: =(E15-I15)/E15 -> -0.073015873 | P15: =(E15-K15)/E15 -> -0.073015873 | Q15: https://cdn.shopify.com/s/files/1/0733/7318/8148/files/cebolla.jpg?v=1762371345 | S15: =VLOOKUP(A15,'precios semana 2906'!A:B,2,0) -> 250 | T15: =(S15/D15)-1 -> 0 | U15: =G15/I15-1 -> -0.42011834 | V15: =G15/K15-1 -> -0.42011834 | W15: =G15/J15-1 -> -0.34883721 | X15: =G15-K15 -> -202.85714 | Y15: =(H15/K15)-1 -> -0.4408284 | Z15: =(H15/J15)-1 -> -0.37209302
A16: Cebolla morada | B16: Unidad | C16: 1 | D16: 300 | E16: 570 | F16: =(E16-D16)/E16 -> 0.47368421 | G16: =D16*1.12 -> 336 | H16: =D16*1.08 -> 324 | I16: =1990/3.5 -> 568.57143 | J16: 463 | K16: =1990/3.5 -> 568.57143 | L16: =(J16-D16)/J16 -> 0.35205184 | M16: =(K16-D16)/K16 -> 0.47236181 | N16: 995 | O16: =(E16-I16)/E16 -> 0.0025062657 | P16: =(E16-K16)/E16 -> 0.0025062657 | Q16: https://cdn.shopify.com/s/files/1/0733/7318/8148/files/cebollamorada.jpg?v=1762371301 | S16: =VLOOKUP(A16,'precios semana 2906'!A:B,2,0) -> 300 | T16: =(S16/D16)-1 -> 0 | U16: =G16/I16-1 -> -0.40904523 | V16: =G16/K16-1 -> -0.40904523 | W16: =G16/J16-1 -> -0.27429806 | X16: =G16-K16 -> -232.57143 | Y16: =(H16/K16)-1 -> -0.43015075 | Z16: =(H16/J16)-1 -> -0.30021598
A17: Cebollín | B17: Paquete | C17: 1 | D17: 700 | E17: 1190 | F17: =(E17-D17)/E17 -> 0.41176471 | G17: =D17*1.12 -> 784 | H17: =D17*1.08 -> 756 | I17: 1550 | J17: 1190 | K17: 1590 | L17: =(J17-D17)/J17 -> 0.41176471 | M17: =(K17-D17)/K17 -> 0.55974843 | N17: 990 | O17: =(E17-I17)/E17 -> -0.30252101 | P17: =(E17-K17)/E17 -> -0.33613445 | Q17: https://cdn.shopify.com/s/files/1/0733/7318/8148/files/cebollin.jpg?v=1762371254 | S17: =VLOOKUP(A17,'precios semana 2906'!A:B,2,0) -> 700 | T17: =(S17/D17)-1 -> 0 | U17: =G17/I17-1 -> -0.49419355 | V17: =G17/K17-1 -> -0.50691824 | W17: =G17/J17-1 -> -0.34117647 | X17: =G17-K17 -> -806 | Y17: =(H17/K17)-1 -> -0.5245283 | Z17: =(H17/J17)-1 -> -0.36470588
A18: Champiñon | B18: Bandeja | C18: 1 | D18: 1500 | E18: 2190 | F18: =(E18-D18)/E18 -> 0.31506849 | G18: =D18*1.12 -> 1680 | H18: =D18*1.08 -> 1620 | I18: 1590 | J18: 1990 | K18: 1650 | L18: =(J18-D18)/J18 -> 0.24623116 | M18: =(K18-D18)/K18 -> 0.090909091 | N18: 2190 | O18: =(E18-I18)/E18 -> 0.2739726 | P18: =(E18-K18)/E18 -> 0.24657534 | Q18: https://cdn.shopify.com/s/files/1/0733/7318/8148/files/champinon.png?v=1762371200 | R18: 2190 | S18: =VLOOKUP(A18,'precios semana 2906'!A:B,2,0) -> 1500 | T18: =(S18/D18)-1 -> 0 | U18: =G18/I18-1 -> 0.056603774 | V18: =G18/K18-1 -> 0.018181818 | W18: =G18/J18-1 -> -0.15577889 | X18: =G18-K18 -> 30 | Y18: =(H18/K18)-1 -> -0.018181818 | Z18: =(H18/J18)-1 -> -0.18592965
A19: Choclo americano | B19: Unidad | C19: 1 | D19: 700 | E19: 990 | F19: =(E19-D19)/E19 -> 0.29292929 | G19: =D19*1.12 -> 784 | H19: =D19*1.08 -> 756 | I19: 898 | J19: 900 | K19: 925 | L19: =(J19-D19)/J19 -> 0.22222222 | M19: =(K19-D19)/K19 -> 0.24324324 | N19: 990 | O19: =(E19-I19)/E19 -> 0.092929293 | P19: =(E19-K19)/E19 -> 0.065656566 | Q19: https://cdn.shopify.com/s/files/1/0733/7318/8148/files/chocloamericano.jpg?v=1762371104 | R19: 990 | S19: =VLOOKUP(A19,'precios semana 2906'!A:B,2,0) -> 800 | T19: =(S19/D19)-1 -> 0.14285714 | U19: =G19/I19-1 -> -0.12694878 | V19: =G19/K19-1 -> -0.15243243 | W19: =G19/J19-1 -> -0.12888889 | X19: =G19-K19 -> -141 | Y19: =(H19/K19)-1 -> -0.1827027 | Z19: =(H19/J19)-1 -> -0.16
A20: Ciboulette | B20: Paquete | C20: 1 | D20: 350 | E20: 740 | F20: =(E20-D20)/E20 -> 0.52702703 | G20: =D20*1.12 -> 392 | H20: =D20*1.08 -> 378 | I20: 690 | J20: 500 | K20: 740 | L20: =(J20-D20)/J20 -> 0.3 | M20: =(K20-D20)/K20 -> 0.52702703 | N20: 790 | O20: =(E20-I20)/E20 -> 0.067567568 | P20: =(E20-K20)/E20 -> 0 | Q20: https://cdn.shopify.com/s/files/1/0733/7318/8148/files/ciboulette.jpg?v=1762371149 | R20: 790 | S20: =VLOOKUP(A20,'precios semana 2906'!A:B,2,0) -> 350 | T20: =(S20/D20)-1 -> 0 | U20: =G20/I20-1 -> -0.43188406 | V20: =G20/K20-1 -> -0.47027027 | W20: =G20/J20-1 -> -0.216 | X20: =G20-K20 -> -348 | Y20: =(H20/K20)-1 -> -0.48918919 | Z20: =(H20/J20)-1 -> -0.244
A21: Cilantro | B21: Paquete | C21: 1 | D21: 600 | E21: 1290 | F21: =(E21-D21)/E21 -> 0.53488372 | G21: =D21*1.12 -> 672 | H21: =D21*1.08 -> 648 | I21: 950 | J21: 990 | K21: 990 | L21: =(J21-D21)/J21 -> 0.39393939 | M21: =(K21-D21)/K21 -> 0.39393939 | N21: 1290 | O21: =(E21-I21)/E21 -> 0.26356589 | P21: =(E21-K21)/E21 -> 0.23255814 | Q21: https://cdn.shopify.com/s/files/1/0733/7318/8148/files/cilantro.jpg?v=1762371069 | R21: 1290 | S21: =VLOOKUP(A21,'precios semana 2906'!A:B,2,0) -> 650 | T21: =(S21/D21)-1 -> 0.083333333 | U21: =G21/I21-1 -> -0.29263158 | V21: =G21/K21-1 -> -0.32121212 | W21: =G21/J21-1 -> -0.32121212 | X21: =G21-K21 -> -318 | Y21: =(H21/K21)-1 -> -0.34545455 | Z21: =(H21/J21)-1 -> -0.34545455
A22: Coliflor | B22: Unidad | C22: 1 | D22: 1500 | E22: 2490 | F22: =(E22-D22)/E22 -> 0.39759036 | G22: =D22*1.12 -> 1680 | H22: =D22*1.08 -> 1620 | I22: 1590 | J22: 2490 | K22: 1690 | L22: =(J22-D22)/J22 -> 0.39759036 | M22: =(K22-D22)/K22 -> 0.11242604 | N22: 1990 | O22: =(E22-I22)/E22 -> 0.36144578 | P22: =(E22-K22)/E22 -> 0.32128514 | Q22: https://cdn.shopify.com/s/files/1/0733/7318/8148/files/coliflor.jpg?v=1762371015 | S22: =VLOOKUP(A22,'precios semana 2906'!A:B,2,0) -> 1500 | T22: =(S22/D22)-1 -> 0 | U22: =G22/I22-1 -> 0.056603774 | V22: =G22/K22-1 -> -0.0059171598 | W22: =G22/J22-1 -> -0.3253012 | X22: =G22-K22 -> -10 | Y22: =(H22/K22)-1 -> -0.041420118 | Z22: =(H22/J22)-1 -> -0.34939759
A23: Diente de dragon | B23: Kilo | C23: 0.2 | D23: 650 | E23: 1060 | F23: =(E23-D23)/E23 -> 0.38679245 | G23: =D23*1.12 -> 728 | H23: =D23*1.08 -> 702 | I23: 990 | J23: 792 | K23: 1060 | L23: =(J23-D23)/J23 -> 0.17929293 | M23: =(K23-D23)/K23 -> 0.38679245 | N23: no hay | O23: =(E23-I23)/E23 -> 0.066037736 | P23: =(E23-K23)/E23 -> 0 | Q23: https://cdn.shopify.com/s/files/1/0733/7318/8148/files/diente-de-dragon.jpg?v=1762286722 | S23: =VLOOKUP(A23,'precios semana 2906'!A:B,2,0) -> 800 | T23: =(S23/D23)-1 -> 0.23076923 | U23: =G23/I23-1 -> -0.26464646 | V23: =G23/K23-1 -> -0.31320755 | W23: =G23/J23-1 -> -0.080808081 | X23: =G23-K23 -> -332 | Y23: =(H23/K23)-1 -> -0.33773585 | Z23: =(H23/J23)-1 -> -0.11363636
A24: Esparragos | B24: Kilo | C24: 0.3 | D24: 3500 | E24: 5290 | F24: =(E24-D24)/E24 -> 0.33837429 | G24: =D24*1.12 -> 3920 | H24: =D24*1.08 -> 3780 | I24: 4190 | J24: 5290 | K24: 4610 | L24: =(J24-D24)/J24 -> 0.33837429 | M24: =(K24-D24)/K24 -> 0.24078091 | N24: no hay | O24: =(E24-I24)/E24 -> 0.20793951 | P24: =(E24-K24)/E24 -> 0.12854442 | Q24: https://cdn.shopify.com/s/files/1/0733/7318/8148/files/esparragos-verdes.jpg?v=1774095995 | S24: =VLOOKUP(A24,'precios semana 2906'!A:B,2,0) -> 3500 | T24: =(S24/D24)-1 -> 0 | U24: =G24/I24-1 -> -0.064439141 | V24: =G24/K24-1 -> -0.14967462 | W24: =G24/J24-1 -> -0.25897921 | X24: =G24-K24 -> -690 | Y24: =(H24/K24)-1 -> -0.18004338 | Z24: =(H24/J24)-1 -> -0.28544423
A25: Jengibre | B25: Kilo | C25: 0.1 | D25: 400 | E25: 1490 | F25: =(E25-D25)/E25 -> 0.73154362 | G25: =D25*1.12 -> 448 | H25: =D25*1.08 -> 432 | I25: 1490 | J25: 1380 | K25: 1590 | L25: =(J25-D25)/J25 -> 0.71014493 | M25: =(K25-D25)/K25 -> 0.74842767 | N25: 1390 | O25: =(E25-I25)/E25 -> 0 | P25: =(E25-K25)/E25 -> -0.067114094 | Q25: https://cdn.shopify.com/s/files/1/0733/7318/8148/files/jengibre.jpg?v=1762370932 | R25: 1390 | S25: =VLOOKUP(A25,'precios semana 2906'!A:B,2,0) -> 400 | T25: =(S25/D25)-1 -> 0 | U25: =G25/I25-1 -> -0.69932886 | V25: =G25/K25-1 -> -0.71823899 | W25: =G25/J25-1 -> -0.67536232 | X25: =G25-K25 -> -1142 | Y25: =(H25/K25)-1 -> -0.72830189 | Z25: =(H25/J25)-1 -> -0.68695652
A26: Lechuga costina | B26: Unidad | C26: 1 | D26: 1000 | E26: 1490 | F26: =(E26-D26)/E26 -> 0.32885906 | G26: =D26*1.12 -> 1120 | H26: =D26*1.08 -> 1080 | I26: 1290 | J26: 1390 | K26: 1420 | L26: =(J26-D26)/J26 -> 0.28057554 | M26: =(K26-D26)/K26 -> 0.29577465 | N26: 1490 | O26: =(E26-I26)/E26 -> 0.13422819 | P26: =(E26-K26)/E26 -> 0.046979866 | Q26: https://cdn.shopify.com/s/files/1/0733/7318/8148/files/lechugacostina.png?v=1762370884 | R26: 1490 | S26: =VLOOKUP(A26,'precios semana 2906'!A:B,2,0) -> 1000 | T26: =(S26/D26)-1 -> 0 | U26: =G26/I26-1 -> -0.13178295 | V26: =G26/K26-1 -> -0.21126761 | W26: =G26/J26-1 -> -0.1942446 | X26: =G26-K26 -> -300 | Y26: =(H26/K26)-1 -> -0.23943662 | Z26: =(H26/J26)-1 -> -0.22302158
A27: Lechuga escarola | B27: Unidad | C27: 1 | D27: 800 | E27: 1460 | F27: =(E27-D27)/E27 -> 0.45205479 | G27: =D27*1.12 -> 896 | H27: =D27*1.08 -> 864 | I27: 1290 | J27: 1290 | K27: 1460 | L27: =(J27-D27)/J27 -> 0.37984496 | M27: =(K27-D27)/K27 -> 0.45205479 | N27: 1490 | O27: =(E27-I27)/E27 -> 0.11643836 | P27: =(E27-K27)/E27 -> 0 | Q27: https://cdn.shopify.com/s/files/1/0733/7318/8148/files/lechugaescarola.jpg?v=1762370847 | R27: 1490 | S27: =VLOOKUP(A27,'precios semana 2906'!A:B,2,0) -> 800 | T27: =(S27/D27)-1 -> 0 | U27: =G27/I27-1 -> -0.30542636 | V27: =G27/K27-1 -> -0.38630137 | W27: =G27/J27-1 -> -0.30542636 | X27: =G27-K27 -> -564 | Y27: =(H27/K27)-1 -> -0.40821918 | Z27: =(H27/J27)-1 -> -0.33023256
A28: Lechuga española | B28: Unidad | C28: 1 | D28: 800 | E28: 1890 | F28: =(E28-D28)/E28 -> 0.57671958 | G28: =D28*1.12 -> 896 | H28: =D28*1.08 -> 864 | I28: 1590 | J28: 1890 | K28: 1740 | L28: =(J28-D28)/J28 -> 0.57671958 | M28: =(K28-D28)/K28 -> 0.54022989 | N28: 1890 | O28: =(E28-I28)/E28 -> 0.15873016 | P28: =(E28-K28)/E28 -> 0.079365079 | Q28: https://cdn.shopify.com/s/files/1/0733/7318/8148/files/lechugaespanola.jpg?v=1762370805 | R28: 1890 | S28: =VLOOKUP(A28,'precios semana 2906'!A:B,2,0) -> 800 | T28: =(S28/D28)-1 -> 0 | U28: =G28/I28-1 -> -0.43647799 | V28: =G28/K28-1 -> -0.48505747 | W28: =G28/J28-1 -> -0.52592593 | X28: =G28-K28 -> -844 | Y28: =(H28/K28)-1 -> -0.50344828 | Z28: =(H28/J28)-1 -> -0.54285714
A29: Lechuga Francesa | B29: Unidad | C29: 1 | D29: 800 | E29: 1290 | F29: =(E29-D29)/E29 -> 0.37984496 | G29: =D29*1.12 -> 896 | H29: =D29*1.08 -> 864 | I29: 1290 | J29: 1090 | K29: 1250 | L29: =(J29-D29)/J29 -> 0.26605505 | M29: =(K29-D29)/K29 -> 0.36 | N29: no hay | O29: =(E29-I29)/E29 -> 0 | P29: =(E29-K29)/E29 -> 0.031007752 | Q29: https://cdn.shopify.com/s/files/1/0733/7318/8148/files/lechugafrancesa.jpg?v=1762370766 | S29: =VLOOKUP(A29,'precios semana 2906'!A:B,2,0) -> 800 | T29: =(S29/D29)-1 -> 0 | U29: =G29/I29-1 -> -0.30542636 | V29: =G29/K29-1 -> -0.2832 | W29: =G29/J29-1 -> -0.17798165 | X29: =G29-K29 -> -354 | Y29: =(H29/K29)-1 -> -0.3088 | Z29: =(H29/J29)-1 -> -0.20733945
A30: Lechuga Marina | B30: Unidad | C30: 1 | D30: 800 | E30: 1290 | F30: =(E30-D30)/E30 -> 0.37984496 | G30: =D30*1.12 -> 896 | H30: =D30*1.08 -> 864 | I30: 1290 | J30: 1090 | K30: 1360 | L30: =(J30-D30)/J30 -> 0.26605505 | M30: =(K30-D30)/K30 -> 0.41176471 | N30: no hay | O30: =(E30-I30)/E30 -> 0 | P30: =(E30-K30)/E30 -> -0.054263566 | Q30: https://cdn.shopify.com/s/files/1/0733/7318/8148/files/lechugamarina.png?v=1762370725 | S30: =VLOOKUP(A30,'precios semana 2906'!A:B,2,0) -> 800 | T30: =(S30/D30)-1 -> 0 | U30: =G30/I30-1 -> -0.30542636 | V30: =G30/K30-1 -> -0.34117647 | W30: =G30/J30-1 -> -0.17798165 | X30: =G30-K30 -> -464 | Y30: =(H30/K30)-1 -> -0.36470588 | Z30: =(H30/J30)-1 -> -0.20733945
A31: Lechuga hidroponica | B31: Unidad | C31: 1 | D31: 900 | E31: 1890 | F31: =(E31-D31)/E31 -> 0.52380952 | G31: =D31*1.12 -> 1008 | H31: =D31*1.08 -> 972 | I31: 1590 | J31: 1690 | K31: 1740 | L31: =(J31-D31)/J31 -> 0.46745562 | M31: =(K31-D31)/K31 -> 0.48275862 | N31: 1890 | O31: =(E31-I31)/E31 -> 0.15873016 | P31: =(E31-K31)/E31 -> 0.079365079 | Q31: https://cdn.shopify.com/s/files/1/0733/7318/8148/files/2076542.jpg?v=1762286622 | R31: 1890 | S31: =VLOOKUP(A31,'precios semana 2906'!A:B,2,0) -> 900 | T31: =(S31/D31)-1 -> 0 | U31: =G31/I31-1 -> -0.36603774 | V31: =G31/K31-1 -> -0.42068966 | W31: =G31/J31-1 -> -0.4035503 | X31: =G31-K31 -> -732 | Y31: =(H31/K31)-1 -> -0.44137931 | Z31: =(H31/J31)-1 -> -0.42485207
A32: Menta | B32: Kilo | C32: 0.05 | D32: 480 | E32: 990 | F32: =(E32-D32)/E32 -> 0.51515152 | G32: =D32*1.12 -> 537.6 | H32: =D32*1.08 -> 518.4 | I32: 990 | J32: 990 | K32: 1050 | L32: =(J32-D32)/J32 -> 0.51515152 | M32: =(K32-D32)/K32 -> 0.54285714 | N32: 2690 | O32: =(E32-I32)/E32 -> 0 | P32: =(E32-K32)/E32 -> -0.060606061 | Q32: https://cdn.shopify.com/s/files/1/0733/7318/8148/files/menta.jpg?v=1762370549 | R32: 1345 | S32: =VLOOKUP(A32,'precios semana 2906'!A:B,2,0) -> 480 | T32: =(S32/D32)-1 -> 0 | U32: =G32/I32-1 -> -0.4569697 | V32: =G32/K32-1 -> -0.488 | W32: =G32/J32-1 -> -0.4569697 | X32: =G32-K32 -> -512.4 | Y32: =(H32/K32)-1 -> -0.50628571 | Z32: =(H32/J32)-1 -> -0.47636364
A33: Papa | B33: Kilo | C33: 1 | D33: 850 | E33: 1590 | F33: =(E33-D33)/E33 -> 0.46540881 | G33: =D33*1.12 -> 952 | H33: =D33*1.08 -> 918 | I33: 1590 | J33: 1090 | K33: 1590 | L33: =(J33-D33)/J33 -> 0.22018349 | M33: =(K33-D33)/K33 -> 0.46540881 | N33: 795 | O33: =(E33-I33)/E33 -> 0 | P33: =(E33-K33)/E33 -> 0 | Q33: https://cdn.shopify.com/s/files/1/0733/7318/8148/files/papasemillon_744a31b4-760a-4b2c-ba89-e2fd58430be6.jpg?v=1762273302 | R33: 1590 | S33: =VLOOKUP(A33,'precios semana 2906'!A:B,2,0) -> 850 | T33: =(S33/D33)-1 -> 0 | U33: =G33/I33-1 -> -0.40125786 | V33: =G33/K33-1 -> -0.40125786 | W33: =G33/J33-1 -> -0.1266055 | X33: =G33-K33 -> -638 | Y33: =(H33/K33)-1 -> -0.42264151 | Z33: =(H33/J33)-1 -> -0.15779817
A34: Pepinos | B34: Unidad | C34: 1 | D34: 650 | E34: 790 | F34: =(E34-D34)/E34 -> 0.17721519 | G34: =D34*1.12 -> 728 | H34: =D34*1.08 -> 702 | I34: 720 | J34: 790 | K34: 750 | L34: =(J34-D34)/J34 -> 0.17721519 | M34: =(K34-D34)/K34 -> 0.13333333 | N34: 790 | O34: =(E34-I34)/E34 -> 0.088607595 | P34: =(E34-K34)/E34 -> 0.050632911 | Q34: https://cdn.shopify.com/s/files/1/0733/7318/8148/files/pepino.jpg?v=1762370475 | R34: 790 | S34: =VLOOKUP(A34,'precios semana 2906'!A:B,2,0) -> 650 | T34: =(S34/D34)-1 -> 0 | U34: =G34/I34-1 -> 0.011111111 | V34: =G34/K34-1 -> -0.029333333 | W34: =G34/J34-1 -> -0.078481013 | X34: =G34-K34 -> -22 | Y34: =(H34/K34)-1 -> -0.064 | Z34: =(H34/J34)-1 -> -0.11139241
A35: Perejil | B35: Paquete | C35: 1 | D35: 600 | E35: 990 | F35: =(E35-D35)/E35 -> 0.39393939 | G35: =D35*1.12 -> 672 | H35: =D35*1.08 -> 648 | I35: 630 | J35: 990 | K35: 650 | L35: =(J35-D35)/J35 -> 0.39393939 | M35: =(K35-D35)/K35 -> 0.076923077 | N35: 1250 | O35: =(E35-I35)/E35 -> 0.36363636 | P35: =(E35-K35)/E35 -> 0.34343434 | Q35: https://cdn.shopify.com/s/files/1/0733/7318/8148/files/perejil.jpg?v=1762370436 | S35: =VLOOKUP(A35,'precios semana 2906'!A:B,2,0) -> 700 | T35: =(S35/D35)-1 -> 0.16666667 | U35: =G35/I35-1 -> 0.066666667 | V35: =G35/K35-1 -> 0.033846154 | W35: =G35/J35-1 -> -0.32121212 | X35: =G35-K35 -> 22 | Y35: =(H35/K35)-1 -> -0.0030769231 | Z35: =(H35/J35)-1 -> -0.34545455
A36: Pimentón amarillo | B36: Unidad | C36: 1 | D36: 1000 | E36: 1690 | F36: =(E36-D36)/E36 -> 0.40828402 | G36: =D36*1.12 -> 1120 | H36: =D36*1.08 -> 1080 | I36: 1690 | J36: 1490 | K36: 1790 | L36: =(J36-D36)/J36 -> 0.32885906 | M36: =(K36-D36)/K36 -> 0.44134078 | N36: no hay | O36: =(E36-I36)/E36 -> 0 | P36: =(E36-K36)/E36 -> -0.059171598 | Q36: https://cdn.shopify.com/s/files/1/0733/7318/8148/files/pimentonamarillo.jpg?v=1762370398 | S36: =VLOOKUP(A36,'precios semana 2906'!A:B,2,0) -> 1000 | T36: =(S36/D36)-1 -> 0 | U36: =G36/I36-1 -> -0.33727811 | V36: =G36/K36-1 -> -0.37430168 | W36: =G36/J36-1 -> -0.24832215 | X36: =G36-K36 -> -670 | Y36: =(H36/K36)-1 -> -0.39664804 | Z36: =(H36/J36)-1 -> -0.27516779
A37: Pimentón rojo | B37: Unidad | C37: 1 | D37: 1000 | E37: 1690 | F37: =(E37-D37)/E37 -> 0.40828402 | G37: =D37*1.12 -> 1120 | H37: =D37*1.08 -> 1080 | I37: 1690 | J37: 1490 | K37: 1790 | L37: =(J37-D37)/J37 -> 0.32885906 | M37: =(K37-D37)/K37 -> 0.44134078 | N37: 1790 | O37: =(E37-I37)/E37 -> 0 | P37: =(E37-K37)/E37 -> -0.059171598 | Q37: https://cdn.shopify.com/s/files/1/0733/7318/8148/files/pimentonrojo.jpg?v=1762370356 | R37: 1790 | S37: =VLOOKUP(A37,'precios semana 2906'!A:B,2,0) -> 800 | T37: =(S37/D37)-1 -> -0.2 | U37: =G37/I37-1 -> -0.33727811 | V37: =G37/K37-1 -> -0.37430168 | W37: =G37/J37-1 -> -0.24832215 | X37: =G37-K37 -> -670 | Y37: =(H37/K37)-1 -> -0.39664804 | Z37: =(H37/J37)-1 -> -0.27516779
A38: Pimentón verde | B38: Unidad | C38: 1 | D38: 700 | E38: 1190 | F38: =(E38-D38)/E38 -> 0.41176471 | G38: =D38*1.12 -> 784 | H38: =D38*1.08 -> 756 | I38: 950 | J38: 990 | K38: 990 | L38: =(J38-D38)/J38 -> 0.29292929 | M38: =(K38-D38)/K38 -> 0.29292929 | N38: 1190 | O38: =(E38-I38)/E38 -> 0.20168067 | P38: =(E38-K38)/E38 -> 0.16806723 | Q38: https://cdn.shopify.com/s/files/1/0733/7318/8148/files/pimentonverde.jpg?v=1762370310 | R38: 1190 | S38: =VLOOKUP(A38,'precios semana 2906'!A:B,2,0) -> 700 | T38: =(S38/D38)-1 -> 0 | U38: =G38/I38-1 -> -0.17473684 | V38: =G38/K38-1 -> -0.20808081 | W38: =G38/J38-1 -> -0.20808081 | X38: =G38-K38 -> -206 | Y38: =(H38/K38)-1 -> -0.23636364 | Z38: =(H38/J38)-1 -> -0.23636364
A39: Porotos verdes | B39: Kilo | C39: 0.5 | D39: 1600 | E39: 2190 | F39: =(E39-D39)/E39 -> 0.26940639 | G39: =D39*1.12 -> 1792 | H39: =D39*1.08 -> 1728 | I39: 995 | J39: 2190 | K39: 1995 | L39: =(J39-D39)/J39 -> 0.26940639 | M39: =(K39-D39)/K39 -> 0.19799499 | N39: no hay | O39: =(E39-I39)/E39 -> 0.5456621 | P39: =(E39-K39)/E39 -> 0.089041096 | Q39: https://cdn.shopify.com/s/files/1/0733/7318/8148/files/poroto-verde.jpg?v=1762286507 | S39: =VLOOKUP(A39,'precios semana 2906'!A:B,2,0) -> 1600 | T39: =(S39/D39)-1 -> 0 | U39: =G39/I39-1 -> 0.80100503 | V39: =G39/K39-1 -> -0.10175439 | W39: =G39/J39-1 -> -0.18173516 | X39: =G39-K39 -> -203 | Y39: =(H39/K39)-1 -> -0.13383459 | Z39: =(H39/J39)-1 -> -0.2109589
A40: Rabanitos | B40: Paquete | C40: 1 | D40: 800 | E40: 1350 | F40: =(E40-D40)/E40 -> 0.40740741 | G40: =D40*1.12 -> 896 | H40: =D40*1.08 -> 864 | I40: 1350 | J40: 990 | K40: 1450 | L40: =(J40-D40)/J40 -> 0.19191919 | M40: =(K40-D40)/K40 -> 0.44827586 | N40: 1990 | O40: =(E40-I40)/E40 -> 0 | P40: =(E40-K40)/E40 -> -0.074074074 | Q40: https://cdn.shopify.com/s/files/1/0733/7318/8148/files/Rabanito.jpg?v=1762370275 | R40: 1990 | S40: =VLOOKUP(A40,'precios semana 2906'!A:B,2,0) -> 800 | T40: =(S40/D40)-1 -> 0 | U40: =G40/I40-1 -> -0.3362963 | V40: =G40/K40-1 -> -0.38206897 | W40: =G40/J40-1 -> -0.094949495 | X40: =G40-K40 -> -554 | Y40: =(H40/K40)-1 -> -0.40413793 | Z40: =(H40/J40)-1 -> -0.12727273
A41: Repollo morado | B41: Unidad | C41: 1 | D41: 3000 | E41: 3990 | F41: =(E41-D41)/E41 -> 0.2481203 | G41: =D41*1.12 -> 3360 | H41: =D41*1.08 -> 3240 | I41: 1590 | J41: 4690 | K41: 1710 | L41: =(J41-D41)/J41 -> 0.36034115 | M41: =(K41-D41)/K41 -> -0.75438596 | N41: 3990 | O41: =(E41-I41)/E41 -> 0.60150376 | P41: =(E41-K41)/E41 -> 0.57142857 | Q41: https://cdn.shopify.com/s/files/1/0733/7318/8148/files/fresh-whole-purple-cabbage-and-cut-in-half-isolate-on-white-background-free-photo.jpg?v=1779204441 | R41: 3990 | S41: =VLOOKUP(A41,'precios semana 2906'!A:B,2,0) -> 3000 | T41: =(S41/D41)-1 -> 0 | U41: =G41/I41-1 -> 1.1132075 | V41: =G41/K41-1 -> 0.96491228 | W41: =G41/J41-1 -> -0.28358209 | X41: =G41-K41 -> 1650 | Y41: =(H41/K41)-1 -> 0.89473684 | Z41: =(H41/J41)-1 -> -0.30916844
A42: Repollo crespo | B42: Unidad | C42: 1 | D42: 3000 | E42: 3990 | F42: =(E42-D42)/E42 -> 0.2481203 | G42: =D42*1.12 -> 3360 | H42: =D42*1.08 -> 3240 | I42: 1590 | J42: 3990 | K42: 1690 | L42: =(J42-D42)/J42 -> 0.2481203 | M42: =(K42-D42)/K42 -> -0.77514793 | N42: 3990 | O42: =(E42-I42)/E42 -> 0.60150376 | P42: =(E42-K42)/E42 -> 0.5764411 | Q42: https://cdn.shopify.com/s/files/1/0733/7318/8148/files/medio-repollo.jpg?v=1762271335 | R42: 3990 | S42: =VLOOKUP(A42,'precios semana 2906'!A:B,2,0) -> 2800 | T42: =(S42/D42)-1 -> -0.066666667 | U42: =G42/I42-1 -> 1.1132075 | V42: =G42/K42-1 -> 0.98816568 | W42: =G42/J42-1 -> -0.15789474 | X42: =G42-K42 -> 1670 | Y42: =(H42/K42)-1 -> 0.91715976 | Z42: =(H42/J42)-1 -> -0.18796992
A43: Rúcula | B43: Kilo | C43: 0.1 | D43: 600 | E43: 1345 | F43: =(E43-D43)/E43 -> 0.55390335 | G43: =D43*1.12 -> 672 | H43: =D43*1.08 -> 648 | I43: 1527 | J43: 745 | K43: 1345 | L43: =(J43-D43)/J43 -> 0.19463087 | M43: =(K43-D43)/K43 -> 0.55390335 | N43: 2690 | O43: =(E43-I43)/E43 -> -0.13531599 | P43: =(E43-K43)/E43 -> 0 | Q43: https://cdn.shopify.com/s/files/1/0733/7318/8148/files/rucula.png?v=1762370236 | R43: 1345 | S43: =VLOOKUP(A43,'precios semana 2906'!A:B,2,0) -> 600 | T43: =(S43/D43)-1 -> 0 | U43: =G43/I43-1 -> -0.55992141 | V43: =G43/K43-1 -> -0.50037175 | W43: =G43/J43-1 -> -0.097986577 | X43: =G43-K43 -> -673 | Y43: =(H43/K43)-1 -> -0.51821561 | Z43: =(H43/J43)-1 -> -0.13020134
A44: Tomate larga vida | B44: Kilo | C44: 1 | D44: 1500 | E44: 2190 | F44: =(E44-D44)/E44 -> 0.31506849 | G44: =D44*1.12 -> 1680 | H44: =D44*1.08 -> 1620 | I44: 1990 | J44: 1990 | K44: 1990 | L44: =(J44-D44)/J44 -> 0.24623116 | M44: =(K44-D44)/K44 -> 0.24623116 | N44: 1095 | O44: =(E44-I44)/E44 -> 0.091324201 | P44: =(E44-K44)/E44 -> 0.091324201 | Q44: https://cdn.shopify.com/s/files/1/0733/7318/8148/files/tomate.jpg?v=1762370196 | R44: 2190 | S44: =VLOOKUP(A44,'precios semana 2906'!A:B,2,0) -> 1500 | T44: =(S44/D44)-1 -> 0 | U44: =G44/I44-1 -> -0.15577889 | V44: =G44/K44-1 -> -0.15577889 | W44: =G44/J44-1 -> -0.15577889 | X44: =G44-K44 -> -310 | Y44: =(H44/K44)-1 -> -0.18592965 | Z44: =(H44/J44)-1 -> -0.18592965
A45: Tomate Cherry | B45: Kilo | C45: 0.25 | D45: 900 | E45: 1990 | F45: =(E45-D45)/E45 -> 0.54773869 | G45: =D45*1.12 -> 1008 | H45: =D45*1.08 -> 972 | I45: 1990 | J45: 1495 | K45: 1990 | L45: =(J45-D45)/J45 -> 0.39799331 | M45: =(K45-D45)/K45 -> 0.54773869 | N45: 2990 | O45: =(E45-I45)/E45 -> 0 | P45: =(E45-K45)/E45 -> 0 | Q45: https://cdn.shopify.com/s/files/1/0733/7318/8148/files/tomatecherry.jpg?v=1762370168 | R45: 1495 | S45: =VLOOKUP(A45,'precios semana 2906'!A:B,2,0) -> 900 | T45: =(S45/D45)-1 -> 0 | U45: =G45/I45-1 -> -0.49346734 | V45: =G45/K45-1 -> -0.49346734 | W45: =G45/J45-1 -> -0.32575251 | X45: =G45-K45 -> -982 | Y45: =(H45/K45)-1 -> -0.51155779 | Z45: =(H45/J45)-1 -> -0.34983278
A46: Tomate pomarola | B46: Kilo | C46: 0.5 | D46: 1100 | E46: 1495 | F46: =(E46-D46)/E46 -> 0.26421405 | G46: =D46*1.12 -> 1232 | H46: =D46*1.08 -> 1188 | I46: 1145 | J46: 1295 | K46: 1245 | L46: =(J46-D46)/J46 -> 0.15057915 | M46: =(K46-D46)/K46 -> 0.11646586 | N46: 845 | O46: =(E46-I46)/E46 -> 0.23411371 | P46: =(E46-K46)/E46 -> 0.16722408 | Q46: https://cdn.shopify.com/s/files/1/0733/7318/8148/files/tomate-pera.jpg?v=1762272039 | R46: 1495 | S46: =VLOOKUP(A46,'precios semana 2906'!A:B,2,0) -> 1100 | T46: =(S46/D46)-1 -> 0 | U46: =G46/I46-1 -> 0.075982533 | V46: =G46/K46-1 -> -0.010441767 | W46: =G46/J46-1 -> -0.048648649 | X46: =G46-K46 -> -13 | Y46: =(H46/K46)-1 -> -0.045783133 | Z46: =(H46/J46)-1 -> -0.082625483
A47: Zanahoria | B47: Kilo | C47: 1 | D47: 800 | E47: 1290 | F47: =(E47-D47)/E47 -> 0.37984496 | G47: =D47*1.12 -> 896 | H47: =D47*1.08 -> 864 | I47: 1290 | J47: 1290 | K47: 1190 | L47: =(J47-D47)/J47 -> 0.37984496 | M47: =(K47-D47)/K47 -> 0.32773109 | N47: 695 | O47: =(E47-I47)/E47 -> 0 | P47: =(E47-K47)/E47 -> 0.07751938 | Q47: https://cdn.shopify.com/s/files/1/0733/7318/8148/files/zanahoria-600x359.jpg?v=1762370132 | R47: 1390 | S47: =VLOOKUP(A47,'precios semana 2906'!A:B,2,0) -> 800 | T47: =(S47/D47)-1 -> 0 | U47: =G47/I47-1 -> -0.30542636 | V47: =G47/K47-1 -> -0.24705882 | W47: =G47/J47-1 -> -0.30542636 | X47: =G47-K47 -> -294 | Y47: =(H47/K47)-1 -> -0.27394958 | Z47: =(H47/J47)-1 -> -0.33023256
A48: Zapallo camote | B48: Corte | C48: 1 | D48: 1000 | E48: 1990 | F48: =(E48-D48)/E48 -> 0.49748744 | G48: =D48*1.12 -> 1120 | H48: =D48*1.08 -> 1080 | I48: 1990 | J48: 990 | K48: 2090 | L48: =(J48-D48)/J48 -> -0.01010101 | M48: =(K48-D48)/K48 -> 0.5215311 | N48: 2490 | O48: =(E48-I48)/E48 -> 0 | P48: =(E48-K48)/E48 -> -0.050251256 | Q48: https://cdn.shopify.com/s/files/1/0733/7318/8148/files/zapallocamote.jpg?v=1762370096 | R48: 1290 | S48: =VLOOKUP(A48,'precios semana 2906'!A:B,2,0) -> 1000 | T48: =(S48/D48)-1 -> 0 | U48: =G48/I48-1 -> -0.43718593 | V48: =G48/K48-1 -> -0.46411483 | W48: =G48/J48-1 -> 0.13131313 | X48: =G48-K48 -> -970 | Y48: =(H48/K48)-1 -> -0.48325359 | Z48: =(H48/J48)-1 -> 0.090909091
A49: Zapallo italiano | B49: Unidad | C49: 1 | D49: 600 | E49: 790 | F49: =(E49-D49)/E49 -> 0.24050633 | G49: =D49*1.12 -> 672 | H49: =D49*1.08 -> 648 | I49: 790 | J49: 790 | K49: 790 | L49: =(J49-D49)/J49 -> 0.24050633 | M49: =(K49-D49)/K49 -> 0.24050633 | N49: 790 | O49: =(E49-I49)/E49 -> 0 | P49: =(E49-K49)/E49 -> 0 | Q49: https://cdn.shopify.com/s/files/1/0733/7318/8148/files/images_1_98edaab3-dc56-49cd-b2bc-d0b9fd52c71c.jpg?v=1774713847 | R49: 790 | S49: =VLOOKUP(A49,'precios semana 2906'!A:B,2,0) -> 600 | T49: =(S49/D49)-1 -> 0 | U49: =G49/I49-1 -> -0.14936709 | V49: =G49/K49-1 -> -0.14936709 | W49: =G49/J49-1 -> -0.14936709 | X49: =G49-K49 -> -118 | Y49: =(H49/K49)-1 -> -0.17974684 | Z49: =(H49/J49)-1 -> -0.17974684
A50: Arandano | B50: Kilo | C50: 0.1 | D50: 1800 | E50: 3490 | F50: =(E50-D50)/E50 -> 0.48424069 | G50: =D50*1.12 -> 2016 | H50: =D50*1.08 -> 1944 | I50: 1364 | J50: 2792 | K50: 2490 | L50: =(J50-D50)/J50 -> 0.35530086 | M50: =(K50-D50)/K50 -> 0.27710843 | N50: 10490 | O50: =(E50-I50)/E50 -> 0.60916905 | P50: =(E50-K50)/E50 -> 0.28653295 | Q50: https://cdn.shopify.com/s/files/1/0733/7318/8148/files/membrillo.jpg?v=1770900939 | S50: =VLOOKUP(A50,'precios semana 2906'!A:B,2,0) -> 2000 | T50: =(S50/D50)-1 -> 0.11111111 | U50: =G50/I50-1 -> 0.47800587 | V50: =G50/K50-1 -> -0.19036145 | W50: =G50/J50-1 -> -0.27793696 | X50: =G50-K50 -> -474 | Y50: =(H50/K50)-1 -> -0.21927711 | Z50: =(H50/J50)-1 -> -0.30372493
A51: Frutillas | B51: Kilo | C51: 0.5 | D51: 1600 | E51: 4690 | F51: =(E51-D51)/E51 -> 0.65884861 | G51: =D51*1.12 -> 1792 | H51: =D51*1.08 -> 1728 | I51: 3190 | J51: 5317 | K51: 4317 | L51: =(J51-D51)/J51 -> 0.69907843 | M51: =(K51-D51)/K51 -> 0.62937225 | N51: 4690 | O51: =(E51-I51)/E51 -> 0.31982942 | P51: =(E51-K51)/E51 -> 0.079530917 | Q51: https://cdn.shopify.com/s/files/1/0733/7318/8148/files/frutilla_9ca7ca2a-6dcc-402a-97bc-24eea4405672.jpg?v=1762272265 | R51: 4690 | S51: =VLOOKUP(A51,'precios semana 2906'!A:B,2,0) -> 1600 | T51: =(S51/D51)-1 -> 0 | U51: =G51/I51-1 -> -0.43824451 | V51: =G51/K51-1 -> -0.58489692 | W51: =G51/J51-1 -> -0.66296784 | X51: =G51-K51 -> -2525 | Y51: =(H51/K51)-1 -> -0.59972203 | Z51: =(H51/J51)-1 -> -0.6750047
A52: Kiwi | B52: Kilo | C52: 0.5 | D52: 1000 | E52: 2095 | F52: =(E52-D52)/E52 -> 0.52267303 | G52: =D52*1.12 -> 1120 | H52: =D52*1.08 -> 1080 | I52: 2095 | J52: 1500 | K52: 2145 | L52: =(J52-D52)/J52 -> 0.33333333 | M52: =(K52-D52)/K52 -> 0.53379953 | N52: 2190 | O52: =(E52-I52)/E52 -> 0 | P52: =(E52-K52)/E52 -> -0.023866348 | Q52: https://cdn.shopify.com/s/files/1/0733/7318/8148/files/kiwi.jpg?v=1762372030 | S52: =VLOOKUP(A52,'precios semana 2906'!A:B,2,0) -> 1000 | T52: =(S52/D52)-1 -> 0 | U52: =G52/I52-1 -> -0.46539379 | V52: =G52/K52-1 -> -0.47785548 | W52: =G52/J52-1 -> -0.25333333 | X52: =G52-K52 -> -1025 | Y52: =(H52/K52)-1 -> -0.4965035 | Z52: =(H52/J52)-1 -> -0.28
A53: Limon | B53: Kilo | C53: 1 | D53: 700 | E53: 1950 | F53: =(E53-D53)/E53 -> 0.64102564 | G53: =D53*1.12 -> 784 | H53: =D53*1.08 -> 756 | I53: 1950 | J53: 1690 | K53: 2090 | L53: =(J53-D53)/J53 -> 0.58579882 | M53: =(K53-D53)/K53 -> 0.66507177 | N53: 995 | O53: =(E53-I53)/E53 -> 0 | P53: =(E53-K53)/E53 -> -0.071794872 | Q53: https://cdn.shopify.com/s/files/1/0733/7318/8148/files/limon.jpg?v=1762372971 | S53: =VLOOKUP(A53,'precios semana 2906'!A:B,2,0) -> 700 | T53: =(S53/D53)-1 -> 0 | U53: =G53/I53-1 -> -0.59794872 | V53: =G53/K53-1 -> -0.62488038 | W53: =G53/J53-1 -> -0.53609467 | X53: =G53-K53 -> -1306 | Y53: =(H53/K53)-1 -> -0.63827751 | Z53: =(H53/J53)-1 -> -0.55266272
A54: Limón sutil | B54: Kilo | C54: 0.5 | D54: 1500 | E54: 1990 | F54: =(E54-D54)/E54 -> 0.24623116 | G54: =D54*1.12 -> 1680 | H54: =D54*1.08 -> 1620 | I54: 1825 | J54: 1990 | K54: 1845 | L54: =(J54-D54)/J54 -> 0.24623116 | M54: =(K54-D54)/K54 -> 0.18699187 | N54: 1790 | O54: =(E54-I54)/E54 -> 0.082914573 | P54: =(E54-K54)/E54 -> 0.072864322 | Q54: https://cdn.shopify.com/s/files/1/0733/7318/8148/files/limonsutil.jpg?v=1762372937 | S54: =VLOOKUP(A54,'precios semana 2906'!A:B,2,0) -> 1300 | T54: =(S54/D54)-1 -> -0.13333333 | U54: =G54/I54-1 -> -0.079452055 | V54: =G54/K54-1 -> -0.089430894 | W54: =G54/J54-1 -> -0.15577889 | X54: =G54-K54 -> -165 | Y54: =(H54/K54)-1 -> -0.12195122 | Z54: =(H54/J54)-1 -> -0.18592965
A55: Limon de pica | B55: Kilo | C55: 0.5 | D55: 2100 | E55: 2490 | F55: =(E55-D55)/E55 -> 0.15662651 | G55: =D55*1.12 -> 2352 | H55: =D55*1.08 -> 2268 | I55: 2190 | J55: 2490 | K55: 2245 | L55: =(J55-D55)/J55 -> 0.15662651 | M55: =(K55-D55)/K55 -> 0.064587973 | O55: =(E55-I55)/E55 -> 0.12048193 | P55: =(E55-K55)/E55 -> 0.098393574 | Q55: https://cdn.shopify.com/s/files/1/0733/7318/8148/files/limonsutil.jpg?v=1762372937 | S55: =VLOOKUP(A55,'precios semana 2906'!A:B,2,0) -> 2000 | T55: =(S55/D55)-1 -> -0.047619048 | U55: =G55/I55-1 -> 0.073972603 | V55: =G55/K55-1 -> 0.04766147 | W55: =G55/J55-1 -> -0.055421687 | X55: =G55-K55 -> 107 | Y55: =(H55/K55)-1 -> 0.010244989 | Z55: =(H55/J55)-1 -> -0.089156627
A56: Mandarina | B56: Kilo | C56: 0.5 | D56: 1200 | E56: 1395 | F56: =(E56-D56)/E56 -> 0.13978495 | G56: =D56*1.12 -> 1344 | H56: =D56*1.08 -> 1296 | I56: 1245 | J56: 1345 | K56: 1395 | L56: =(J56-D56)/J56 -> 0.10780669 | M56: =(K56-D56)/K56 -> 0.13978495 | N56: 1445 | O56: =(E56-I56)/E56 -> 0.10752688 | P56: =(E56-K56)/E56 -> 0 | Q56: https://cdn.shopify.com/s/files/1/0733/7318/8148/files/mandarinesInt.webp?v=1780761611 | S56: =VLOOKUP(A56,'precios semana 2906'!A:B,2,0) -> 1200 | T56: =(S56/D56)-1 -> 0 | U56: =G56/I56-1 -> 0.079518072 | V56: =G56/K56-1 -> -0.03655914 | W56: =G56/J56-1 -> -0.00074349442 | X56: =G56-K56 -> -51 | Y56: =(H56/K56)-1 -> -0.070967742 | Z56: =(H56/J56)-1 -> -0.036431227
A57: Mango | B57: Unidad | C57: 1 | D57: 1300 | E57: 1990 | F57: =(E57-D57)/E57 -> 0.34673367 | G57: =D57*1.12 -> 1456 | H57: =D57*1.08 -> 1404 | I57: 1260 | J57: 2490 | K57: 1505 | L57: =(J57-D57)/J57 -> 0.47791165 | M57: =(K57-D57)/K57 -> 0.13621262 | N57: 2690 | O57: =(E57-I57)/E57 -> 0.36683417 | P57: =(E57-K57)/E57 -> 0.24371859 | Q57: https://cdn.shopify.com/s/files/1/0733/7318/8148/files/mango.jpg?v=1762372871 | R57: 2690 | S57: =VLOOKUP(A57,'precios semana 2906'!A:B,2,0) -> 1300 | T57: =(S57/D57)-1 -> 0 | U57: =G57/I57-1 -> 0.15555556 | V57: =G57/K57-1 -> -0.03255814 | W57: =G57/J57-1 -> -0.41526104 | X57: =G57-K57 -> -49 | Y57: =(H57/K57)-1 -> -0.067109635 | Z57: =(H57/J57)-1 -> -0.43614458
A58: Manzana fuji | B58: Kilo | C58: 1 | D58: 1750 | E58: 2590 | F58: =(E58-D58)/E58 -> 0.32432432 | G58: =D58*1.12 -> 1960 | H58: =D58*1.08 -> 1890 | I58: 1990 | J58: 2190 | K58: 2590 | L58: =(J58-D58)/J58 -> 0.20091324 | M58: =(K58-D58)/K58 -> 0.32432432 | N58: 1445 | O58: =(E58-I58)/E58 -> 0.23166023 | P58: =(E58-K58)/E58 -> 0 | Q58: https://cdn.shopify.com/s/files/1/0733/7318/8148/files/manzanafuji-600x600.jpg?v=1762372835 | S58: =VLOOKUP(A58,'precios semana 2906'!A:B,2,0) -> 1900 | T58: =(S58/D58)-1 -> 0.085714286 | U58: =G58/I58-1 -> -0.015075377 | V58: =G58/K58-1 -> -0.24324324 | W58: =G58/J58-1 -> -0.10502283 | X58: =G58-K58 -> -630 | Y58: =(H58/K58)-1 -> -0.27027027 | Z58: =(H58/J58)-1 -> -0.1369863
A59: Manzana verde | B59: Kilo | C59: 1 | D59: 1750 | E59: 2590 | F59: =(E59-D59)/E59 -> 0.32432432 | G59: =D59*1.12 -> 1960 | H59: =D59*1.08 -> 1890 | I59: 1990 | J59: 2190 | K59: 2590 | L59: =(J59-D59)/J59 -> 0.20091324 | M59: =(K59-D59)/K59 -> 0.32432432 | N59: 1445 | O59: =(E59-I59)/E59 -> 0.23166023 | P59: =(E59-K59)/E59 -> 0 | Q59: https://cdn.shopify.com/s/files/1/0733/7318/8148/files/manzanaverde.jpg?v=1762372779 | S59: =VLOOKUP(A59,'precios semana 2906'!A:B,2,0) -> 1900 | T59: =(S59/D59)-1 -> 0.085714286 | U59: =G59/I59-1 -> -0.015075377 | V59: =G59/K59-1 -> -0.24324324 | W59: =G59/J59-1 -> -0.10502283 | X59: =G59-K59 -> -630 | Y59: =(H59/K59)-1 -> -0.27027027 | Z59: =(H59/J59)-1 -> -0.1369863
A60: Manzana pink lady | B60: Kilo | C60: 1 | D60: 1750 | E60: 2590 | F60: =(E60-D60)/E60 -> 0.32432432 | G60: =D60*1.12 -> 1960 | H60: =D60*1.08 -> 1890 | I60: 1890 | J60: 2190 | K60: 2590 | L60: =(J60-D60)/J60 -> 0.20091324 | M60: =(K60-D60)/K60 -> 0.32432432 | N60: 1445 | O60: =(E60-I60)/E60 -> 0.27027027 | P60: =(E60-K60)/E60 -> 0 | Q60: https://cdn.shopify.com/s/files/1/0733/7318/8148/files/manzanapink.jpg?v=1762273338 | S60: =VLOOKUP(A60,'precios semana 2906'!A:B,2,0) -> 1900 | T60: =(S60/D60)-1 -> 0.085714286 | U60: =G60/I60-1 -> 0.037037037 | V60: =G60/K60-1 -> -0.24324324 | W60: =G60/J60-1 -> -0.10502283 | X60: =G60-K60 -> -630 | Y60: =(H60/K60)-1 -> -0.27027027 | Z60: =(H60/J60)-1 -> -0.1369863
A61: Mancaqui | B61: Kilo | C61: 0.5 | D61: 1000 | E61: 1390 | F61: =(E61-D61)/E61 -> 0.28057554 | G61: =D61*1.12 -> 1120 | H61: =D61*1.08 -> 1080 | I61: 1295 | J61: 1690 | L61: =(J61-D61)/J61 -> 0.40828402 | O61: =(E61-I61)/E61 -> 0.068345324 | P61: =(E61-K61)/E61 -> 1 | Q61: https://cdn.shopify.com/s/files/1/0733/7318/8148/files/caqui-fruta-1-xl-668x400x80xX_1.jpg?v=1770900746 | S61: =VLOOKUP(A61,'precios semana 2906'!A:B,2,0) -> Borrar/ fuera de temp. | T61: =(S61/D61)-1 -> #VALUE! | U61: =G61/I61-1 -> -0.13513514 | W61: =G61/J61-1 -> -0.33727811 | Y61: =(H61/K61)-1 -> #DIV/0! | Z61: =(H61/J61)-1 -> -0.36094675
A62: Naranjas | B62: Kilo | C62: 1 | D62: 1350 | E62: 2290 | F62: =(E62-D62)/E62 -> 0.41048035 | G62: =D62*1.12 -> 1512 | H62: =D62*1.08 -> 1458 | I62: 2790 | J62: 2290 | K62: 2890 | L62: =(J62-D62)/J62 -> 0.41048035 | M62: =(K62-D62)/K62 -> 0.53287197 | N62: 1445 | O62: =(E62-I62)/E62 -> -0.21834061 | P62: =(E62-K62)/E62 -> -0.26200873 | Q62: https://cdn.shopify.com/s/files/1/0733/7318/8148/files/naranja_6e3b5b89-6076-4161-8be6-af8ef573eb08.jpg?v=1762372259 | S62: =VLOOKUP(A62,'precios semana 2906'!A:B,2,0) -> 1350 | T62: =(S62/D62)-1 -> 0 | U62: =G62/I62-1 -> -0.45806452 | V62: =G62/K62-1 -> -0.47681661 | W62: =G62/J62-1 -> -0.33973799 | X62: =G62-K62 -> -1378 | Y62: =(H62/K62)-1 -> -0.49550173 | Z62: =(H62/J62)-1 -> -0.36331878
A63: Palta hass chilena | B63: Kilo | C63: 1 | D63: 5500 | E63: 6500 | F63: =(E63-D63)/E63 -> 0.15384615 | G63: =D63*1.12 -> 6160 | H63: =D63*1.08 -> 5940 | I63: 5990 | J63: 5990 | K63: 6490 | L63: =(J63-D63)/J63 -> 0.081803005 | M63: =(K63-D63)/K63 -> 0.15254237 | N63: 6490 | O63: =(E63-I63)/E63 -> 0.078461538 | P63: =(E63-K63)/E63 -> 0.0015384615 | Q63: https://cdn.shopify.com/s/files/1/0733/7318/8148/files/paltahass.png?v=1762372204 | S63: =VLOOKUP(A63,'precios semana 2906'!A:B,2,0) -> #N/A | T63: =(S63/D63)-1 -> #N/A | U63: =G63/I63-1 -> 0.028380634 | V63: =G63/K63-1 -> -0.050847458 | W63: =G63/J63-1 -> 0.028380634 | X63: =G63-K63 -> -330 | Y63: =(H63/K63)-1 -> -0.084745763 | Z63: =(H63/J63)-1 -> -0.0083472454
A64: Palta hass peruana | B64: Kilo | C64: 1 | D64: 4300 | E64: 5300 | F64: =(E64-D64)/E64 -> 0.18867925 | G64: =D64*1.12 -> 4816 | H64: =D64*1.08 -> 4644 | I64: 2857 | K64: 2890 | M64: =(K64-D64)/K64 -> -0.48788927 | N64: no hay | O64: =(E64-I64)/E64 -> 0.4609434 | P64: =(E64-K64)/E64 -> 0.45471698 | Q64: https://cdn.shopify.com/s/files/1/0733/7318/8148/files/Disenosintitulo_4.png?v=1780880764 | S64: =VLOOKUP(A64,'precios semana 2906'!A:B,2,0) -> 4000 | T64: =(S64/D64)-1 -> -0.069767442 | U64: =G64/I64-1 -> 0.68568428 | V64: =G64/K64-1 -> 0.66643599 | X64: =G64-K64 -> 1926 | Y64: =(H64/K64)-1 -> 0.60692042 | Z64: =(H64/J64)-1 -> #DIV/0!
A65: Pera | B65: Kilo | C65: 0.5 | D65: 1000 | E65: 2290 | F65: =(E65-D65)/E65 -> 0.56331878 | G65: =D65*1.12 -> 1120 | H65: =D65*1.08 -> 1080 | I65: 1075 | J65: 1145 | K65: 1095 | L65: =(J65-D65)/J65 -> 0.12663755 | M65: =(K65-D65)/K65 -> 0.086757991 | N65: 1345 | O65: =(E65-I65)/E65 -> 0.53056769 | P65: =(E65-K65)/E65 -> 0.52183406 | Q65: https://cdn.shopify.com/s/files/1/0733/7318/8148/files/pera.jpg?v=1762372159 | S65: =VLOOKUP(A65,'precios semana 2906'!A:B,2,0) -> 1800 | T65: =(S65/D65)-1 -> 0.8 | U65: =G65/I65-1 -> 0.041860465 | V65: =G65/K65-1 -> 0.02283105 | W65: =G65/J65-1 -> -0.021834061 | X65: =G65-K65 -> 25 | Y65: =(H65/K65)-1 -> -0.01369863 | Z65: =(H65/J65)-1 -> -0.056768559
A66: Pepinodulce | B66: Kilo | C66: 0.5 | D66: 1000 | E66: 1645 | F66: =(E66-D66)/E66 -> 0.39209726 | G66: =D66*1.12 -> 1120 | H66: =D66*1.08 -> 1080 | I66: 1645 | J66: 1245 | K66: 1745 | L66: =(J66-D66)/J66 -> 0.19678715 | M66: =(K66-D66)/K66 -> 0.4269341 | N66: 1695 | O66: =(E66-I66)/E66 -> 0 | P66: =(E66-K66)/E66 -> -0.060790274 | Q66: https://cdn.shopify.com/s/files/1/0733/7318/8148/files/pepinodulce.jpg?v=1762372072 | S66: =VLOOKUP(A66,'precios semana 2906'!A:B,2,0) -> 2000 | T66: =(S66/D66)-1 -> 1 | U66: =G66/I66-1 -> -0.31914894 | V66: =G66/K66-1 -> -0.35816619 | W66: =G66/J66-1 -> -0.10040161 | X66: =G66-K66 -> -625 | Y66: =(H66/K66)-1 -> -0.38108883 | Z66: =(H66/J66)-1 -> -0.13253012
A67: Piña caramelo | B67: Unidad | C67: 1 | D67: 2900 | E67: 3490 | F67: =(E67-D67)/E67 -> 0.16905444 | G67: =D67*1.12 -> 3248 | H67: =D67*1.08 -> 3132 | I67: 2590 | J67: 3490 | K67: 2690 | L67: =(J67-D67)/J67 -> 0.16905444 | M67: =(K67-D67)/K67 -> -0.078066914 | N67: 3990 | O67: =(E67-I67)/E67 -> 0.25787966 | P67: =(E67-K67)/E67 -> 0.22922636 | Q67: https://cdn.shopify.com/s/files/1/0733/7318/8148/files/Pina-un.png?v=1780761811 | S67: =VLOOKUP(A67,'precios semana 2906'!A:B,2,0) -> 3000 | T67: =(S67/D67)-1 -> 0.034482759 | U67: =G67/I67-1 -> 0.25405405 | V67: =G67/K67-1 -> 0.20743494 | W67: =G67/J67-1 -> -0.069340974 | X67: =G67-K67 -> 558 | Y67: =(H67/K67)-1 -> 0.16431227 | Z67: =(H67/J67)-1 -> -0.1025788
A68: Plátano | B68: Kilo | C68: 1 | D68: 1300 | E68: 1790 | F68: =(E68-D68)/E68 -> 0.27374302 | G68: =D68*1.12 -> 1456 | H68: =D68*1.08 -> 1404 | I68: 1450 | J68: 1990 | K68: 1590 | L68: =(J68-D68)/J68 -> 0.34673367 | M68: =(K68-D68)/K68 -> 0.18238994 | N68: 1990 | O68: =(E68-I68)/E68 -> 0.18994413 | P68: =(E68-K68)/E68 -> 0.11173184 | Q68: https://cdn.shopify.com/s/files/1/0733/7318/8148/files/platano.jpg?v=1762371982 | S68: =VLOOKUP(A68,'precios semana 2906'!A:B,2,0) -> 1400 | T68: =(S68/D68)-1 -> 0.076923077 | U68: =G68/I68-1 -> 0.004137931 | V68: =G68/K68-1 -> -0.08427673 | W68: =G68/J68-1 -> -0.26834171 | X68: =G68-K68 -> -134 | Y68: =(H68/K68)-1 -> -0.11698113 | Z68: =(H68/J68)-1 -> -0.29447236
A69: Pomelo | B69: Kilo | C69: 0.5 | D69: 900 | E69: 1075 | F69: =(E69-D69)/E69 -> 0.1627907 | G69: =D69*1.12 -> 1008 | H69: =D69*1.08 -> 972 | I69: 1075 | J69: 745 | K69: 965 | L69: =(J69-D69)/J69 -> -0.20805369 | M69: =(K69-D69)/K69 -> 0.067357513 | N69: 3190 | O69: =(E69-I69)/E69 -> 0 | P69: =(E69-K69)/E69 -> 0.10232558 | Q69: https://cdn.shopify.com/s/files/1/0733/7318/8148/files/Pomelo.jpg?v=1762371883 | R69: 1595 | S69: =VLOOKUP(A69,'precios semana 2906'!A:B,2,0) -> 900 | T69: =(S69/D69)-1 -> 0 | U69: =G69/I69-1 -> -0.062325581 | V69: =G69/K69-1 -> 0.044559585 | W69: =G69/J69-1 -> 0.35302013 | X69: =G69-K69 -> 43 | Y69: =(H69/K69)-1 -> 0.007253886 | Z69: =(H69/J69)-1 -> 0.30469799
A70: Tuna | B70: Kilo | C70: 0.5 | D70: 1800 | E70: 1995 | F70: =(E70-D70)/E70 -> 0.097744361 | G70: =D70*1.12 -> 2016 | H70: =D70*1.08 -> 1944 | I70: 1645 | J70: 1995 | K70: 1995 | L70: =(J70-D70)/J70 -> 0.097744361 | M70: =(K70-D70)/K70 -> 0.097744361 | O70: =(E70-I70)/E70 -> 0.1754386 | P70: =(E70-K70)/E70 -> 0 | Q70: https://cdn.shopify.com/s/files/1/0733/7318/8148/files/tuna.jpg?v=1762371838 | S70: =VLOOKUP(A70,'precios semana 2906'!A:B,2,0) -> 2000 | T70: =(S70/D70)-1 -> 0.11111111 | U70: =G70/I70-1 -> 0.22553191 | V70: =G70/K70-1 -> 0.010526316 | W70: =G70/J70-1 -> 0.010526316 | X70: =G70-K70 -> 21 | Y70: =(H70/K70)-1 -> -0.02556391 | Z70: =(H70/J70)-1 -> -0.02556391
A71: Uva roja | B71: Kilo | C71: 0.5 | D71: 900 | E71: 2245 | F71: =(E71-D71)/E71 -> 0.59910913 | G71: =D71*1.12 -> 1008 | H71: =D71*1.08 -> 972 | J71: 4490 | K71: 2245 | L71: =(J71-D71)/J71 -> 0.79955457 | M71: =(K71-D71)/K71 -> 0.59910913 | P71: =(E71-K71)/E71 -> 0 | Q71: https://cdn.shopify.com/s/files/1/0733/7318/8148/files/grape-fruit-table-grapes-2612718.jpg?v=1770901113 | S71: =VLOOKUP(A71,'precios semana 2906'!A:B,2,0) -> 1400 | T71: =(S71/D71)-1 -> 0.55555556 | U71: =G71/I71-1 -> #DIV/0! | V71: =G71/K71-1 -> -0.55100223 | W71: =G71/J71-1 -> -0.77550111 | X71: =G71-K71 -> -1237 | Y71: =(H71/K71)-1 -> -0.56703786 | Z71: =(H71/J71)-1 -> -0.78351893
A72: Uva verde | B72: Kilo | C72: 0.5 | D72: 2000 | E72: 3495 | F72: =(E72-D72)/E72 -> 0.42775393 | G72: =D72*1.12 -> 2240 | H72: =D72*1.08 -> 2160 | I72: 3884 | J72: 4490 | K72: 3495 | L72: =(J72-D72)/J72 -> 0.5545657 | M72: =(K72-D72)/K72 -> 0.42775393 | O72: =(E72-I72)/E72 -> -0.11130186 | P72: =(E72-K72)/E72 -> 0 | Q72: https://cdn.shopify.com/s/files/1/0733/7318/8148/files/uva_verde-2_3e8a8775-5689-43f3-8bc9-6602340551c4.png?v=1770901178 | S72: =VLOOKUP(A72,'precios semana 2906'!A:B,2,0) -> 2000 | T72: =(S72/D72)-1 -> 0 | U72: =G72/I72-1 -> -0.42327497 | V72: =G72/K72-1 -> -0.35908441 | W72: =G72/J72-1 -> -0.50111359 | X72: =G72-K72 -> -1255 | Y72: =(H72/K72)-1 -> -0.38197425 | Z72: =(H72/J72)-1 -> -0.51893096
A73: Almendras | B73: Kilo | C73: 0.1 | D73: 1900 | E73: 2200 | F73: =(E73-D73)/E73 -> 0.13636364 | G73: =D73*1.12 -> 2128 | H73: =D73*1.08 -> 2052 | I73: =14700*0.1 -> 1470 | J73: 1699 | K73: =15414*0.1 -> 1541.4 | L73: =(J73-D73)/J73 -> -0.11830489 | M73: =(K73-D73)/K73 -> -0.23264565 | N73: =7990/5 -> 1598 | O73: =(E73-I73)/E73 -> 0.33181818 | P73: =(E73-K73)/E73 -> 0.29936364 | Q73: https://cdn.shopify.com/s/files/1/0733/7318/8148/files/almendras_jpg.jpg?v=1762365216 | S73: =VLOOKUP(A73,'precios semana 2906'!A:B,2,0) -> 1900 | T73: =(S73/D73)-1 -> 0 | U73: =G73/I73-1 -> 0.44761905 | V73: =G73/K73-1 -> 0.38056312 | W73: =G73/J73-1 -> 0.25250147 | X73: =G73-K73 -> 586.6 | Y73: =(H73/K73)-1 -> 0.3312573 | Z73: =(H73/J73)-1 -> 0.20776928
A74: Almendras con chocolate | B74: Kilo | C74: 0.1 | D74: 2200 | E74: 3990 | F74: =(E74-D74)/E74 -> 0.44862155 | G74: =D74*1.12 -> 2464 | H74: =D74*1.08 -> 2376 | J74: 3645 | L74: =(J74-D74)/J74 -> 0.39643347 | O74: =(E74-I74)/E74 -> 1 | P74: =(E74-K74)/E74 -> 1 | Q74: https://cdn.shopify.com/s/files/1/0733/7318/8148/files/almendraschocolate_jpg.jpg?v=1762365179 | S74: =VLOOKUP(A74,'precios semana 2906'!A:B,2,0) -> 2200 | T74: =(S74/D74)-1 -> 0 | U74: =G74/I74-1 -> #DIV/0! | V74: =G74/K74-1 -> #DIV/0! | W74: =G74/J74-1 -> -0.32400549 | Y74: =(H74/K74)-1 -> #DIV/0! | Z74: =(H74/J74)-1 -> -0.34814815
A75: Aloe vera | B75: Kilo | C75: 0.1 | D75: 2150 | G75: =D75*1.12 -> 2408 | H75: =D75*1.08 -> 2322 | Q75: https://ibb.co/ycgY92GC | S75: =VLOOKUP(A75,'precios semana 2906'!A:B,2,0) -> 2150 | T75: =(S75/D75)-1 -> 0 | U75: =G75/I75-1 -> #DIV/0! | V75: =G75/K75-1 -> #DIV/0! | Y75: =(H75/K75)-1 -> #DIV/0! | Z75: =(H75/J75)-1 -> #DIV/0!
A76: Avellanas europea | B76: Kilo | C76: 0.1 | D76: 2300 | E76: 2990 | F76: =(E76-D76)/E76 -> 0.23076923 | G76: =D76*1.12 -> 2576 | H76: =D76*1.08 -> 2484 | J76: 2995 | K76: 2690 | L76: =(J76-D76)/J76 -> 0.23205342 | M76: =(K76-D76)/K76 -> 0.14498141 | P76: =(E76-K76)/E76 -> 0.10033445 | Q76: https://cdn.shopify.com/s/files/1/0733/7318/8148/files/5-avellana-europea3011.jpg?v=1762365142 | S76: =VLOOKUP(A76,'precios semana 2906'!A:B,2,0) -> 2300 | T76: =(S76/D76)-1 -> 0 | U76: =G76/I76-1 -> #DIV/0! | V76: =G76/K76-1 -> -0.042379182 | W76: =G76/J76-1 -> -0.13989983 | X76: =G76-K76 -> -114 | Y76: =(H76/K76)-1 -> -0.076579926 | Z76: =(H76/J76)-1 -> -0.1706177
A77: Castañas de caju | B77: Kilo | C77: 0.1 | D77: 1200 | E77: 1490 | F77: =(E77-D77)/E77 -> 0.19463087 | G77: =D77*1.12 -> 1344 | H77: =D77*1.08 -> 1296 | I77: =18225*0.1 -> 1822.5 | J77: 2995 | K77: =24271*0.1 -> 2427.1 | L77: =(J77-D77)/J77 -> 0.59933222 | M77: =(K77-D77)/K77 -> 0.50558279 | N77: =12990/5 -> 2598 | O77: =(E77-I77)/E77 -> -0.22315436 | P77: =(E77-K77)/E77 -> -0.62892617 | Q77: https://cdn.shopify.com/s/files/1/0733/7318/8148/files/castanascaju_jpg.jpg?v=1762271831 | S77: =VLOOKUP(A77,'precios semana 2906'!A:B,2,0) -> 1200 | T77: =(S77/D77)-1 -> 0 | U77: =G77/I77-1 -> -0.26255144 | V77: =G77/K77-1 -> -0.44625273 | W77: =G77/J77-1 -> -0.55125209 | X77: =G77-K77 -> -1083.1 | Y77: =(H77/K77)-1 -> -0.46602942 | Z77: =(H77/J77)-1 -> -0.5672788
A78: Chips de banana | B78: Kilo | C78: 0.1 | D78: 750 | E78: 1490 | F78: =(E78-D78)/E78 -> 0.4966443 | G78: =D78*1.12 -> 840 | H78: =D78*1.08 -> 810 | I78: =9735*0.1 -> 973.5 | J78: 1490 | K78: =9900*0.1 -> 990 | L78: =(J78-D78)/J78 -> 0.4966443 | M78: =(K78-D78)/K78 -> 0.24242424 | N78: No hay | O78: =(E78-I78)/E78 -> 0.3466443 | P78: =(E78-K78)/E78 -> 0.33557047 | Q78: https://cdn.shopify.com/s/files/1/0733/7318/8148/files/chipsbanana_jpg.jpg?v=1762365247 | S78: =VLOOKUP(A78,'precios semana 2906'!A:B,2,0) -> 750 | T78: =(S78/D78)-1 -> 0 | U78: =G78/I78-1 -> -0.13713405 | V78: =G78/K78-1 -> -0.15151515 | W78: =G78/J78-1 -> -0.43624161 | X78: =G78-K78 -> -150 | Y78: =(H78/K78)-1 -> -0.18181818 | Z78: =(H78/J78)-1 -> -0.45637584
A79: Ciruela deshidratada | B79: Kilo | C79: 0.1 | D79: 800 | E79: 1590 | F79: =(E79-D79)/E79 -> 0.49685535 | G79: =D79*1.12 -> 896 | H79: =D79*1.08 -> 864 | I79: =14166*0.1 -> 1416.6 | J79: 1596 | K79: =9967*0.1 -> 996.7 | L79: =(J79-D79)/J79 -> 0.49874687 | M79: =(K79-D79)/K79 -> 0.19735126 | N79: =5990/5 -> 1198 | O79: =(E79-I79)/E79 -> 0.1090566 | P79: =(E79-K79)/E79 -> 0.37314465 | Q79: https://cdn.shopify.com/s/files/1/0733/7318/8148/files/cirueladeshidratada.jpg-600x503.jpg?v=1762365715 | S79: =VLOOKUP(A79,'precios semana 2906'!A:B,2,0) -> 800 | T79: =(S79/D79)-1 -> 0 | U79: =G79/I79-1 -> -0.36749965 | V79: =G79/K79-1 -> -0.10103341 | W79: =G79/J79-1 -> -0.43859649 | X79: =G79-K79 -> -100.7 | Y79: =(H79/K79)-1 -> -0.13313936 | Z79: =(H79/J79)-1 -> -0.45864662
A80: Coco en cubos | B80: Kilo | C80: 0.1 | D80: 1500 | E80: 2550 | F80: =(E80-D80)/E80 -> 0.41176471 | G80: =D80*1.12 -> 1680 | H80: =D80*1.08 -> 1620 | Q80: https://ibb.co/Tx0NwCNN | S80: =VLOOKUP(A80,'precios semana 2906'!A:B,2,0) -> 1500 | T80: =(S80/D80)-1 -> 0 | U80: =G80/I80-1 -> #DIV/0! | V80: =G80/K80-1 -> #DIV/0! | Y80: =(H80/K80)-1 -> #DIV/0! | Z80: =(H80/J80)-1 -> #DIV/0!
A81: Coco laminado | B81: Kilo | C81: 0.01 | D81: 1500 | E81: 2550 | F81: =(E81-D81)/E81 -> 0.41176471 | G81: =D81*1.12 -> 1680 | H81: =D81*1.08 -> 1620 | J81: 2550 | L81: =(J81-D81)/J81 -> 0.41176471 | Q81: https://cdn.shopify.com/s/files/1/0733/7318/8148/files/cocolaminado_jpg.jpg?v=1770819410 | S81: =VLOOKUP(A81,'precios semana 2906'!A:B,2,0) -> 1500 | T81: =(S81/D81)-1 -> 0 | U81: =G81/I81-1 -> #DIV/0! | V81: =G81/K81-1 -> #DIV/0! | W81: =G81/J81-1 -> -0.34117647 | Y81: =(H81/K81)-1 -> #DIV/0! | Z81: =(H81/J81)-1 -> -0.36470588
A82: Coco rallado | B82: Kilo | C82: 0.1 | D82: 850 | E82: 1990 | F82: =(E82-D82)/E82 -> 0.57286432 | G82: =D82*1.12 -> 952 | H82: =D82*1.08 -> 918 | I82: 1790 | J82: 1990 | K82: 1920 | L82: =(J82-D82)/J82 -> 0.57286432 | M82: =(K82-D82)/K82 -> 0.55729167 | N82: =2999/2 -> 1499.5 | O82: =(E82-I82)/E82 -> 0.10050251 | P82: =(E82-K82)/E82 -> 0.035175879 | Q82: https://cdn.shopify.com/s/files/1/0733/7318/8148/files/cocorallado.jpg?v=1770819461 | S82: =VLOOKUP(A82,'precios semana 2906'!A:B,2,0) -> 850 | T82: =(S82/D82)-1 -> 0 | U82: =G82/I82-1 -> -0.46815642 | V82: =G82/K82-1 -> -0.50416667 | W82: =G82/J82-1 -> -0.52160804 | X82: =G82-K82 -> -968 | Y82: =(H82/K82)-1 -> -0.521875 | Z82: =(H82/J82)-1 -> -0.53869347
A83: Cranberries | B83: Kilo | C83: 0.1 | D83: 900 | E83: 1390 | F83: =(E83-D83)/E83 -> 0.35251799 | G83: =D83*1.12 -> 1008 | H83: =D83*1.08 -> 972 | I83: =11475*0.1 -> 1147.5 | K83: 1316 | O83: =(E83-I83)/E83 -> 0.17446043 | Q83: https://cdn.shopify.com/s/files/1/0733/7318/8148/files/cramberries_jpg.jpg?v=1762365110 | S83: =VLOOKUP(A83,'precios semana 2906'!A:B,2,0) -> #N/A | T83: =(S83/D83)-1 -> #N/A | U83: =G83/I83-1 -> -0.12156863 | V83: =G83/K83-1 -> -0.23404255 | Y83: =(H83/K83)-1 -> -0.26139818 | Z83: =(H83/J83)-1 -> #DIV/0!
A84: Dátiles | B84: Kilo | C84: 0.01 | D84: 600 | E84: 1245 | F84: =(E84-D84)/E84 -> 0.51807229 | G84: =D84*1.12 -> 672 | H84: =D84*1.08 -> 648 | J84: 1245 | L84: =(J84-D84)/J84 -> 0.51807229 | Q84: https://cdn.shopify.com/s/files/1/0733/7318/8148/files/datiles_jpg.jpg?v=1762365547 | S84: =VLOOKUP(A84,'precios semana 2906'!A:B,2,0) -> 600 | T84: =(S84/D84)-1 -> 0 | U84: =G84/I84-1 -> #DIV/0! | V84: =G84/K84-1 -> #DIV/0! | W84: =G84/J84-1 -> -0.46024096 | Y84: =(H84/K84)-1 -> #DIV/0! | Z84: =(H84/J84)-1 -> -0.47951807
A85: Flor de hibiscos | B85: Kilo | C85: 0.1 | D85: 1850 | E85: 3990 | F85: =(E85-D85)/E85 -> 0.53634085 | G85: =D85*1.12 -> 2072 | H85: =D85*1.08 -> 1998 | J85: 6980 | L85: =(J85-D85)/J85 -> 0.73495702 | Q85: https://cdn.shopify.com/s/files/1/0733/7318/8148/files/florhibiscos_jpg.jpg?v=1762365517 | S85: =VLOOKUP(A85,'precios semana 2906'!A:B,2,0) -> 1850 | T85: =(S85/D85)-1 -> 0 | U85: =G85/I85-1 -> #DIV/0! | V85: =G85/K85-1 -> #DIV/0! | W85: =G85/J85-1 -> -0.70315186 | Y85: =(H85/K85)-1 -> #DIV/0! | Z85: =(H85/J85)-1 -> -0.71375358
A86: Goji | B86: Kilo | C86: 0.1 | D86: 1700 | E86: 2750 | F86: =(E86-D86)/E86 -> 0.38181818 | G86: =D86*1.12 -> 1904 | H86: =D86*1.08 -> 1836 | Q86: https://cdn.shopify.com/s/files/1/0733/7318/8148/files/goji.jpg-600x399.jpg?v=1762365073 | S86: =VLOOKUP(A86,'precios semana 2906'!A:B,2,0) -> 1700 | T86: =(S86/D86)-1 -> 0 | U86: =G86/I86-1 -> #DIV/0! | V86: =G86/K86-1 -> #DIV/0! | Y86: =(H86/K86)-1 -> #DIV/0! | Z86: =(H86/J86)-1 -> #DIV/0!
A87: Huesillo grande | B87: Kilo | C87: 0.25 | D87: 2550 | E87: No hay | G87: =D87*1.12 -> 2856 | H87: =D87*1.08 -> 2754 | K87: 3329.25 | M87: =(K87-D87)/K87 -> 0.23406173 | Q87: https://cdn.shopify.com/s/files/1/0733/7318/8148/files/huesillomediano_jpg.jpg?v=1762365483 | S87: =VLOOKUP(A87,'precios semana 2906'!A:B,2,0) -> 2550 | T87: =(S87/D87)-1 -> 0 | U87: =G87/I87-1 -> #DIV/0! | V87: =G87/K87-1 -> -0.14214913 | X87: =G87-K87 -> -473.25 | Y87: =(H87/K87)-1 -> -0.17278666 | Z87: =(H87/J87)-1 -> #DIV/0!
A88: Kiwi deshidratado | B88: Kilo | C88: 0.1 | D88: 1450 | E88: No hay | G88: =D88*1.12 -> 1624 | H88: =D88*1.08 -> 1566 | Q88: https://cdn.shopify.com/s/files/1/0733/7318/8148/files/kiwideshidratado_jpg.jpg?v=1762365454 | S88: =VLOOKUP(A88,'precios semana 2906'!A:B,2,0) -> 1450 | T88: =(S88/D88)-1 -> 0 | U88: =G88/I88-1 -> #DIV/0! | V88: =G88/K88-1 -> #DIV/0! | Y88: =(H88/K88)-1 -> #DIV/0! | Z88: =(H88/J88)-1 -> #DIV/0!
A89: Linaza | B89: Kilo | C89: 0.1 | D89: 300 | E89: 690 | F89: =(E89-D89)/E89 -> 0.56521739 | G89: =D89*1.12 -> 336 | H89: =D89*1.08 -> 324 | I89: 512.4 | J89: 716 | K89: 897.5 | L89: =(J89-D89)/J89 -> 0.58100559 | M89: =(K89-D89)/K89 -> 0.66573816 | N89: =2790/5 -> 558 | O89: =(E89-I89)/E89 -> 0.2573913 | P89: =(E89-K89)/E89 -> -0.30072464 | Q89: https://cdn.shopify.com/s/files/1/0733/7318/8148/files/linaza_jpg.jpg?v=1762365040 | S89: =VLOOKUP(A89,'precios semana 2906'!A:B,2,0) -> 300 | T89: =(S89/D89)-1 -> 0 | U89: =G89/I89-1 -> -0.3442623 | V89: =G89/K89-1 -> -0.62562674 | W89: =G89/J89-1 -> -0.53072626 | X89: =G89-K89 -> -561.5 | Y89: =(H89/K89)-1 -> -0.63899721 | Z89: =(H89/J89)-1 -> -0.54748603
A90: Maíz curagua | B90: Kilo | C90: 0.5 | D90: 780 | E90: No hay | G90: =D90*1.12 -> 873.6 | H90: =D90*1.08 -> 842.4 | I90: 1050 | K90: 2230 | M90: =(K90-D90)/K90 -> 0.65022422 | N90: 1190 | Q90: https://cdn.shopify.com/s/files/1/0733/7318/8148/files/maizcuragua_jpg.jpg?v=1762365004 | S90: =VLOOKUP(A90,'precios semana 2906'!A:B,2,0) -> 780 | T90: =(S90/D90)-1 -> 0 | U90: =G90/I90-1 -> -0.168 | V90: =G90/K90-1 -> -0.60825112 | X90: =G90-K90 -> -1356.4 | Y90: =(H90/K90)-1 -> -0.62224215 | Z90: =(H90/J90)-1 -> #DIV/0!
A91: Mango deshidratado | B91: Kilo | C91: 0.1 | D91: 1430 | E91: No hay | G91: =D91*1.12 -> 1601.6 | H91: =D91*1.08 -> 1544.4 | Q91: https://cdn.shopify.com/s/files/1/0733/7318/8148/files/mangodeshidratado_jpg.png?v=1762365419 | S91: =VLOOKUP(A91,'precios semana 2906'!A:B,2,0) -> 1430 | T91: =(S91/D91)-1 -> 0 | U91: =G91/I91-1 -> #DIV/0! | V91: =G91/K91-1 -> #DIV/0! | Y91: =(H91/K91)-1 -> #DIV/0! | Z91: =(H91/J91)-1 -> #DIV/0!
A92: Maní chocolate | B92: Kilo | C92: 0.1 | D92: 660 | E92: 3490 | F92: =(E92-D92)/E92 -> 0.81088825 | G92: =D92*1.12 -> 739.2 | H92: =D92*1.08 -> 712.8 | J92: 3495 | L92: =(J92-D92)/J92 -> 0.8111588 | Q92: https://cdn.shopify.com/s/files/1/0733/7318/8148/files/manichocolate.jpg-600x400.jpg?v=1762355468 | S92: =VLOOKUP(A92,'precios semana 2906'!A:B,2,0) -> 660 | T92: =(S92/D92)-1 -> 0 | U92: =G92/I92-1 -> #DIV/0! | V92: =G92/K92-1 -> #DIV/0! | W92: =G92/J92-1 -> -0.78849785 | Y92: =(H92/K92)-1 -> #DIV/0! | Z92: =(H92/J92)-1 -> -0.7960515
A93: Mani con sal | B93: Kilo | C93: 0.1 | D93: 330 | E93: 750 | F93: =(E93-D93)/E93 -> 0.56 | G93: =D93*1.12 -> 369.6 | H93: =D93*1.08 -> 356.4 | I93: 666.7 | J93: 756 | K93: 635 | L93: =(J93-D93)/J93 -> 0.56349206 | M93: =(K93-D93)/K93 -> 0.48031496 | N93: =2990/5 -> 598 | O93: =(E93-I93)/E93 -> 0.11106667 | P93: =(E93-K93)/E93 -> 0.15333333 | Q93: https://cdn.shopify.com/s/files/1/0733/7318/8148/files/manisal_jpg_41282ef1-8b71-4224-b828-4b944d2fcd6b.jpg?v=1762355433 | S93: =VLOOKUP(A93,'precios semana 2906'!A:B,2,0) -> 330 | T93: =(S93/D93)-1 -> 0 | U93: =G93/I93-1 -> -0.44562772 | V93: =G93/K93-1 -> -0.41795276 | W93: =G93/J93-1 -> -0.51111111 | X93: =G93-K93 -> -265.4 | Y93: =(H93/K93)-1 -> -0.43874016 | Z93: =(H93/J93)-1 -> -0.52857143
A94: Maní confitado | B94: Kilo | C94: 0.1 | D94: 520 | E94: 830 | F94: =(E94-D94)/E94 -> 0.37349398 | G94: =D94*1.12 -> 582.4 | H94: =D94*1.08 -> 561.6 | I94: 993.3 | J94: 823 | K94: 890 | L94: =(J94-D94)/J94 -> 0.36816525 | M94: =(K94-D94)/K94 -> 0.41573034 | O94: =(E94-I94)/E94 -> -0.19674699 | P94: =(E94-K94)/E94 -> -0.072289157 | Q94: https://cdn.shopify.com/s/files/1/0733/7318/8148/files/maniconfitado.jpg-600x600.jpg?v=1762355380 | S94: =VLOOKUP(A94,'precios semana 2906'!A:B,2,0) -> 520 | T94: =(S94/D94)-1 -> 0 | U94: =G94/I94-1 -> -0.4136716 | V94: =G94/K94-1 -> -0.34561798 | W94: =G94/J94-1 -> -0.29234508 | X94: =G94-K94 -> -307.6 | Y94: =(H94/K94)-1 -> -0.36898876 | Z94: =(H94/J94)-1 -> -0.31761847
A95: Maní japonés natural | B95: Kilo | C95: 0.1 | D95: 580 | E95: 1980 | F95: =(E95-D95)/E95 -> 0.70707071 | G95: =D95*1.12 -> 649.6 | H95: =D95*1.08 -> 626.4 | I95: 975 | J95: 1972 | K95: 745 | L95: =(J95-D95)/J95 -> 0.70588235 | M95: =(K95-D95)/K95 -> 0.22147651 | N95: =5990/5 -> 1198 | O95: =(E95-I95)/E95 -> 0.50757576 | P95: =(E95-K95)/E95 -> 0.62373737 | Q95: https://cdn.shopify.com/s/files/1/0733/7318/8148/files/maninatural_jpg.jpg?v=1762355303 | S95: =VLOOKUP(A95,'precios semana 2906'!A:B,2,0) -> 580 | T95: =(S95/D95)-1 -> 0 | U95: =G95/I95-1 -> -0.33374359 | V95: =G95/K95-1 -> -0.12805369 | W95: =G95/J95-1 -> -0.67058824 | X95: =G95-K95 -> -95.4 | Y95: =(H95/K95)-1 -> -0.15919463 | Z95: =(H95/J95)-1 -> -0.68235294
A96: Maní Japonés picante | B96: Kilo | C96: 0.1 | D96: 580 | E96: 1980 | F96: =(E96-D96)/E96 -> 0.70707071 | G96: =D96*1.12 -> 649.6 | H96: =D96*1.08 -> 626.4 | I96: =11162*0.1 -> 1116.2 | J96: 1972 | K96: =11800*0.1 -> 1180 | L96: =(J96-D96)/J96 -> 0.70588235 | M96: =(K96-D96)/K96 -> 0.50847458 | O96: =(E96-I96)/E96 -> 0.43626263 | P96: =(E96-K96)/E96 -> 0.4040404 | Q96: https://cdn.shopify.com/s/files/1/0733/7318/8148/files/manipicante_jpg.jpg?v=1762355268 | S96: =VLOOKUP(A96,'precios semana 2906'!A:B,2,0) -> 580 | T96: =(S96/D96)-1 -> 0 | U96: =G96/I96-1 -> -0.41802544 | V96: =G96/K96-1 -> -0.44949153 | W96: =G96/J96-1 -> -0.67058824 | X96: =G96-K96 -> -530.4 | Y96: =(H96/K96)-1 -> -0.46915254 | Z96: =(H96/J96)-1 -> -0.68235294
A97: Maní sin sal | B97: Kilo | C97: 0.1 | D97: 330 | E97: 750 | F97: =(E97-D97)/E97 -> 0.56 | G97: =D97*1.12 -> 369.6 | H97: =D97*1.08 -> 356.4 | I97: 707.1 | J97: 756 | K97: 779 | L97: =(J97-D97)/J97 -> 0.56349206 | M97: =(K97-D97)/K97 -> 0.57637997 | N97: =2990/5 -> 598 | O97: =(E97-I97)/E97 -> 0.0572 | P97: =(E97-K97)/E97 -> -0.038666667 | Q97: https://cdn.shopify.com/s/files/1/0733/7318/8148/files/manisal_jpg.jpg?v=1762355236 | S97: =VLOOKUP(A97,'precios semana 2906'!A:B,2,0) -> 330 | T97: =(S97/D97)-1 -> 0 | U97: =G97/I97-1 -> -0.47730165 | V97: =G97/K97-1 -> -0.52554557 | W97: =G97/J97-1 -> -0.51111111 | X97: =G97-K97 -> -409.4 | Y97: =(H97/K97)-1 -> -0.54249037 | Z97: =(H97/J97)-1 -> -0.52857143
A98: Manzana deshidratada | B98: Kilo | C98: 0.1 | D98: 1020 | E98: No hay | G98: =D98*1.12 -> 1142.4 | H98: =D98*1.08 -> 1101.6 | K98: =16300*0.1 -> 1630 | M98: =(K98-D98)/K98 -> 0.37423313 | Q98: https://cdn.shopify.com/s/files/1/0733/7318/8148/files/manzanadeshidratada_jpg.jpg?v=1762365347 | S98: =VLOOKUP(A98,'precios semana 2906'!A:B,2,0) -> 1020 | T98: =(S98/D98)-1 -> 0 | U98: =G98/I98-1 -> #DIV/0! | V98: =G98/K98-1 -> -0.2991411 | X98: =G98-K98 -> -487.6 | Y98: =(H98/K98)-1 -> -0.32417178 | Z98: =(H98/J98)-1 -> #DIV/0!
A99: Nueces | B99: Kilo | C99: 0.1 | D99: 1580 | E99: 2100 | F99: =(E99-D99)/E99 -> 0.24761905 | G99: =D99*1.12 -> 1769.6 | H99: =D99*1.08 -> 1706.4 | I99: =19414*0.1 -> 1941.4 | J99: 2080 | K99: =14986*0.1 -> 1498.6 | L99: =(J99-D99)/J99 -> 0.24038462 | M99: =(K99-D99)/K99 -> -0.054317363 | N99: =4990/2.5 -> 1996 | O99: =(E99-I99)/E99 -> 0.07552381 | P99: =(E99-K99)/E99 -> 0.28638095 | Q99: https://cdn.shopify.com/s/files/1/0733/7318/8148/files/nuez_jpg_94116685-22eb-4355-bdab-95e8df89c813.jpg?v=1762355019 | S99: =VLOOKUP(A99,'precios semana 2906'!A:B,2,0) -> 1580 | T99: =(S99/D99)-1 -> 0 | U99: =G99/I99-1 -> -0.08849284 | V99: =G99/K99-1 -> 0.18083545 | W99: =G99/J99-1 -> -0.14923077 | X99: =G99-K99 -> 271 | Y99: =(H99/K99)-1 -> 0.13866275 | Z99: =(H99/J99)-1 -> -0.17961538
A100: Papaya deshidratada | B100: Kilo | C100: 0.1 | D100: 960 | E100: No hay | G100: =D100*1.12 -> 1075.2 | H100: =D100*1.08 -> 1036.8 | Q100: https://cdn.shopify.com/s/files/1/0733/7318/8148/files/papayadeshidratada_jpg.jpg?v=1762365310 | S100: =VLOOKUP(A100,'precios semana 2906'!A:B,2,0) -> 960 | T100: =(S100/D100)-1 -> 0 | U100: =G100/I100-1 -> #DIV/0! | V100: =G100/K100-1 -> #DIV/0! | Y100: =(H100/K100)-1 -> #DIV/0! | Z100: =(H100/J100)-1 -> #DIV/0!
...

Sheet Números
B2: Monto pedido mínimo
B3: Productos | C3: 15000 | D3: 15000 | E3: 40000
B4: Delivery bruto | C4: 2990 | D4: 3990 | E4: 0
A5: 0 | B5: Service Fee | C5: =C3*$A5 -> 0 | D5: =D3*$A5 -> 0 | E5: =E3*$A5 -> 0
B6: GOV Bruto | C6: =C3+C4+C5 -> 17990 | D6: =D3+D4+D5 -> 18990 | E6: =E3+E4+E5 -> 40000
B7: GOV Neto | C7: =C6/1.19 -> 15117.647 | D7: =D6/1.19 -> 15957.983 | E7: =E6/1.19 -> 33613.445
B9: Costos directos netos | C9: =SUM(C10:C15)*-1 -> -11998.876 | D9: =SUM(D10:D15)*-1 -> -12018.876 | E9: =SUM(E10:E15)*-1 -> -26504.202
A10: 0.39 | B10: Productos | C10: =C3/1.19*(1-$A10) -> 7689.0756 | D10: =D3/1.19*(1-$A10) -> 7689.0756 | E10: =E3/1.19*(1-$A10) -> 20504.202
B11: Picking | C11: 800 | D11: 800 | E11: 800
A12: 0 | B12: Packing | C12: 0 | D12: 0 | E12: 0
B13: Delivery | C13: 2400 | D13: 2400 | E13: 2400
A14: 0.05 | B14: Cashback (5%) | C14: =C3*$A14 -> 750 | D14: =D3*5% -> 750 | E14: =E3*5% -> 2000
A15: 0.02 | B15: Pasarela de pagos (2%) | C15: =C6*$A15 -> 359.8 | D15: =D6*2% -> 379.8 | E15: =E6*2% -> 800
B17: Margen neto $ | C17: =C7+C9 -> 3118.7714 | D17: =D7+D9 -> 3939.1076 | E17: =E7+E9 -> 7109.2437
B18: Margen neto % | C18: =C17/C3 -> 0.2079181 | D18: =D17/D3 -> 0.26260717 | E18: =E17/E3 -> 0.17773109

Sheet precios semana 2906
A1: Arandano | B1: 2000
A2: Frutillas | B2: 1600
A3: Frambuesa | B3: sin stock
A4: Higo | B4: sin stock
A5: Kiwi | B5: 1000
A6: Granada | B6: 1500
A7: Ciruela | B7: Borrar/ fuera de temp.
A8: Limon | B8: 700
A9: Limón sutil | B9: 1300
A10: Limon de pica | B10: 2000
A11: Mandarina | B11: 1200
A12: Mango | B12: 1300
A13: Manzana fuji | B13: 1900
A14: Manzana verde | B14: 1900
A15: Manzana pink lady | B15: 1900
A16: Mancaqui | B16: Borrar/ fuera de temp.
A17: Naranjas | B17: 1350
A18: Palta hass chilena | B18: 5800
A19: Palta hass peruana | B19: 4000
A20: Pera | B20: 1800
A21: Pepinodulce | B21: 2000
A22: Piña caramelo | B22: 3000
A23: Plátano | B23: 1400
A24: Platano peruano | B24: 1000
A25: Pomelo | B25: 900
A26: Tuna | B26: 2000
A27: Uva roja | B27: 1400
A28: Uva verde | B28: 2000
... A37: Apio | B37: 1400
A38: Alcachofas madrigal | B38: Sin stock
A39: Alcachofas españolas | B39: 800
A40: Berenjena | B40: 600
A41: Berros | B41: 700
A42: Betarraga | B42: 1000
A43: Brocoli | B43: 1400
A44: Brotes alfalfa | B44: Sin stock
A45: Brotes arveja | B45: Sin stock
A46: Bruselas | B46: 1200
A47: Camote Morado | B47: 1000
A48: Cebolla | B48: 250
A49: Cebolla morada | B49: 300
A50: Cebollín | B50: 700
A51: Champiñon | B51: 1500
A52: Choclo americano | B52: 800
A53: Choclo humero | B53: Fuera de temporada
A54: Ciboulette | B54: 350
A55: Cilantro | B55: 650
A56: Coliflor | B56: 1500
A57: Diente de dragon | B57: 800
A58: Habas | B58: 750
A59: Habas peladas | B59: 1000
A60: Espinaca (pura hoja) | B60: 800
A61: Esparragos | B61: 3500
A62: Jengibre | B62: 400
A63: Lechuga costina | B63: 1000
A64: Lechuga escarola | B64: 800
A65: Lechuga española | B65: 800
... A129: Tomate deshidratado | B129: 1550

Sheet Comparación
A1: Producto proveedor | B1: Unidad | C1: Lider (precio) | D1: Jumbo (precio) | E1: Juan Esparraguito (precio) | F1: Proxy de búsqueda | G1: Lider - producto encontrado (gramaje) | H1: Jumbo - producto encontrado (gramaje) | I1: Juan Esparraguito - producto encontrado (gramaje) | J1: Lider normalizado | K1: Jumbo normalizado | L1: Juan Esparraguito normalizado | M1: Juan esparraguito vs Jumbo (+31% promedio)
A2: Acelga | B2: Paquete | C2: 1490 | D2: 1590 | E2: no hay | F2: acelga | G2: Acelga Bolsa, 500 g | H2: Acelga 500 g | I2: no hay | J2: $2.980/kg | K2: $3.180/kg | L2: no hay | M2: =E2/D2-1 -> #VALUE!
A3: Ají amarillo (peruano) | B3: Kilo | C3: no hay | D3: no hay | E3: 1390 | F3: ají amarillo / peruano | G3: no hay | H3: no hay | I3: Ají Peruano (100 grs) | J3: no hay | K3: no hay | L3: $13.900/kg | M3: =E3/D3-1 -> #VALUE!
A4: Ají verde (infierno) | B4: Kilo | C4: 5390 | D4: 579 | E4: 590 | F4: ají verde | G4: Ají Verde Granel | H4: Ají Verde Granel | I4: Ají Verde (un) | J4: $5.390/kg | K4: $579/kg | L4: $590/un | M4: =E4/D4-1 -> 0.018998273
A5: Ajo | B5: Unidad | C5: 1090 | D5: 1190 | E5: =400*3 -> 1200 | F5: ajo | G5: Ajo en Malla, 3 Un | H5: Ajo 3 un. | I5: Ajo (un) | J5: $363/un | K5: $397/un | L5: $400/un | M5: =E5/D5-1 -> 0.0084033613
A6: Albahaca | B6: Kilo | C6: 1590 | D6: 1590 | E6: 1690 | F6: albahaca | G6: Albahaca Bolsa, 1 Un | H6: Albahaca 1 un. | I6: Albahaca | J6: $1.590/un | K6: $1.590/un | L6: $1.690/un | M6: =E6/D6-1 -> 0.062893082
A7: Alcachofas españolas | B7: Unidad | C7: 790 | D7: 790 | E7: 1290 | F7: alcachofa (cualquier variedad) | G7: Alcachofa Francesa, 1 Un | H7: Alcachofa Española 1 un. | I7: Alcachofa Española (un) | J7: $790/un | K7: $790/un | L7: $1.290/un | M7: =E7/D7-1 -> 0.63291139
A8: Almendras | B8: Kilo | C8: 14700 | D8: 14700 | E8: 15980 | F8: almendras | G8: no hay | H8: Almendras Naturales Granel | I8: no hay | J8: no hay | K8: $1.899/kg | L8: no hay | M8: =E8/D8-1 -> 0.08707483
A9: Almendras con chocolate | B9: Kilo | C9: no hay | D9: 4530 | E9: no hay | F9: almendras con chocolate | G9: no hay | H9: no hay | I9: no hay | J9: no hay | K9: no hay | L9: no hay | M9: =E9/D9-1 -> #VALUE!
A10: Aloe vera | B10: Kilo | C10: 2790 | D10: 2890 | E10: no hay | F10: aloe vera | G10: Aloe Vera Hoja, 1 Un | H10: Hoja Aloe Vera 1 un. | I10: no hay | J10: $2.790/un | K10: $2.890/un | L10: no hay | M10: =E10/D10-1 -> #VALUE!
A11: Apio | B11: Unidad | C11: 1000 | D11: 1490 | E11: 1990 | F11: apio | G11: Apio Mata Bolsa, 1 Un | H11: Apio Mata 1 un. | I11: Apio (un) | J11: $1.000/un | K11: $1.490/un | L11: $1.990/un | M11: =E11/D11-1 -> 0.33557047
A12: Arandano | B12: Kilo | C12: 2390 | D12: 2490 | E12: 10490 | F12: arándano | G12: Arándanos Importado Pote, 125 g | H12: Arándanos Pote 125 g | I12: Arándanos (250 grs) | J12: $19.120/kg | K12: $19.920/kg | L12: $41.960/kg | M12: =E12/D12-1 -> 3.2128514
A13: Avellanas europea | B13: Kilo | C13: no hay | D13: 1899 | E13: no hay | F13: avellana europea | G13: no hay | H13: Avellana Europea Granel | I13: no hay | J13: no hay | K13: $1.899/kg | L13: no hay | M13: =E13/D13-1 -> #VALUE!
A14: Berenjena | B14: Unidad | C14: 790 | D14: 790 | E14: 890 | F14: berenjena | G14: Berenjena Negra, 1 Un | H14: Berenjena 1 un. | I14: Berenjena (un) | J14: $790/un | K14: $790/un | L14: $890/un | M14: =E14/D14-1 -> 0.12658228
A15: Berros | B15: Kilo | C15: 1690 | D15: 1820 | E15: 2690 | F15: berro | G15: Berro Bolsa, 200 gr | H15: Berro Hidropónico 200 g | I15: Berros Hidropónicos (200 grs) | J15: $8.450/kg | K15: $9.100/kg | L15: $13.450/kg | M15: =E15/D15-1 -> 0.47802198
A16: Betarraga | B16: Paquete | C16: 1390 | D16: 1490 | E16: 2190 | F16: betarraga | G16: Betarraga Tubular Malla, 5 Un | H16: Betarraga Feria 5 un. | I16: Betarraga (4 un) | J16: $278/un | K16: $298/un | L16: $548/un | M16: =E16/D16-1 -> 0.46979866
A17: Brocoli | B17: Unidad | C17: 1090 | D17: 1590 | E17: 1990 | F17: brócoli | G17: Brócoli, 1 Un | H17: Brócoli Films 1 un. | I17: Brocoli (un) | J17: $1.090/un | K17: $1.590/un | L17: $1.990/un | M17: =E17/D17-1 -> 0.25157233
A18: Bruselas | B18: Kilo | C18: 3190 | D18: 3290 | E18: 2490 | F18: bruselas | G18: Brusela Malla, 500 gr | H18: Brusela 500 g | I18: Bruselas (500 grs) | J18: $6.380/kg | K18: $6.580/kg | L18: $4.980/kg | M18: =E18/D18-1 -> -0.24316109
A19: Camote Morado | B19: Kilo | C19: 3090 | D19: 1545 | E19: 1395 | F19: camote | G19: Camote Granel | H19: Camote Peruano Granel | I19: Papa Camote (2 un aprox) | J19: $3.090/kg | K19: $1.545/kg | L19: $698/un | M19: =E19/D19-1 -> -0.097087379
A20: Castañas de caju | B20: Kilo | C20: no hay | D20: 1899 | E20: no hay | F20: castañas de cajú | G20: no hay | H20: Castañas de Cajú Tostadas Sin Sal Granel | I20: no hay | J20: no hay | K20: $1.899/kg | L20: no hay | M20: =E20/D20-1 -> #VALUE!
A21: Cebolla | B21: Unidad | C21: 1550 | D21: 845 | E21: 795 | F21: cebolla | G21: Cebolla Granel. | H21: Cebolla Granel (1 a 2 un. Aprox) | I21: Cebolla (1 a 2 un aprox.) | J21: $1.550/kg | K21: $845/kg | L21: $398/un | M21: =E21/D21-1 -> -0.059171598
A22: Cebolla morada | B22: Unidad | C22: 1990 | D22: 995 | E22: 995 | F22: cebolla morada | G22: Cebolla Morada Malla, 1 Kg | H22: Cebolla Morada Granel | I22: Cebolla Morada (1 a 2 un aprox.) | J22: $1.990/kg | K22: $995/kg | L22: $498/un | M22: =E22/D22-1 -> 0
A23: Cebollín | B23: Paquete | C23: 1550 | D23: 850 | E23: 990 | F23: cebollín | G23: Cebollín Pack Bolsa, 6 Un | H23: Cebollín Feria 3 un. | I23: Cebollín (3 un) | J23: $258/un | K23: $283/un | L23: $330/un | M23: =E23/D23-1 -> 0.16470588
A24: Champiñon | B24: Bandeja | C24: 1590 | D24: 1650 | E24: 2190 | F24: champiñón blanco | G24: Champiñones Blanco Bandeja, 200 g | H24: Champiñón Bandeja 200 g | I24: Champiñón Blanco (200 grs) | J24: $7.950/kg | K24: $8.250/kg | L24: $10.950/kg | M24: =E24/D24-1 -> 0.32727273
A25: Chips de banana | B25: Kilo | C25: no hay | D25: 3990 | E25: no hay | F25: chips de banana | G25: no hay | H25: Banana Chips 400 g | I25: no hay | J25: no hay | K25: $9.975/kg | L25: no hay | M25: =E25/D25-1 -> #VALUE!
A26: Choclo americano | B26: Unidad | C26: 3590 | D26: 3700 | E26: 990 | F26: choclo | G26: Choclo Dulce Bandeja 4Un, 1 Un | H26: Choclo 4 un. | I26: Choclo Americano (un) | J26: $898/un | K26: $925/un | L26: $990/un | M26: =E26/D26-1 -> -0.73243243
A27: Ciboulette | B27: Paquete | C27: 690 | D27: 740 | E27: 790 | F27: ciboulette | G27: Ciboulette Bandeja, 20 g | H27: Ciboulette Display 20 g | I27: Ciboulette (20 grs) | J27: $34.500/kg | K27: $37.000/kg | L27: $39.500/kg | M27: =E27/D27-1 -> 0.067567568
A28: Cilantro | B28: Paquete | C28: 1390 | D28: 990 | E28: 1290 | F28: cilantro | G28: Cilantro Baby Pote, 60 gr | H28: Cilantro Paquete 120 g | I28: Cilantro Sanitizado (100 grs) | J28: $23.167/kg | K28: $8.250/kg | L28: $12.900/kg | M28: =E28/D28-1 -> 0.3030303
A29: Ciruela deshidratada | B29: Kilo | C29: no hay | D29: 4990 | E29: no hay | F29: ciruela deshidratada | G29: no hay | H29: Ciruelas Deshidratadas Pote 500 g | I29: no hay | J29: no hay | K29: $9.980/kg | L29: no hay | M29: =E29/D29-1 -> #VALUE!
A30: Coco en cubos | B30: Kilo | C30: no hay | D30: 1399 | E30: no hay | F30: coco (cubos/lonjas) | G30: no hay | H30: Coco en Lonjas Granel | I30: no hay | J30: no hay | K30: $1.399/kg | L30: no hay | M30: =E30/D30-1 -> #VALUE!
A31: Coco laminado | B31: Kilo | C31: no hay | D31: 1399 | E31: no hay | F31: coco laminado/lonjas | G31: no hay | H31: Coco en Lonjas Granel | I31: no hay | J31: no hay | K31: $1.399/kg | L31: no hay | M31: =E31/D31-1 -> #VALUE!
A32: Coco rallado | B32: Kilo | C32: no hay | D32: =1920*10 -> 19200 | E32: =2990*4 -> 11960 | F32: coco rallado | G32: no hay | H32: no hay | I32: no hay | J32: no hay | K32: no hay | L32: no hay | M32: =E32/D32-1 -> -0.37708333
A33: Coliflor | B33: Unidad | C33: 1590 | D33: 1690 | E33: 1990 | F33: coliflor | G33: Coliflor, 1 Un | H33: Coliflor Films 1 un. | I33: Coliflor (un) | J33: $1.590/un | K33: $1.690/un | L33: $1.990/un | M33: =E33/D33-1 -> 0.17751479
A34: Cranberries | B34: Kilo | C34: no hay | D34: 1299 | E34: no hay | F34: cranberries | G34: no hay | H34: Cranberries Mitad Granel | I34: no hay | J34: no hay | K34: $1.299/kg | L34: no hay | M34: =E34/D34-1 -> #VALUE!
A35: Dátiles | B35: Kilo | C35: no hay | D35: 4990 | E35: no hay | F35: dátiles | G35: no hay | H35: Dátil Sin Carozo 700 g | I35: no hay | J35: no hay | K35: $7.129/kg | L35: no hay | M35: =E35/D35-1 -> #VALUE!
A36: Diente de dragon | B36: Kilo | C36: 1990 | D36: 1790 | E36: no hay | F36: diente de dragón / pitahaya | G36: Diente de Dragón Bolsa, 1 Kg | H36: Diente de Dragón Granel | I36: no hay | J36: $1.990/kg | K36: $1.790/kg | L36: no hay | M36: =E36/D36-1 -> #VALUE!
A37: Esparragos | B37: Kilo | C37: no hay | D37: no hay | E37: no hay | F37: espárrago | G37: no hay | H37: no hay | I37: no hay | J37: no hay | K37: no hay | L37: no hay | M37: =E37/D37-1 -> #VALUE!
A38: Flor de hibiscos | B38: Kilo | C38: no hay | D38: no hay | E38: no hay | F38: flor de hibisco | G38: no hay | H38: no hay | I38: no hay | J38: no hay | K38: no hay | L38: no hay | M38: =E38/D38-1 -> #VALUE!
A39: Frutillas | B39: Kilo | C39: 2590 | D39: 2590 | E39: 4690 | F39: frutilla | G39: Frutillas Pote, 300 g | H39: Frutilla Pote 300 g | I39: Frutillas (500 grs) | J39: $8.633/kg | K39: $8.633/kg | L39: $9.380/kg | M39: =E39/D39-1 -> 0.81081081
A40: Goji | B40: Kilo | C40: no hay | D40: 1650 | E40: no hay | F40: goji | G40: no hay | H40: Goji 100 g | I40: no hay | J40: no hay | K40: $16.500/kg | L40: no hay | M40: =E40/D40-1 -> #VALUE!
A41: Huesillo grande | B41: Kilo | C41: no hay | D41: 7990 | E41: no hay | F41: huesillo grande | G41: no hay | H41: Huesillo Grande 600 g | I41: no hay | J41: no hay | K41: $13.317/kg | L41: no hay | M41: =E41/D41-1 -> #VALUE!
A42: Huevo Primera Blanco | B42: Unidad | C42: 309.66667 | D42: 373 | E42: no hay | F42: huevo blanco (no es F&V) | G42: no hay | H42: no hay | I42: no hay | J42: no hay | K42: no hay | L42: no hay | M42: =E42/#REF!-1 -> #VALUE!
A43: Huevo Primera Blanco 30 | B43: Unidad | C43: 9290 | D43: 11190 | E43: no hay | F43: huevo blanco (no es F&V) | G43: no hay | H43: no hay | I43: no hay | J43: no hay | K43: no hay | L43: no hay | M43: =E43/#REF!-1 -> #VALUE!
A44: Huevo Primera Color | B44: Unidad | C44: 333 | D44: 389.66667 | E44: 466.33333 | F44: huevo color (no es F&V) | G44: no hay | H44: no hay | I44: no hay | J44: no hay | K44: no hay | L44: no hay | M44: =E44/#REF!-1 -> #REF!
A45: Huevos Primera Color 30 | B45: Unidad | C45: 9990 | D45: 11690 | E45: 13990 | F45: huevo color (no es F&V) | G45: no hay | H45: no hay | I45: no hay | J45: no hay | K45: no hay | L45: no hay | M45: =E45/#REF!-1 -> #REF!
A46: Jengibre | B46: Kilo | C46: 1490 | D46: 1590 | E46: 1390 | F46: jengibre | G46: Jengibre Pote, 120 g | H46: Jengibre 100 g | I46: Jengibre (100 grs) | J46: $12.417/kg | K46: $15.900/kg | L46: $13.900/kg | M46: =E46/D46-1 -> -0.12578616
A47: Kiwi | B47: Kilo | C47: 2590 | D47: 2145 | E47: 2190 | F47: kiwi | G47: Kiwi Bolsa, 1 kg | H47: Kiwi Exportación Granel | I47: Kiwi (3 un aprox.) | J47: $2.590/kg | K47: $2.145/kg | L47: $730/un | M47: =E47/D47-1 -> 0.020979021
A48: Kiwi deshidratado | B48: Kilo | C48: no hay | D48: no hay | E48: no hay | F48: kiwi deshidratado | G48: no hay | H48: no hay | I48: no hay | J48: no hay | K48: no hay | L48: no hay | M48: =E48/D48-1 -> #VALUE!
A49: Lechuga costina | B49: Unidad | C49: 1290 | D49: 1420 | E49: 1490 | F49: lechuga costina | G49: Lechuga Costina Bolsa, 1 Un | H49: Lechuga Costina 1 un. | I49: Lechuga Costina (un) | J49: $1.290/un | K49: $1.420/un | L49: $1.490/un | M49: =E49/D49-1 -> 0.049295775
A50: Lechuga escarola | B50: Unidad | C50: 2490 | D50: 1460 | E50: 1490 | F50: lechuga escarola | G50: Lechuga Escarola Bolsa, 2 Un | H50: Lechuga Escarola 1 un. | I50: Lechuga Escarola (un) | J50: $1.245/un | K50: $1.460/un | L50: $1.490/un | M50: =E50/D50-1 -> 0.020547945
A51: Lechuga española | B51: Unidad | C51: 1290 | D51: 1250 | E51: 1890 | F51: lechuga española | G51: Lechuga Española Bolsa, 1 Un | H51: Lechuga Española 1 un. | I51: Lechuga Española Hidropónica (un) | J51: $1.290/un | K51: $1.250/un | L51: $1.890/un | M51: =E51/D51-1 -> 0.512
A52: Lechuga Francesa | B52: Unidad | C52: 1290 | D52: 1250 | E52: no hay | F52: lechuga francesa | G52: Lechuga Francesa Bolsa, 1 Un | H52: Lechuga Francesa 1 un. | I52: no hay | J52: $1.290/un | K52: $1.250/un | L52: no hay | M52: =E52/D52-1 -> #VALUE!
A53: Lechuga hidroponica | B53: Unidad | C53: 1590 | D53: 1740 | E53: 1890 | F53: lechuga hidropónica | G53: Lechuga Hoja De Roble Verde Hidroponica Bolsa, 1 Un | H53: Lechuga Hidropónica Española 1 un. | I53: Lechuga Española Hidropónica (un) | J53: $1.590/un | K53: $1.740/un | L53: $1.890/un | M53: =E53/D53-1 -> 0.086206897
A54: Lechuga Marina | B54: Unidad | C54: 1290 | D54: 1360 | E54: no hay | F54: lechuga marina | G54: Lechuga Marina Bolsa, 1 Un | H54: Lechuga Hidropónica Marina 1 un. | I54: no hay | J54: $1.290/un | K54: $1.360/un | L54: no hay | M54: =E54/D54-1 -> #VALUE!
A55: Limon | B55: Kilo | C55: 1950 | D55: 795 | E55: 995 | F55: limón | G55: Limón Granel | H55: Limón Granel (1 a 2 un. Aprox) | I55: Limón (3 un aprox.) | J55: $1.950/kg | K55: $795/kg | L55: $332/un | M55: =E55/D55-1 -> 0.25157233
A56: Limon de pica | B56: Kilo | C56: no hay | D56: no hay | E56: no hay | F56: limón de pica | G56: no hay | H56: no hay | I56: no hay | J56: no hay | K56: no hay | L56: no hay | M56: =E56/D56-1 -> #VALUE!
A57: Limón sutil | B57: Kilo | C57: 3650 | D57: 1845 | E57: 1790 | F57: limón sutil | G57: Limón Sutil Malla, 1 kg | H57: Limón Sutil Granel | I57: Limón Sutil (8 un aprox.) | J57: $3.650/kg | K57: $1.845/kg | L57: $224/un | M57: =E57/D57-1 -> -0.029810298
A58: Linaza | B58: Kilo | C58: no hay | D58: 999 | E58: no hay | F58: linaza | G58: no hay | H58: Semillas de Linaza Granel | I58: no hay | J58: no hay | K58: $999/kg | L58: no hay | M58: =E58/D58-1 -> #VALUE!
A59: Maíz curagua | B59: Kilo | C59: no hay | D59: no hay | E59: no hay | F59: maíz curagua | G59: no hay | H59: no hay | I59: no hay | J59: no hay | K59: no hay | L59: no hay | M59: =E59/D59-1 -> #VALUE!
A60: Mancaqui | B60: Kilo | C60: no hay | D60: no hay | E60: no hay | F60: mancaqui | G60: Mancaqui Granel | H60: no hay | I60: no hay | J60: no hay | K60: no hay | L60: no hay | M60: =E60/D60-1 -> #VALUE!
A61: Mandarina | B61: Kilo | C61: 2000 | D61: 1395 | E61: 1445 | F61: mandarina | G61: Mandarina Malla, 1 kg | H61: Mandarina Granel | I61: Mandarina (6 un aprox.) | J61: $2.000/kg | K61: $1.395/kg | L61: $241/un | M61: =E61/D61-1 -> 0.035842294
A62: Mango | B62: Unidad | C62: 2890 | D62: 1505 | E62: 2690 | F62: mango | G62: Mango Granel | H62: Mango Granel (1 un. Aprox) | I62: Mango (un) - Normal | J62: $2.890/kg | K62: $1.505/kg | L62: $2.690/un | M62: =E62/D62-1 -> 0.78737542
A63: Mango deshidratado | B63: Kilo | C63: no hay | D63: 4590 | E63: no hay | F63: mango deshidratado / en lonja | G63: no hay | H63: Mango en Lonja 150 g | I63: no hay | J63: no hay | K63: $30.600/kg | L63: no hay | M63: =E63/D63-1 -> #VALUE!
A64: Maní chocolate | B64: Kilo | C64: no hay | D64: no hay | E64: no hay | F64: maní con chocolate | G64: no hay | H64: no hay | I64: no hay | J64: no hay | K64: no hay | L64: no hay | M64: =E64/D64-1 -> #VALUE!
A65: Mani con sal | B65: Kilo | C65: no hay | D65: 3790 | E65: no hay | F65: maní con sal / tostado | G65: no hay | H65: Maní Tostado 700 g | I65: no hay | J65: no hay | K65: $5.414/kg | L65: no hay | M65: =E65/D65-1 -> #VALUE!
A66: Maní confitado | B66: Kilo | C66: no hay | D66: no hay | E66: no hay | F66: maní confitado | G66: no hay | H66: no hay | I66: no hay | J66: no hay | K66: no hay | L66: no hay | M66: =E66/D66-1 -> #VALUE!
A67: Maní japonés natural | B67: Kilo | C67: no hay | D67: no hay | E67: no hay | F67: maní japonés natural | G67: no hay | H67: no hay | I67: no hay | J67: no hay | K67: no hay | L67: no hay | M67: =E67/D67-1 -> #VALUE!
A68: Maní Japonés picante | B68: Kilo | C68: no hay | D68: no hay | E68: no hay | F68: maní japonés picante | G68: no hay | H68: no hay | I68: no hay | J68: no hay | K68: no hay | L68: no hay | M68: =E68/D68-1 -> #VALUE!
A69: Maní sin sal | B69: Kilo | C69: no hay | D69: 3990 | E69: no hay | F69: maní sin sal | G69: no hay | H69: Maní Tostado Sin Sal 700 g | I69: no hay | J69: no hay | K69: $5.700/kg | L69: no hay | M69: =E69/D69-1 -> #VALUE!
A70: Manzana deshidratada | B70: Kilo | C70: no hay | D70: 3490 | E70: no hay | F70: manzana deshidratada | G70: no hay | H70: Manzana Deshidratada Secao 80 g | I70: no hay | J70: no hay | K70: $43.625/kg | L70: no hay | M70: =E70/D70-1 -> #VALUE!
A71: Manzana fuji | B71: Kilo | C71: 1990 | D71: 1295 | E71: 1445 | F71: manzana fuji | G71: Manzana Fuji Bolsa., 1 kg | H71: Manzana Fuji Importada Granel (2 a 3 un. Aprox) | I71: Manzana Fuji (2 un aprox.) | J71: $1.990/kg | K71: $1.295/kg | L71: $722/un | M71: =E71/D71-1 -> 0.11583012
A72: Manzana pink lady | B72: Kilo | C72: 1890 | D72: 1295 | E72: 1445 | F72: manzana pink lady | G72: Manzana Pink Lady Bolsa, 1 kg | H72: Manzana Pink Lady Granel | I72: Manzana Pink Lady (2 un aprox.) | J72: $1.890/kg | K72: $1.295/kg | L72: $722/un | M72: =E72/D72-1 -> 0.11583012
A73: Manzana verde | B73: Kilo | C73: 1990 | D73: 1295 | E73: 1445 | F73: manzana verde | G73: Manzana Verde Bolsa, 1 kg | H73: Manzana Verde Granel | I73: Manzana Verde (2 un aprox.) | J73: $1.990/kg | K73: $1.295/kg | L73: $722/un | M73: =E73/D73-1 -> 0.11583012
A74: Menta | B74: Kilo | C74: 990 | D74: 1050 | E74: 2690 | F74: menta | G74: Menta Pote, 1 Un | H74: Menta Bandeja 30 g | I74: Menta Sanitizada (100 grs) | J74: $990/un | K74: $35.000/kg | L74: $26.900/kg | M74: =E74/D74-1 -> 1.5619048
A75: Naranjas | B75: Kilo | C75: 2690 | D75: 1445 | E75: 1445 | F75: naranja | G75: Naranja Granel | H75: Naranja Granel (2 a 3 un. Aprox) | I75: Naranja (2 un aprox.) | J75: $2.690/kg | K75: $1.445/kg | L75: $722/un | M75: =E75/D75-1 -> 0
A76: Nueces | B76: Kilo | C76: no hay | D76: 1499 | E76: no hay | F76: nueces | G76: no hay | H76: Nueces en Trozo Granel | I76: no hay | J76: no hay | K76: $1.499/kg | L76: no hay | M76: =E76/D76-1 -> #VALUE!
A77: Palta hass chilena | B77: Kilo | C77: 4990 | D77: 2890 | E77: 6490 | F77: palta hass chilena | G77: Palta Hass Chilena Malla, 1 kg | H77: Palta Hass Malla 1 kg | I77: Palta Hass (4 un aprox.) - Para Hoy | J77: $4.990/kg | K77: $2.890/kg | L77: $1.622/un | M77: =E77/D77-1 -> 1.2456747
A78: Palta hass peruana | B78: Kilo | C78: no hay | D78: 5990 | E78: no hay | F78: palta hass peruana / importada | G78: no hay | H78: Palta Hass Extra Importada Granel | I78: no hay | J78: no hay | K78: $5.990/kg | L78: no hay | M78: =E78/D78-1 -> #VALUE!
A79: Papa | B79: Kilo | C79: 1590 | D79: 795 | E79: 795 | F79: papa | G79: Papas Granel | H79: Papa Granel | I79: Papa (4 un aprox.) | J79: $1.590/kg | K79: $795/kg | L79: $199/un | M79: =E79/D79-1 -> 0
A80: Papaya deshidratada | B80: Kilo | C80: no hay | D80: no hay | E80: no hay | F80: papaya deshidratada | G80: no hay | H80: no hay | I80: no hay | J80: no hay | K80: no hay | L80: no hay | M80: =E80/D80-1 -> #VALUE!
A81: Pasas con chocolate | B81: Kilo | C81: no hay | D81: no hay | E81: no hay | F81: pasas con chocolate | G81: no hay | H81: no hay | I81: no hay | J81: no hay | K81: no hay | L81: no hay | M81: =E81/D81-1 -> #VALUE!
A82: Pasas negras | B82: Kilo | C82: no hay | D82: 3170 | E82: no hay | F82: pasas negras / morenas | G82: no hay | H82: Pasas Morenas 300 g | I82: no hay | J82: no hay | K82: $10.567/kg | L82: no hay | M82: =E82/D82-1 -> #VALUE!
A83: Pasas rubias | B83: Kilo | C83: no hay | D83: 999 | E83: no hay | F83: pasas rubias | G83: no hay | H83: Pasas Rubias 100 g | I83: no hay | J83: no hay | K83: $9.990/kg | L83: no hay | M83: =E83/D83-1 -> #VALUE!
A84: Pepas de zapallo | B84: Kilo | C84: no hay | D84: 1299 | E84: no hay | F84: pepas / semillas de zapallo | G84: no hay | H84: Semillas de Zapallo Granel | I84: no hay | J84: no hay | K84: $1.299/kg | L84: no hay | M84: =E84/D84-1 -> #VALUE!
A85: Pepinodulce | B85: Kilo | C85: 3290 | D85: 1745 | E85: 1695 | F85: pepino dulce | G85: Pepino Dulce Granel | H85: Pepino Dulce Granel | I85: Pepino dulce (2 un aprox.) | J85: $3.290/kg | K85: $1.745/kg | L85: $848/un | M85: =E85/D85-1 -> -0.028653295
A86: Pepinos | B86: Unidad | C86: 720 | D86: 750 | E86: 790 | F86: pepino ensalada | G86: Pepino Ensalada, 1 Un | H86: Pepino Ensalada 1 un. | I86: Pepino (un) | J86: $720/un | K86: $750/un | L86: $790/un | M86: =E86/D86-1 -> 0.053333333
A87: Pera | B87: Kilo | C87: 1790 | D87: 1095 | E87: 1345 | F87: pera | G87: Pera Bolsa., 1 kg | H87: Pera Packham's Granel | I87: Pera (2 un aprox.) | J87: $1.790/kg | K87: $1.095/kg | L87: $672/un | M87: =E87/D87-1 -> 0.2283105
A88: Perejil | B88: Paquete | C88: 630 | D88: 650 | E88: 1250 | F88: perejil | G88: Perejil Bolsa, 120 g | H88: Perejil 1 un. | I88: Perejil Sanitizado (100 grs) | J88: $5.250/kg | K88: $650/un | L88: $12.500/kg | M88: =E88/D88-1 -> 0.92307692
A89: Pimentón amarillo | B89: Unidad | C89: 1690 | D89: 1790 | E89: no hay | F89: pimiento/pimentón amarillo | G89: Pimiento Amarillo, 1 Un | H89: Pimiento Amarillo 1 un. | I89: no hay | J89: $1.690/un | K89: $1.790/un | L89: no hay | M89: =E89/D89-1 -> #VALUE!
A90: Pimentón rojo | B90: Unidad | C90: 1690 | D90: 1790 | E90: 1790 | F90: pimiento/pimentón rojo | G90: Pimiento Rojo, 1 Un | H90: Pimiento Rojo Extra | I90: Pimentón Rojo (un) | J90: $1.690/un | K90: $1.790/un | L90: $1.790/un | M90: =E90/D90-1 -> 0
A91: Pimentón verde | B91: Unidad | C91: 950 | D91: 990 | E91: 1190 | F91: pimiento/pimentón verde | G91: Pimiento Verde, 1 Un | H91: Pimiento Verde 1 un. | I91: Pimentón Verde (un) | J91: $950/un | K91: $990/un | L91: $1.190/un | M91: =E91/D91-1 -> 0.2020202
A92: Piña caramelo | B92: Unidad | C92: 2590 | D92: 2690 | E92: 3990 | F92: piña | G92: Piña, 1 Un | H92: Piña Calibre 7 - 1 un. | I92: Piña (un) | J92: $2.590/un | K92: $2.690/un | L92: $3.990/un | M92: =E92/D92-1 -> 0.48327138
A93: Pistacho con sal | B93: Kilo | C93: no hay | D93: 4690 | E93: no hay | F93: pistacho con sal | G93: no hay | H93: Pistachos Sin Cáscara 100 g | I93: no hay | J93: no hay | K93: $46.900/kg | L93: no hay | M93: =E93/D93-1 -> #VALUE!
A94: Plátano | B94: Kilo | C94: 1450 | D94: 795 | E94: 1990 | F94: plátano | G94: Plátano Granel | H94: Plátano Extra Granel (1 a 2 un. Aprox) | I94: Plátano Kg (4 un aprox.) - Más verdes | J94: $1.450/kg | K94: $795/kg | L94: $498/un | M94: =E94/D94-1 -> 1.5031447
A95: Pomelo | B95: Kilo | C95: 2150 | D95: 3860 | E95: =1595*2 -> 3190 | F95: pomelo | G95: Pomelo Granel | H95: Pomelo Rosado 2 kg | I95: Pomelos (1 un aprox.) | J95: $2.150/kg | K95: $1.930/kg | L95: $1.595/un | M95: =E95/D95-1 -> -0.17357513
A96: Pomelo deshidratado | B96: Kilo | C96: no hay | D96: no hay | E96: no hay | F96: pomelo deshidratado | G96: no hay | H96: no hay | I96: no hay | J96: no hay | K96: no hay | L96: no hay | M96: =E96/D96-1 -> #VALUE!
A97: Porotos verdes | B97: Kilo | C97: no hay | D97: 1995 | E97: no hay | F97: porotos verdes | G97: no hay | H97: Porotos Verdes Granel | I97: no hay | J97: no hay | K97: $1.995/kg | L97: no hay | M97: =E97/D97-1 -> #VALUE!
A98: Rabanitos | B98: Paquete | C98: 1350 | D98: 1450 | E98: 1990 | F98: rabanito | G98: Rabanitos Bandeja, 8 Un | H98: Rabanitos Atado 8 un. | I98: Rabanitos baby sanitizados 220 grs | J98: $169/un | K98: $181/un | L98: $9.045/kg | M98: =E98/D98-1 -> 0.37241379
A99: Repollo crespo | B99: Unidad | C99: 1590 | D99: 1710 | E99: 3990 | F99: repollo crespo | G99: Repollo Crespo, 1 Un | H99: Repollo Crespo 1 un. | I99: Repollo Crespo (un) | J99: $1.590/un | K99: $1.710/un | L99: $3.990/un | M99: =E99/D99-1 -> 1.3333333
A100: Repollo morado | B100: Unidad | C100: 1590 | D100: 1690 | E100: 3990 | F100: repollo morado | G100: Repollo Morado, 1 Un | H100: Repollo Morado Film 1 un. | I100: Repollo Morado (un) | J100: $1.590/un | K100: $1.690/un | L100: $3.990/un | M100: =E100/D100-1 -> 1.3609467
...

Sheet Lider
A1: Nombre completo del producto | B1: Precio actual | C1: Url de la imagen | D1: Categoria | E1: Cantidad de medida | F1: Unidad
A2: Limón Malla, 1 kg | B2: 1950 | C2: https://i5.walmartimages.cl/asr/248bd1b1-37a4-464f-aa17-53104ebe63ac.7840608b4f5e2e75776c79060f2de2f4.jpeg?odnHeight=580&odnWidth=580&odnBg=FFFFFF | D2: Frutas | E2: 1 | F2: kilos
A3: Mandarina Malla, 1 kg | B3: 2000 | C3: https://i5.walmartimages.cl/asr/083eabb8-cd7f-46c2-ace0-8664f45a0cd8.906cbaffd69e0d8a60626c5fe9f8b7cb.jpeg?null=&odnHeight=580&odnWidth=580&odnBg=FFFFFF | D3: Frutas | E3: 1 | F3: kilos
A4: Manzana Royal Bolsa, 1 kg | B4: 1990 | C4: https://i5.walmartimages.cl/asr/87055fe6-e907-4a58-8677-0563ee63c3d1.2bb397d62720c4a73ec62b5bc6edd4f3.jpeg?odnHeight=580&odnWidth=580&odnBg=FFFFFF | D4: Frutas | E4: 1 | F4: kilos
A5: Manzana Verde Bolsa, 1 kg | B5: 1990 | C5: https://i5.walmartimages.cl/asr/26816f7e-4d05-463b-b73e-cd6f05220db8.a49fa7c44acb5d70eadb6d39e4a02ddd.jpeg?odnHeight=580&odnWidth=580&odnBg=FFFFFF | D5: Frutas | E5: 1 | F5: kilos
A6: Palta Hass Chilena Granel | B6: 6290 | C6: https://i5.walmartimages.cl/asr/c1231a68-55a7-4c9e-9f6f-35163325a1d0.a02a9ad32ba8f2ea5afbffbeafce3d6d.jpeg?odnHeight=580&odnWidth=580&odnBg=FFFFFF | D6: Frutas | E6: 1 | F6: kilos
A7: Plátano Granel | B7: 1450 | C7: https://i5.walmartimages.cl/asr/c1a030d6-88b6-44fb-9fe1-f5374fcdf51e.0431f1fccec368ba6a244b84b17e5b01.jpeg?odnHeight=580&odnWidth=580&odnBg=FFFFFF | D7: Frutas | E7: 1 | F7: kilos
A8: Manzana Fuji Granel. | B8: 2490 | C8: https://i5.walmartimages.cl/asr/aaf18678-bd4f-4e39-8f25-582207e7d87d.1713ece21412bcf8549cfdd3877aa35a.jpeg?odnHeight=580&odnWidth=580&odnBg=FFFFFF | D8: Frutas | E8: 1 | F8: kilos
A9: Frutillas Pote, 300 g | B9: 2590 | C9: https://i5.walmartimages.cl/asr/3eb1e73d-5fc6-4d43-87c6-590c56eb24a2.1c2d56a033728a5ab87d862c2ce0ae61.jpeg?odnHeight=580&odnWidth=580&odnBg=FFFFFF | D9: Frutas | E9: 300 | F9: gramos
A10: Naranja Importada Granel | B10: 2790 | C10: https://i5.walmartimages.cl/asr/7cec853e-fb16-4a48-9eec-c763cee05513.cf714b9536fcc0d6ea89e1eee7afe81a.jpeg?odnHeight=580&odnWidth=580&odnBg=FFFFFF | D10: Frutas | E10: 1 | F10: kilos
A11: Naranja Malla, 2 kg | B11: 3590 | C11: https://i5.walmartimages.cl/asr/49eac9c8-a6ab-49fb-8b03-978ccd8ab53c.fd750cbb4b081ea4cb169b99a94d0f4c.jpeg?odnHeight=580&odnWidth=580&odnBg=FFFFFF | D11: Frutas | E11: 2 | F11: kilos
A12: Mango Granel | B12: 2890 | C12: https://i5.walmartimages.cl/asr/09467583-8b9c-4d63-b52b-bf7d3828704a.91674db31600eb4eb8bb0d34699b672e.jpeg?odnHeight=580&odnWidth=580&odnBg=FFFFFF | D12: Frutas | E12: 1 | F12: kilos
A13: Kiwi Granel | B13: 4190 | C13: https://i5.walmartimages.cl/asr/a3ff5ea4-0eea-4483-9d33-8bef94fa9ebc.78ebe29f03a715ed65a2cfc62ab6d095.jpeg?odnHeight=580&odnWidth=580&odnBg=FFFFFF | D13: Frutas | E13: 1 | F13: kilos
... A21: Pomelo Granel | B21: 2150 | C21: https://i5.walmartimages.cl/asr/20df7f10-f765-47be-9147-9dbc72e5d56f.2b926841f31184654a8b84c90873c27b.jpeg?odnHeight=580&odnWidth=580&odnBg=FFFFFF | D21: Frutas | E21: 1 | F21: kilos
A22: Mix de Frutas (Manzanas, naranjas y Peras) Bolsa, 1,5 kg | B22: 2190 | C22: https://i5.walmartimages.cl/asr/e3df83ee-22d4-4354-a8d5-b575c62aab3c.6388bb26100f035705c1cbd655803392.jpeg?odnHeight=580&odnWidth=580&odnBg=FFFFFF | D22: Frutas | E22: 1,5 | F22: kilos
A23: Manzana Fuji Bolsa., 1 kg | B23: 1990 | C23: https://i5.walmartimages.cl/asr/a1171bcc-9ed2-48fe-935e-e09d4e7c6622.635d05bd27937258640b697749e2dddf.jpeg?odnHeight=580&odnWidth=580&odnBg=FFFFFF | D23: Frutas | E23: 1 | F23: kilos
A24: Pepino Dulce Granel | B24: 3290 | C24: https://i5.walmartimages.cl/asr/f0e61f15-8f9f-4617-90fb-692827840f9f.94b758636bcafa818ae67e3eb1c5bc88.jpeg?odnHeight=580&odnWidth=580&odnBg=FFFFFF | D24: Frutas | E24: 1 | F24: kilos
A25: Arándanos Importado Pote, 125 g | B25: 2390 | C25: https://i5.walmartimages.cl/asr/83aed111-738b-4da4-8ec2-bd0d276a88bf.e427a0a7d8d2fd2e7853f16c3ddf39c7.jpeg?odnHeight=580&odnWidth=580&odnBg=FFFFFF | D25: Frutas | E25: 125 | F25: gramos
A26: Manzana Verde Granel. | B26: 2490 | C26: https://i5.walmartimages.cl/asr/ec8c8ad9-0518-4d8a-8f2b-6954e34fcde5.8431f0f3a2a78283f3f579bd931c629f.jpeg?odnHeight=580&odnWidth=580&odnBg=FFFFFF | D26: Frutas | E26: 1 | F26: kilos
A27: Limón Sutil Malla, 1 kg | B27: 3650 | C27: https://i5.walmartimages.cl/asr/6e91773b-2219-416f-be21-571d2a150a59.93b3dc03226d82221f635e108c4a882f.jpeg?odnHeight=580&odnWidth=580&odnBg=FFFFFF | D27: Frutas | E27: 1 | F27: kilos
A28: Limón Granel | B28: 1950 | C28: https://i5.walmartimages.cl/asr/b4883972-a340-4960-b082-80df64a5e6f1.d11cccdf2d520234e7c34584c4715701.jpeg?odnHeight=580&odnWidth=580&odnBg=FFFFFF | D28: Frutas | E28: 1 | F28: kilos
A29: Pera Packams Granel | B29: 2150 | C29: https://i5.walmartimages.cl/asr/241bd205-b6b9-429b-b68b-91c78ef59c8a.96082974a4b67edc985e53ec84efe4b2.jpeg?odnHeight=580&odnWidth=580&odnBg=FFFFFF | D29: Frutas | E29: 1 | F29: kilos
A30: Frutillas Pote, 500 g | B30: 3190 | C30: https://i5.walmartimages.cl/asr/3f93ee9f-29e1-4ec6-9357-623c62793713.a6641a8ae20a6bd07255e02fbabe9faf.jpeg?odnHeight=580&odnWidth=580&odnBg=FFFFFF | D30: Frutas | E30: 500 | F30: gramos
A31: Arándano Pote, 300 g | B31: 4090 | C31: https://i5.walmartimages.cl/asr/93895a7e-108f-466b-b076-6e0e83282232.6a18620121058c55c18f6cc2d69fffbf.jpeg?null=&odnHeight=580&odnWidth=580&odnBg=FFFFFF | D31: Frutas | E31: 300 | F31: gramos
A32: Granada Granel | B32: 4490 | C32: https://i5.walmartimages.cl/asr/9b694b29-44c2-49b4-a997-4625bc2f8e1e.0e64d26c7dd4a11eed203d828c7d41e6.jpeg?null=&odnHeight=580&odnWidth=580&odnBg=FFFFFF | D32: Frutas | E32: 1 | F32: kilos
A33: Kiwi Amarillo Pote, 500 g | B33: 2790 | C33: https://i5.walmartimages.cl/asr/a5564f5c-8c35-418a-9808-2eccef53bac1.55449767a32f5445560d29a9f6b961c7.jpeg?odnHeight=580&odnWidth=580&odnBg=FFFFFF | D33: Frutas | E33: 500 | F33: gramos
A34: Plátano Barraganete Granel | B34: 1450 | C34: https://i5.walmartimages.cl/asr/67639522-2e1b-41fd-8415-a18342dfe374.8a23b5eaae7fc2f4cac9602954828cd9.jpeg?odnHeight=580&odnWidth=580&odnBg=FFFFFF | D34: Frutas | E34: 1 | F34: kilos
A35: Mandarina Sofruco Malla, 1,5 kg | B35: 4990 | C35: https://i5.walmartimages.cl/asr/bc84d819-d9d4-4af2-9c5c-0f78e499a10a.df7cea40eebf648c19df2e1cc034f7a5.jpeg?odnHeight=580&odnWidth=580&odnBg=FFFFFF | D35: Frutas | E35: 1,5 | F35: kilos
A36: Pera Abate Granel. | B36: 2150 | C36: https://i5.walmartimages.cl/asr/020d1058-f205-4af2-9132-a3ad49f232c0.0e34653ea39927e158544b800d928ecd.jpeg?odnHeight=580&odnWidth=580&odnBg=FFFFFF | D36: Frutas | E36: 1 | F36: kilos
A37: Plátano Baby Orito Granel | B37: 2000 | C37: https://i5.walmartimages.cl/asr/f4170aac-aa5d-4d07-a018-0570ef72d9e1.77714a1d8f5693d3af642554f47f9af6.jpeg?odnHeight=580&odnWidth=580&odnBg=FFFFFF | D37: Frutas | E37: 1 | F37: kilos
A38: Limón Sin Semillas Malla, 900 g | B38: 1990 | C38: https://i5.walmartimages.cl/asr/122b0b25-3f2a-4665-872e-848f663caec7.dfd1e39ba1fac8248edf239f49a943e4.jpeg?odnHeight=580&odnWidth=580&odnBg=FFFFFF | D38: Frutas | E38: 900 | F38: gramos
A39: Frambuesas Pote, 70 g | B39: 1990 | C39: https://i5.walmartimages.cl/asr/45bef92f-1d02-45c8-9603-18d9a9cab63d.d1c55c070f1545f75f9162a65148a3e2.jpeg?odnHeight=580&odnWidth=580&odnBg=FFFFFF | D39: Frutas | E39: 70 | F39: gramos
A40: Tuna Malla, 1 kg | B40: 2890 | C40: https://i5.walmartimages.cl/asr/f454eabc-a704-4051-9cc2-61ae3a9ea708.bced8adf7ec553a8090f89307c2c1209.jpeg?odnHeight=580&odnWidth=580&odnBg=FFFFFF | D40: Frutas | E40: 1 | F40: kilos
A41: Tuna Granel | B41: 3290 | C41: https://i5.walmartimages.cl/asr/945e5518-2a01-460c-ab47-0bbc57535333.a3085046531cd30670182a88928b43d3.jpeg?odnHeight=580&odnWidth=580&odnBg=FFFFFF | D41: Frutas | E41: 1 | F41: kilos
A42: Membrillo Granel | B42: 2490 | C42: https://i5.walmartimages.cl/asr/f5c7878d-2051-4bdf-9def-f0c742aa2f05.c70df7278aaa19bb79c3b753ced98cbf.jpeg?null=&odnHeight=580&odnWidth=580&odnBg=FFFFFF | D42: Frutas | E42: 1 | F42: kilos
A43: Manzana Roja Bolsa, 1 kg | B43: 1990 | C43: https://i5.walmartimages.cl/asr/9be25181-4fa4-4d4c-80ec-78a6cdb3e21f.78b8b6dd7091ae87f32c369b6899146f.jpeg?odnHeight=580&odnWidth=580&odnBg=FFFFFF | D43: Frutas | E43: 1 | F43: kilos
A44: Pomelo Malla, 2 kg | B44: 3590 | C44: https://i5.walmartimages.cl/asr/f732e2ee-6e52-47fd-a2c8-668b3f55be61.5c1b0adbe47499e39fe12b0cd35e03c3.jpeg?odnHeight=580&odnWidth=580&odnBg=FFFFFF | D44: Frutas | E44: 2 | F44: kilos
A45: Palta Negra La Cruz Malla, 1 kg | B45: 4490 | C45: https://i5.walmartimages.cl/asr/0dbee476-6ddb-4f2d-ae73-eb68608d1add.730bf0363fd9c98703bad21f801acea4.jpeg?odnHeight=580&odnWidth=580&odnBg=FFFFFF | D45: Frutas | E45: 1 | F45: kilos
A46: Manzana Pink Lady Bolsa, 1 kg | B46: 1890 | C46: https://i5.walmartimages.cl/asr/c2e7395a-5e45-40b6-bd41-8d4be8612e31.e7293d2995edcc31407df3b2f1a6e7df.jpeg?null=&odnHeight=580&odnWidth=580&odnBg=FFFFFF | D46: Frutas | E46: 1 | F46: kilos
A47: Castaña Granel | B47: 4990 | C47: https://i5.walmartimages.cl/asr/6605b742-d7b3-4e0d-8b71-a0fc353af7dd.e5785c7e01ae4cde1b8e5beb78894825.jpeg?null=&odnHeight=580&odnWidth=580&odnBg=FFFFFF | D47: Frutas | E47: 1 | F47: kilos
... A146: Brusela Malla, 500 gr | B146: 3190 | C146: https://i5.walmartimages.cl/asr/0d5ee8ad-3ade-47ba-9fba-8ec3c8ac58f1.c2f7472433dfc0f10bb04450d4bd6df4.jpeg?odnHeight=580&odnWidth=580&odnBg=FFFFFF | D146: Verduras | E146: 500 | F146: gramos
A147: Papa Ox Malla, 1,5 kg | B147: 2990 | C147: https://i5.walmartimages.cl/asr/6861e6bd-07fb-4de4-bf01-9689e4628191.51fd7c65a58d496121a0f0c6c759817c.jpeg?null=&odnHeight=580&odnWidth=580&odnBg=FFFFFF | D147: Verduras | E147: 1,5 | F147: kilos
A148: Perejil Bolsa, 120 g | B148: 630 | C148: https://i5.walmartimages.cl/asr/455622bf-4599-46c8-b680-f11cfdb3f537.8821a6a9d31ac2e91be53430f61c9cff.jpeg?odnHeight=580&odnWidth=580&odnBg=FFFFFF | D148: Verduras | E148: 120 | F148: gramos
A149: Rúcula Hojas Bolsa, 150 gr | B149: 2290 | C149: https://i5.walmartimages.cl/asr/fcf394f4-5846-4531-b1ce-496ca7d37b21.1845f897c0fa9ebc288945c3ff97e5c8.jpeg?odnHeight=580&odnWidth=580&odnBg=FFFFFF | D149: Verduras | E149: 150 | F149: gramos
A150: Cilantro Baby Pote, 60 gr | B150: 1390 | C150: https://i5.walmartimages.cl/asr/b721aa79-e5f0-42f2-86f4-ca509ce058a4.e0e520416276f2fb62fa8df3d633103e.jpeg?odnHeight=580&odnWidth=580&odnBg=FFFFFF | D150: Verduras | E150: 60 | F150: gramos
A151: Zapallo Butternut, 1 Un | B151: 2290 | C151: https://i5.walmartimages.cl/asr/b3b43ca1-fb05-4487-b4e5-5c6df573d5ec.37f79297d58ee523f29cb3119181ac02.jpeg?odnHeight=580&odnWidth=580&odnBg=FFFFFF | D151: Verduras | E151: 1 | F151: unidad
A152: Ciboulette Oriental Bolsa, 50 g | B152: 990 | C152: https://i5.walmartimages.cl/asr/27c70d74-f31c-4ffe-8222-ce7c6d62d165.1b9f7a08ec3552fe58e1fb9a777e1d54.jpeg?odnHeight=580&odnWidth=580&odnBg=FFFFFF | D152: Verduras | E152: 50 | F152: gramos
A153: Pepino Alaska, 1 Un | B153: 1190 | C153: https://i5.walmartimages.cl/asr/779a19d1-13b0-4427-a2e4-18e972e41320.7462cefe6c32c26cabfea6a855bec662.jpeg?odnHeight=580&odnWidth=580&odnBg=FFFFFF | D153: Verduras | E153: 1 | F153: unidad
A154: Espinaca Baby Pote, 150 g | B154: 2990 | C154: https://i5.walmartimages.cl/asr/aa7d56dd-0911-437b-a57c-d636d1117a21.eb0b997ce81ed4937b09f0996763686d.jpeg?odnHeight=580&odnWidth=580&odnBg=FFFFFF | D154: Verduras | E154: 150 | F154: gramos
A155: Ensalada Zanahoria Juliana Bolsa, 180 g | B155: 1090 | C155: https://i5.walmartimages.cl/asr/8887b7e8-29d1-4e92-aad5-6bacd809ccdd.6e301f2c777c78f644b1bae250b82b82.jpeg?odnHeight=580&odnWidth=580&odnBg=FFFFFF | D155: Verduras | E155: 180 | F155: gramos
A156: Espinaca baby, 150 g | B156: 1890 | C156: https://i5.walmartimages.cl/asr/89ce73b1-6f82-40b5-9e07-ab35ac3dbf13.3d23c24f8d330e15858739aee70c1452.jpeg?odnHeight=580&odnWidth=580&odnBg=FFFFFF | D156: Verduras | E156: 150 | F156: gramos
A157: Apio Corazones Bolsa, 1 Un | B157: 2990 | C157: https://i5.walmartimages.cl/asr/c8746a4d-a89b-430e-ab8f-33f21aad793a.58c692ad6f63ed57ee980c600fa385d2.jpeg?odnHeight=580&odnWidth=580&odnBg=FFFFFF | D157: Verduras | E157: 1 | F157: unidad
A158: Ensalada Coleslaw Bolsa, 180 g | B158: 1090 | C158: https://i5.walmartimages.cl/asr/72711c0f-874b-4615-9c6f-e03632b04cb7.b9bf661b8c2a6a6016dc54253e7cbb90.jpeg?odnHeight=580&odnWidth=580&odnBg=FFFFFF | D158: Verduras | E158: 180 | F158: gramos
A159: Tomate Mix Cóctel Granel | B159: 5990 | C159: https://i5.walmartimages.cl/asr/475ecb33-fcca-410f-8fc0-77756c25f250.71e5e33d904fb5672bd1634b66dec649.jpeg?null=&odnHeight=580&odnWidth=580&odnBg=FFFFFF | D159: Verduras | E159: 1 | F159: kilos
... A248: Laurel Pote, 1 Un | B248: 990 | C248: https://i5.walmartimages.cl/asr/3e6431a8-949f-477c-9903-26b507783227.9fd303703531163c88f57ed926067b58.jpeg?odnHeight=580&odnWidth=580&odnBg=FFFFFF | D248: Verduras | E248: 1 | F248: unidad
A249: Betarraga Malla Imperfecta, 1,5 kg | B249: 1290 | C249: https://i5.walmartimages.cl/asr/8f79cef3-7cdc-417f-b3ca-5aebbef246a7.12f0dca5ce5a19286f1379df10c59c08.jpeg?null=&odnHeight=580&odnWidth=580&odnBg=FFFFFF | D249: Verduras | E249: 1,5 | F249: kilos
A250: Ensalada Mixta Bolsa, 600 gr | B250: 2290 | C250: https://i5.walmartimages.cl/asr/1d9d8ce0-93fa-4b0a-8480-738b18e5923b.75a15a5f7f8220a9deb0d8f9881fba2c.jpeg?odnHeight=580&odnWidth=580&odnBg=FFFFFF | D250: Verduras | E250: 600 | F250: gramos
A251: Zapallo Trozo Orgánico Bolsa, 500 gr | B251: 2190 | C251: https://i5.walmartimages.cl/asr/ecdc6758-773f-4b80-8525-d7a336200915.4e2b6e38adf13f2ec3fc1022e499d34c.jpeg?odnHeight=580&odnWidth=580&odnBg=FFFFFF | D251: Verduras | E251: 500 | F251: gramos
A252: Zanahoria Orgánica Bolsa, 1 kg | B252: 1990 | C252: https://i5.walmartimages.cl/asr/e27d885f-d9d0-406d-91c7-445205b4aa47.ab91ddf075e759249ffa23d64017d296.jpeg?null=&odnHeight=580&odnWidth=580&odnBg=FFFFFF | D252: Verduras | E252: 1 | F252: kilos
A253: Ensalada Coleslaw Bolsa, 300 g | B253: 3790 | C253: https://i5.walmartimages.cl/asr/b4663f0f-7c77-43b6-ab6b-71e4da4dbc7a.fbb87028fd80313753c334c64748ff98.jpeg?odnHeight=580&odnWidth=580&odnBg=FFFFFF | D253: Verduras | E253: 300 | F253: gramos
A254: Ensalada Salad Kit Coleslaw Bolsa, 300 g | B254: 2890 | C254: https://i5.walmartimages.cl/asr/b8e594e7-b800-4141-be52-fe7606f9c7b2.fb286ca05713bad35e8f16ac69abaf2d.jpeg?null=&odnHeight=580&odnWidth=580&odnBg=FFFFFF | D254: Verduras | E254: 300 | F254: gramos
A255: Ensalada Toscana Dole, 300 g | B255: 1250 | C255: https://i5.walmartimages.cl/asr/5f52e9fe-7328-401d-a230-6992e3ad5ad9.507b4a77775d10f0b6389e935e36a2f0.jpeg?odnHeight=580&odnWidth=580&odnBg=FFFFFF | D255: Verduras | E255: 300 | F255: gramos
A256: Berro Bolsa, 200 gr | B256: 1690 | C256: https://i5.walmartimages.cl/asr/a8517a9b-f898-4a18-9733-2c292b76bde6.3cfe1a7bb61e6d45896d3aef2b438b9d.jpeg?odnHeight=580&odnWidth=580&odnBg=FFFFFF | D256: Verduras | E256: 200 | F256: gramos
A257: Ají Ahumado Pote, 50 g | B257: 1790 | C257: https://i5.walmartimages.cl/asr/93db18ce-e006-4c6d-a0cf-974ed2645384.3cffa5be97a08fbc0f087816fa1bcc92.jpeg?odnHeight=580&odnWidth=580&odnBg=FFFFFF | D257: Verduras | E257: 50 | F257: gramos
A258: Ají Verde Malla Imperfecto, 5 Un | B258: 1290 | C258: https://i5.walmartimages.cl/asr/432a3eb2-1e1b-4d6c-94c9-f0fa419be3d6.5f52410d5fd26b40283f0809cc7e0596.jpeg?odnHeight=580&odnWidth=580&odnBg=FFFFFF | D258: Verduras | E258: 5 | F258: unidad
A259: Ají Habanero Mix Colores Pote, 100 g | B259: 1390 | C259: https://i5.walmartimages.cl/asr/476fae6a-b217-4956-98e2-73a82ba14738.284cabb7aa83a7f4ef85022ba19ec7fd.jpeg?null=&odnHeight=580&odnWidth=580&odnBg=FFFFFF | D259: Verduras | E259: 100 | F259: gramos
A260: Ensalada Zanahoria Rallada Bolsa, 300 gr | B260: 1790 | C260: https://i5.walmartimages.cl/asr/a308de91-2f35-4929-88fa-26054c1ff387.3057cb077e8581f75859d9fb4f3a360e.jpeg?odnHeight=580&odnWidth=580&odnBg=FFFFFF | D260: Verduras | E260: 300 | F260: gramos
A261: Tomillo Pote, 1 Un | B261: 990 | C261: https://i5.walmartimages.cl/asr/b408f332-be74-4aec-9040-9dceec8d742d.b243b019aeffec0d08cbea8a6e702826.jpeg?odnHeight=580&odnWidth=580&odnBg=FFFFFF | D261: Verduras | E261: 1 | F261: unidad
... A266: Ají Cacho de Cabra Bolsa, 60 g | B266: 1790 | C266: https://i5.walmartimages.cl/asr/8d02a672-34d2-461e-9ed5-dfbf79d748c1.d79905d12a3881eb60d1e586284fe7ae.jpeg?odnHeight=580&odnWidth=580&odnBg=FFFFFF | D266: Verduras | E266: 60 | F266: gramos

Sheet Jumbo
A1: Nombre completo del producto | B1: Precio actual | C1: Url de la imagen | D1: Categoria | E1: Cantidad de medida | F1: Unidad
A2: Nectarín Importado Granel | B2: 3995 | C2: https://jumbocl.vteximg.com.br/arquivos/ids/352981-250-250/977515.jpg?v=638776695489130000 | D2: Frutas | E2: 1 | F2: kilos
A3: Plátano Extra Granel (1 a 2 un. Aprox) | B3: 795 | C3: https://jumbocl.vteximg.com.br/arquivos/ids/350892-250-250/Platano-granel.jpg?v=638776683161100000 | D3: Frutas | E3: 1 | F3: kilos
A4: Palta Hass Extra Chilena (2 un. Aprox) | B4: 3245 | C4: https://jumbocl.vteximg.com.br/arquivos/ids/348021-250-250/Palta-Hass-Extra-Chilena-granel.jpg?v=638784526059170000 | D4: Verduras | E4: 2 | F4: unidad
A5: Papa Malla 2 kg | B5: 2590 | C5: https://jumbocl.vteximg.com.br/arquivos/ids/348025-250-250/Papa-malla-2-kg.jpg?v=638776479317000000 | D5: Verduras | E5: 2 | F5: kilos
A6: Limón Malla 1 kg | B6: 1590 | C6: https://jumbocl.vteximg.com.br/arquivos/ids/348018-250-250/Limon-malla-1-kg.jpg?v=638776479219900000 | D6: Verduras | E6: 1 | F6: kilos
A7: Palta Hass Malla 1 kg | B7: 2890 | C7: https://jumbocl.vteximg.com.br/arquivos/ids/348022-250-250/Palta-hass-malla-1-kg.jpg?v=638776479276530000 | D7: Verduras | E7: 1 | F7: kilos
A8: Zanahoria Bolsa 1 kg | B8: 1350 | C8: https://jumbocl.vteximg.com.br/arquivos/ids/348051-250-250/Zanahoria-bolsa-1-kg.jpg?v=638776479671400000 | D8: Verduras | E8: 1 | F8: kilos
A9: Champiñón Bandeja 200 g | B9: 1650 | C9: https://jumbocl.vteximg.com.br/arquivos/ids/355100-250-250/Champi%C3%B1on-bandeja-200-g.jpg?v=638776705195000000 | D9: Verduras | E9: 200 | F9: gramos
A10: Zapallo Italiano 1 un. | B10: 790 | C10: https://jumbocl.vteximg.com.br/arquivos/ids/348057-250-250/Zapallo-italiano-un.jpg?v=638776479756130000 | D10: Verduras | E10: 1 | F10: unidad
A11: Tomate Larga Vida Granel (1 a 2 un. Aprox) | B11: 995 | C11: https://jumbocl.vteximg.com.br/arquivos/ids/297810-250-250/Tomate-granel.jpg?v=638775743642170000 | D11: Verduras | E11: 1 | F11: kilos
A12: Pepino Ensalada 1 un. | B12: 750 | C12: https://jumbocl.vteximg.com.br/arquivos/ids/348029-250-250/Pepino-ensalada-un.jpg?v=638776479365130000 | D12: Verduras | E12: 1 | F12: unidad
A13: Brócoli Films 1 un. | B13: 1590 | C13: https://jumbocl.vteximg.com.br/arquivos/ids/347994-250-250/Brocoli-films-un.jpg?v=638776478878200000 | D13: Verduras | E13: 1 | F13: unidad
... A123: Ajo 2 un. | B123: 1090 | C123: https://jumbocl.vteximg.com.br/arquivos/ids/353019-250-250/Ajo-2-un.jpg?v=638776695668300000 | D123: Verduras | E123: 2 | F123: unidad
A124: Mandarina Bolsa 1.5 kg | B124: 6990 | C124: https://jumbocl.vteximg.com.br/arquivos/ids/366686-250-250/Mandarina-bolsa-15-kg.jpg?v=638776764261130000 | D124: Frutas | E124: 1,5 | F124: kilos
A125: Tomate Hidropónico Racimo Granel | B125: 1245 | C125: https://jumbocl.vteximg.com.br/arquivos/ids/348044-250-250/261265-KG.jpg?v=638776479549630000 | D125: Verduras | E125: 1 | F125: kilos
A126: Cebolla Crujiente Ligeramente Salada 80 g | B126: 2490 | C126: https://jumbocl.vteximg.com.br/arquivos/ids/502890-250-250/Cebolla-Crujiente-Ligeramente-Salada-80-g.jpg?v=638924452010370000 | D126: Verduras | E126: 80 | F126: gramos
A127: Spring Mix Dole 150 g | B127: 3890 | C127: https://jumbocl.vteximg.com.br/arquivos/ids/347920-250-250/Spring-mix-Dole-150-g.jpg?v=638776477883670000 | D127: Verduras | E127: 150 | F127: gramos
A128: Corazones de Apio Dole 2 un. | B128: 3210 | C128: https://jumbocl.vteximg.com.br/arquivos/ids/353163-250-250/Corazones-de-Apio-Dole-2-unid.jpg?v=638776696231330000 | D128: Verduras | E128: 2 | F128: unidad
A129: Plátano Barraganette Granel | B129: 995 | C129: https://jumbocl.vteximg.com.br/arquivos/ids/347946-250-250/Platano-Barraganette-granel.jpg?v=638776478245070000 | D129: Frutas | E129: 1 | F129: kilos
A130: Salad Kit Coleslaw 300 g | B130: 2690 | C130: https://jumbocl.vteximg.com.br/arquivos/ids/445447-250-250/Salad-Kit-Coleslaw-300-g.jpg?v=638839631379530000 | D130: Verduras | E130: 300 | F130: gramos
A131: Ensalada Dole Apio 420 g | B131: 2390 | C131: https://jumbocl.vteximg.com.br/arquivos/ids/347909-250-250/Ensalada-apio-Dole-420-g.jpg?v=638776477738800000 | D131: Verduras | E131: 420 | F131: gramos
A132: Mix Frutilla Arándano 250 g | B132: 3490 | C132: https://jumbocl.vteximg.com.br/arquivos/ids/372027-250-250/Mix-frutilla-arandano-250-g.jpg?v=638776789638830000 | D132: Frutas | E132: 250 | F132: gramos
A133: Repollo Blanco Dole 300 g | B133: 1890 | C133: https://jumbocl.vteximg.com.br/arquivos/ids/347917-250-250/Repollo-blanco-300-g.jpg?v=638776477848100000 | D133: Verduras | E133: 300 | F133: gramos
A134: Manzana Modi Granel | B134: 1340 | C134: https://jumbocl.vteximg.com.br/arquivos/ids/590969-250-250/Manzana-Modi-Granel.jpg?v=639090085896070000 | D134: Frutas | E134: 1 | F134: kilos
A135: Pera Beurre Bosc Granel | B135: 2190 | C135: https://jumbocl.vteximg.com.br/arquivos/ids/586818-250-250/1057035-KG-01_96168.jpg?v=639083263089070000 | D135: Frutas | E135: 1 | F135: kilos
A136: Zanahoria Dole Corte Juliana 300 g | B136: 2190 | C136: https://jumbocl.vteximg.com.br/arquivos/ids/347922-250-250/Zanahoria-corte-Juliana-300-g.jpg?v=638776477909230000 | D136: Verduras | E136: 300 | F136: gramos
... A255: Hierba Buena Don Clemente Fresca 30 g | B255: 1060 | C255: https://jumbocl.vteximg.com.br/arquivos/ids/353009-250-250/1342051.jpg?v=638776695623800000 | D255: Verduras | E255: 30 | F255: gramos
A256: Papa Ox Malla 1.5 kg | B256: 3190 | C256: https://jumbocl.vteximg.com.br/arquivos/ids/393552-250-250/PAPA-OX-MALLA-15-KG.jpg?v=638776875102330000 | D256: Verduras | E256: 1,5 | F256: kilos
A257: Espinaca Agrolam 50 g | B257: 1050 | C257: https://jumbocl.vteximg.com.br/arquivos/ids/368354-250-250/Espinaca-50-g.jpg?v=638776772168000000 | D257: Verduras | E257: 50 | F257: gramos
A258: Cilantro Baby 60 g | B258: 1590 | C258: https://jumbocl.vteximg.com.br/arquivos/ids/348007-250-250/1227317.jpg?v=638776479082830000 | D258: Verduras | E258: 60 | F258: gramos
A259: Hierba Manzanilla Deshidratada 16 g | B259: 2190 | C259: https://jumbocl.vteximg.com.br/arquivos/ids/319061-250-250/Hierba-Manzanilla-Deshidratada-16-g.jpg?v=638776416491470000 | D259: Verduras | E259: 16 | F259: gramos
A260: Champiñón Ostra 200 g | B260: 1990 | C260: https://jumbocl.vteximg.com.br/arquivos/ids/348004-250-250/Champi%C3%B1ones-ostra-200-g.jpg?v=638776479042900000 | D260: Verduras | E260: 200 | F260: gramos
A261: Zapallo Diaguita Orgánico 1 un. | B261: 4490 | C261: https://jumbocl.vteximg.com.br/arquivos/ids/356829-250-250/Principal-34670.jpg?v=638776714539730000 | D261: Frutas y verduras orgánicas | E261: 1 | F261: unidad
A262: Mix Power Mix 700 g | B262: 8270 | C262: https://jumbocl.vteximg.com.br/arquivos/ids/366995-250-250/Mix-power-mix-700-g-1-183513419.jpg?v=638776765794870000 | D262: Frutos Secos y Semillas | E262: 700 | F262: gramos
A263: Pimiento Dulce 1 un. | B263: 1390 | C263: https://jumbocl.vteximg.com.br/arquivos/ids/362388-250-250/Pimiento-dulce-unid-1-476742.jpg?v=638776742734130000 | D263: Verduras | E263: 1 | F263: unidad
A264: Rúcula Baby Dole 140 g | B264: 3790 | C264: https://jumbocl.vteximg.com.br/arquivos/ids/347963-250-250/Rucula-Baby-Dole-140-g.jpg?v=638776478471400000 | D264: Verduras | E264: 140 | F264: gramos
A265: Ensalada Corazón de Apio 2 un. | B265: 3210 | C265: https://jumbocl.vteximg.com.br/arquivos/ids/501595-250-250/Ensalada-Corazon-de-Apio-2-un.jpg?v=638920189080070000 | D265: Verduras | E265: 2 | F265: unidad
A266: Mix Frutos Secos y Semillas 700 g | B266: 6990 | C266: https://jumbocl.vteximg.com.br/arquivos/ids/379282-250-250/Mix-Frutos-Secos-y-Semillas-700-g.jpg?v=638776818618330000 | D266: Frutos Secos y Semillas | E266: 700 | F266: gramos
A267: Brotes de Soya | B267: 1190 | C267: https://jumbocl.vteximg.com.br/arquivos/ids/306784-250-250/Brotes-de-Soya.jpg?v=638776383138100000 | D267: Verduras | E267: 1 | F267: unidad
A268: Zanahoria Baby 454 g | B268: 5490 | C268: https://jumbocl.vteximg.com.br/arquivos/ids/393366-250-250/Zanahoria-Baby-454-g.jpg?v=638776874340130000 | D268: Verduras | E268: 454 | F268: gramos
... A615: Salsa Heinz Hot Chilli Squeeze 245 g | B615: 3690 | C615: https://jumbocl.vteximg.com.br/arquivos/ids/625311-250-250/Salsa-Heinz-Hot-Chilli-Squeeze-245-g.jpg?v=639123194140100000 | D615: Verduras | E615: 245 | F615: gramos

Sheet Juan Esparraguito
A1: Nombre completo del producto | B1: Precio actual | C1: Url de la imagen | D1: Categoria | E1: Cantidad de medida | F1: Unidad
A2: Caja Semanal Base (1 -2 persona) - Más verdes / Para Hoy | B2: 22950 | C2: https://cdn.shopify.com/s/files/1/0358/9780/2890/files/Canasta_base_de_frutas_y_verduras_Juan_Esparraguito.jpg?v=1774443286 | D2: Frutas | E2: 1 | F2: bolsa
A3: Caja Semanal Base (1 -2 persona) - Más verdes / 2 -3 días | B3: 22950 | C3: https://cdn.shopify.com/s/files/1/0358/9780/2890/files/Canasta_base_de_frutas_y_verduras_Juan_Esparraguito.jpg?v=1774443286 | D3: Frutas | E3: 1 | F3: bolsa
A4: Caja Semanal Base (1 -2 persona) - Más amarillos / Para Hoy | B4: 22950 | C4: https://cdn.shopify.com/s/files/1/0358/9780/2890/files/Canasta_base_de_frutas_y_verduras_Juan_Esparraguito.jpg?v=1774443286 | D4: Frutas | E4: 1 | F4: bolsa
A5: Caja Semanal Base (1 -2 persona) - Más amarillos / 2 -3 días | B5: 22950 | C5: https://cdn.shopify.com/s/files/1/0358/9780/2890/files/Canasta_base_de_frutas_y_verduras_Juan_Esparraguito.jpg?v=1774443286 | D5: Frutas | E5: 1 | F5: bolsa
A6: Caja Semanal Completa (2-3 personas) - Más verdes / Para Hoy | B6: 37735 | C6: https://cdn.shopify.com/s/files/1/0358/9780/2890/files/sinarandano.jpg?v=1780939580 | D6: Frutas | E6: 1 | F6: bolsa
A7: Caja Semanal Completa (2-3 personas) - Más verdes / 2 -3 días | B7: 37735 | C7: https://cdn.shopify.com/s/files/1/0358/9780/2890/files/sinarandano.jpg?v=1780939580 | D7: Frutas | E7: 1 | F7: bolsa
A8: Caja Semanal Completa (2-3 personas) - Más amarillos / Para Hoy | B8: 37735 | C8: https://cdn.shopify.com/s/files/1/0358/9780/2890/files/sinarandano.jpg?v=1780939580 | D8: Frutas | E8: 1 | F8: bolsa
A9: Caja Semanal Completa (2-3 personas) - Más amarillos / 2 -3 días | B9: 37735 | C9: https://cdn.shopify.com/s/files/1/0358/9780/2890/files/sinarandano.jpg?v=1780939580 | D9: Frutas | E9: 1 | F9: bolsa
A10: Caja Semanal Familiar (+4 personas) - Más verdes / Para Hoy | B10: 64065 | C10: https://cdn.shopify.com/s/files/1/0358/9780/2890/files/2_4bbd85bb-ff86-418f-bba7-9521000503f5.jpg?v=1780940429 | D10: Frutas | E10: 1 | F10: bolsa
A11: Caja Semanal Familiar (+4 personas) - Más verdes / 2 -3 días | B11: 64065 | C11: https://cdn.shopify.com/s/files/1/0358/9780/2890/files/2_4bbd85bb-ff86-418f-bba7-9521000503f5.jpg?v=1780940429 | D11: Frutas | E11: 1 | F11: bolsa
A12: Caja Semanal Familiar (+4 personas) - Más amarillos / Para Hoy | B12: 64065 | C12: https://cdn.shopify.com/s/files/1/0358/9780/2890/files/2_4bbd85bb-ff86-418f-bba7-9521000503f5.jpg?v=1780940429 | D12: Frutas | E12: 1 | F12: bolsa
A13: Caja Semanal Familiar (+4 personas) - Más amarillos / 2 -3 días | B13: 64065 | C13: https://cdn.shopify.com/s/files/1/0358/9780/2890/files/2_4bbd85bb-ff86-418f-bba7-9521000503f5.jpg?v=1780940429 | D13: Frutas | E13: 1 | F13: bolsa
... A113: Zapallo Trozo (500 grs) | B113: 1290 | C113: https://cdn.shopify.com/s/files/1/0358/9780/2890/files/FotosWeb_parte3_Mesadetrabajo1copia7.jpg?v=1711036726 | D113: Verduras | E113: 500 | F113: gramos

Sheet Packs
A1: Caja Semanal Esenciales (2-3 prs)
A2: Producto | B2: Cantidad | C2: Costo | D2: PVP
A3: Cebolla | B3: 3 | C3: =(VLOOKUP(A3,'Listado de precios'!A:D,4,0))*B3 -> 750 | D3: =VLOOKUP(A3,'Listado de precios'!A:E,5,0)*B3 -> 1350 | E3: =VLOOKUP(A3,'Listado de precios'!A:Q,12,0) -> 0.41860465
A4: Limon | B4: 1 | C4: =(VLOOKUP(A4,'Listado de precios'!A:D,4,0))*B4 -> 700 | D4: =VLOOKUP(A4,'Listado de precios'!A:E,5,0)*B4 -> 1950 | E4: =VLOOKUP(A4,'Listado de precios'!A:Q,12,0) -> 0.58579882
A5: Papa | B5: 1 | C5: =(VLOOKUP(A5,'Listado de precios'!A:D,4,0))*B5 -> 850 | D5: =VLOOKUP(A5,'Listado de precios'!A:E,5,0)*B5 -> 1590 | E5: =VLOOKUP(A5,'Listado de precios'!A:Q,12,0) -> 0.22018349
A6: Pimentón verde | B6: 1 | C6: =(VLOOKUP(A6,'Listado de precios'!A:D,4,0))*B6 -> 700 | D6: =VLOOKUP(A6,'Listado de precios'!A:E,5,0)*B6 -> 1190 | E6: =VLOOKUP(A6,'Listado de precios'!A:Q,12,0) -> 0.29292929
A7: Tomate larga vida | B7: 1 | C7: =(VLOOKUP(A7,'Listado de precios'!A:D,4,0))*B7 -> 1500 | D7: =VLOOKUP(A7,'Listado de precios'!A:E,5,0)*B7 -> 2190 | E7: =VLOOKUP(A7,'Listado de precios'!A:Q,12,0) -> 0.24623116
A8: Zanahoria | B8: 1 | C8: =(VLOOKUP(A8,'Listado de precios'!A:D,4,0))*B8 -> 800 | D8: =VLOOKUP(A8,'Listado de precios'!A:E,5,0)*B8 -> 1290 | E8: =VLOOKUP(A8,'Listado de precios'!A:Q,12,0) -> 0.37984496
A9: Ajo | B9: 1 | C9: =(VLOOKUP(A9,'Listado de precios'!A:D,4,0))*B9 -> 200 | D9: =VLOOKUP(A9,'Listado de precios'!A:E,5,0)*B9 -> 350 | E9: =VLOOKUP(A9,'Listado de precios'!A:Q,12,0) -> 0.33333333
A10: Huevo Primera Color | B10: 12 | C10: =(VLOOKUP(A10,'Listado de precios'!A:D,4,0))*B10 -> 3000 | D10: =VLOOKUP(A10,'Listado de precios'!A:E,5,0)*B10 -> 4800 | E10: =VLOOKUP(A10,'Listado de precios'!A:Q,12,0) -> 0.44320713
A11: Total | B11: =SUM(B2:B10) -> 21 | C11: =SUM(C3:C10) -> 8500 | D11: 14990 | E11: =(D11-C11)/D11 -> 0.4329553
A13: Caja semanal completa (3-4 prs)
A14: Cebolla | B14: 3 | C14: =(VLOOKUP(A14,'Listado de precios'!A:D,4,0))*B14 -> 750 | D14: =VLOOKUP(A14,'Listado de precios'!A:E,5,0)*B14 -> 1350 | E14: =VLOOKUP(A14,'Listado de precios'!A:Q,12,0) -> 0.41860465
A15: Brocoli | B15: 1 | C15: =(VLOOKUP(A15,'Listado de precios'!A:D,4,0))*B15 -> 1400 | D15: =VLOOKUP(A15,'Listado de precios'!A:E,5,0)*B15 -> 1990 | E15: =VLOOKUP(A15,'Listado de precios'!A:Q,12,0) -> 0.29648241
A16: Lechuga española | B16: 1 | C16: =(VLOOKUP(A16,'Listado de precios'!A:D,4,0))*B16 -> 800 | D16: =VLOOKUP(A16,'Listado de precios'!A:E,5,0)*B16 -> 1890 | E16: =VLOOKUP(A16,'Listado de precios'!A:Q,12,0) -> 0.57671958
A17: Limon | B17: 1 | C17: =(VLOOKUP(A17,'Listado de precios'!A:D,4,0))*B17 -> 700 | D17: =VLOOKUP(A17,'Listado de precios'!A:E,5,0)*B17 -> 1950 | E17: =VLOOKUP(A17,'Listado de precios'!A:Q,12,0) -> 0.58579882
A18: Palta hass chilena | B18: 1 | C18: =(VLOOKUP(A18,'Listado de precios'!A:D,4,0))*B18 -> 5500 | D18: =VLOOKUP(A18,'Listado de precios'!A:E,5,0)*B18 -> 6500 | E18: =VLOOKUP(A18,'Listado de precios'!A:Q,12,0) -> 0.081803005
A19: Papa | B19: 1 | C19: =(VLOOKUP(A19,'Listado de precios'!A:D,4,0))*B19 -> 850 | D19: =VLOOKUP(A19,'Listado de precios'!A:E,5,0)*B19 -> 1590 | E19: =VLOOKUP(A19,'Listado de precios'!A:Q,12,0) -> 0.22018349
A20: Pimentón verde | B20: 1 | C20: =(VLOOKUP(A20,'Listado de precios'!A:D,4,0))*B20 -> 700 | D20: =VLOOKUP(A20,'Listado de precios'!A:E,5,0)*B20 -> 1190 | E20: =VLOOKUP(A20,'Listado de precios'!A:Q,12,0) -> 0.29292929
A21: Tomate larga vida | B21: 1 | C21: =(VLOOKUP(A21,'Listado de precios'!A:D,4,0))*B21 -> 1500 | D21: =VLOOKUP(A21,'Listado de precios'!A:E,5,0)*B21 -> 2190 | E21: =VLOOKUP(A21,'Listado de precios'!A:Q,12,0) -> 0.24623116
A22: Zanahoria | B22: 1 | C22: =(VLOOKUP(A22,'Listado de precios'!A:D,4,0))*B22 -> 800 | D22: =VLOOKUP(A22,'Listado de precios'!A:E,5,0)*B22 -> 1290 | E22: =VLOOKUP(A22,'Listado de precios'!A:Q,12,0) -> 0.37984496
A23: Zapallo italiano | B23: 2 | C23: =(VLOOKUP(A23,'Listado de precios'!A:D,4,0))*B23 -> 1200 | D23: =VLOOKUP(A23,'Listado de precios'!A:E,5,0)*B23 -> 1580 | E23: =VLOOKUP(A23,'Listado de precios'!A:Q,12,0) -> 0.24050633
A24: Zapallo camote | B24: 1 | C24: =(VLOOKUP(A24,'Listado de precios'!A:D,4,0))*B24 -> 1000 | D24: =VLOOKUP(A24,'Listado de precios'!A:E,5,0)*B24 -> 1990 | E24: =VLOOKUP(A24,'Listado de precios'!A:Q,12,0) -> -0.01010101
A25: Ajo | B25: 1 | C25: =(VLOOKUP(A25,'Listado de precios'!A:D,4,0))*B25 -> 200 | D25: =VLOOKUP(A25,'Listado de precios'!A:E,5,0)*B25 -> 350 | E25: =VLOOKUP(A25,'Listado de precios'!A:Q,12,0) -> 0.33333333
... A30: Huevo Primera Color | B30: 12 | C30: =(VLOOKUP(A30,'Listado de precios'!A:D,4,0))*B30 -> 3000 | D30: =VLOOKUP(A30,'Listado de precios'!A:E,5,0)*B30 -> 4800 | E30: =VLOOKUP(A30,'Listado de precios'!A:Q,12,0) -> 0.44320713
A31: Total | B31: =SUM(B14:B30) -> 31 | C31: =SUM(C14:C30) -> 23400 | D31: 35990 | E31: =(D31-C31)/D31 -> 0.34981939
A33: Caja semanal frutas
A34: Plátano | B34: 1 | C34: =(VLOOKUP(A34,'Listado de precios'!A:D,4,0))*B34 -> 1300 | D34: =VLOOKUP(A34,'Listado de precios'!A:E,5,0)*B34 -> 1790 | E34: =VLOOKUP(A34,'Listado de precios'!A:Q,12,0) -> 0.34673367
A35: Naranjas | B35: 1 | C35: =(VLOOKUP(A35,'Listado de precios'!A:D,4,0))*B35 -> 1350 | D35: =VLOOKUP(A35,'Listado de precios'!A:E,5,0)*B35 -> 2290 | E35: =VLOOKUP(A35,'Listado de precios'!A:Q,12,0) -> 0.41048035
A36: Frutillas | B36: 1 | C36: =(VLOOKUP(A36,'Listado de precios'!A:D,4,0))*B36 -> 1600 | D36: =VLOOKUP(A36,'Listado de precios'!A:E,5,0)*B36 -> 4690 | E36: =VLOOKUP(A36,'Listado de precios'!A:Q,12,0) -> 0.69907843
A37: Manzana fuji | B37: 1 | C37: =(VLOOKUP(A37,'Listado de precios'!A:D,4,0))*B37 -> 1750 | D37: =VLOOKUP(A37,'Listado de precios'!A:E,5,0)*B37 -> 2590 | E37: =VLOOKUP(A37,'Listado de precios'!A:Q,12,0) -> 0.20091324
A38: Total | B38: =SUM(B34:B37) -> 4 | C38: =SUM(C34:C37) -> 6000 | D38: 11490 | E38: =(D38-C38)/D38 -> 0.47780679
A40: Caja ensaladas lover
A41: Lechuga española | B41: 1 | C41: =(VLOOKUP(A41,'Listado de precios'!A:D,4,0))*B41 -> 800 | D41: =VLOOKUP(A41,'Listado de precios'!A:E,5,0)*B41 -> 1890 | E41: =VLOOKUP(A41,'Listado de precios'!A:Q,12,0) -> 0.57671958
A42: Pepinos | B42: 1 | C42: =(VLOOKUP(A42,'Listado de precios'!A:D,4,0))*B42 -> 650 | D42: =VLOOKUP(A42,'Listado de precios'!A:E,5,0)*B42 -> 790 | E42: =VLOOKUP(A42,'Listado de precios'!A:Q,12,0) -> 0.17721519
A43: Palta hass chilena | B43: 1 | C43: =(VLOOKUP(A43,'Listado de precios'!A:D,4,0))*B43 -> 5500 | D43: =VLOOKUP(A43,'Listado de precios'!A:E,5,0)*B43 -> 6500 | E43: =VLOOKUP(A43,'Listado de precios'!A:Q,12,0) -> 0.081803005
A44: Tomate larga vida | B44: 1 | C44: =(VLOOKUP(A44,'Listado de precios'!A:D,4,0))*B44 -> 1500 | D44: =VLOOKUP(A44,'Listado de precios'!A:E,5,0)*B44 -> 2190 | E44: =VLOOKUP(A44,'Listado de precios'!A:Q,12,0) -> 0.24623116
A45: Limon | B45: 1 | C45: =(VLOOKUP(A45,'Listado de precios'!A:D,4,0))*B45 -> 700 | D45: =VLOOKUP(A45,'Listado de precios'!A:E,5,0)*B45 -> 1950 | E45: =VLOOKUP(A45,'Listado de precios'!A:Q,12,0) -> 0.58579882
A46: Total | B46: =SUM(B41:B45) -> 5 | C46: =SUM(C41:C45) -> 9150 | D46: =SUM(D41:D45) -> 13320 | E46: =(D46-C46)/D46 -> 0.31306306

Sheet LP GF
A1: Nombre producto | B1: Precio | C1: Url Imagen | D1: Descripcion Opcional | E1: SKU Opcional | F1: EAN Opcional | G1: Categoria | H1: Unidad de medida Opcional | I1: Cantidad de medida | J1: Tamaño
A2: Acelga - Paquete | B2: 1290 | C2: https://cdn.shopify.com/s/files/1/0733/7318/8148/files/acelga.jpg?v=1762371793 | D2: Paquete de acelga fresca, ideal para ensaladas, guisos y preparaciones saludables. | G2: Verdulería | H2: Paquete | I2: 1 | J2: sm
A3: Ají Amarillo (peruano) - Kilo | B3: 1196 | C3: https://cdn.shopify.com/s/files/1/0733/7318/8148/files/ajiamarillo.jpg?v=1762286889 | D3: Ají amarillo peruano fresco por kilo, perfecto para salsas y recetas tradicionales. | G3: Verdulería | H3: Kilo | I3: 0.1 | J3: sm
A4: Ají Verde (infierno) - Kilo | B4: 1112 | C4: https://cdn.shopify.com/s/files/1/0733/7318/8148/files/ajiverde.png?v=1762371744 | D4: Ají verde de sabor intenso disponible por kilo, ideal para dar picor a tus comidas. | G4: Verdulería | H4: Kilo | I4: 0.2 | J4: sm
A5: Ajo - Unidad | B5: 300 | C5: https://cdn.shopify.com/s/files/1/0733/7318/8148/files/ajo.jpg?v=1762371704 | D5: Cabeza de ajo fresca por unidad, esencial para condimentar todo tipo de preparaciones. | G5: Verdulería | H5: Unidad | I5: 1 | J5: sm
A6: Albahaca - Kilo | B6: 745 | C6: https://cdn.shopify.com/s/files/1/0733/7318/8148/files/zoomfotonoticia-129.jpg?v=1762371661 | D6: Albahaca fresca por kilo, ideal para pastas, ensaladas y salsas. | G6: Verdulería | H6: Kilo | I6: 0.05 | J6: sm
A7: Apio - Unidad | B7: 1990 | C7: https://cdn.shopify.com/s/files/1/0733/7318/8148/files/apio.jpg?v=1762371609 | D7: Apio fresco por unidad, perfecto para ensaladas, sopas y jugos. | G7: Verdulería | H7: Unidad | I7: 1 | J7: sm
A8: Alcachofas Españolas - Unidad | B8: 1390 | C8: https://cdn.shopify.com/s/files/1/0733/7318/8148/files/alcachofa_espaola_1ce9f8da-7a49-4ca2-9f3c-dad8035d9680.jpg?v=1762273270 | D8: Alcachofa española fresca por unidad, ideal para cocinar o consumir al vapor. | G8: Verdulería | H8: Unidad | I8: 1 | J8: sm
A9: Berenjena - Unidad | B9: 790 | C9: https://cdn.shopify.com/s/files/1/0733/7318/8148/files/berenjena.jpg?v=1762371565 | D9: Berenjena fresca por unidad, excelente para asados, guisos y salteados. | G9: Verdulería | H9: Unidad | I9: 1 | J9: sm
A10: Berros - Kilo | B10: 995 | C10: https://cdn.shopify.com/s/files/1/0733/7318/8148/files/berro.png?v=1762371522 | D10: Berros frescos por kilo, ideales para ensaladas y acompañamientos. | G10: Verdulería | H10: Kilo | I10: 0.05 | J10: sm
A11: Betarraga - Paquete | B11: 2250 | C11: https://cdn.shopify.com/s/files/1/0733/7318/8148/files/betarraga.jpg?v=1762371470 | D11: Paquete de betarragas frescas, perfectas para ensaladas y jugos. | G11: Verdulería | H11: Paquete | I11: 1 | J11: sm
A12: Brócoli - Unidad | B12: 1990 | C12: https://cdn.shopify.com/s/files/1/0733/7318/8148/files/brocoli.jpg?v=1762371426 | D12: Brócoli fresco por unidad, ideal para cocción al vapor, salteados y ensaladas. | G12: Verdulería | H12: Unidad | I12: 1 | J12: sm
A13: Bruselas - Kilo | B13: 3690 | C13: https://cdn.shopify.com/s/files/1/0733/7318/8148/files/brusela_7ad88d5e-8c5a-44de-b1b8-f5077d48c88a.jpg?v=1770824864 | D13: Coles de Bruselas frescas por kilo, perfectas para hornear o saltear. | G13: Verdulería | H13: Kilo | I13: 0.5 | J13: sm
... A74: Almendras con Chocolate - Kilo | B74: 3990 | C74: https://cdn.shopify.com/s/files/1/0733/7318/8148/files/almendraschocolate_jpg.jpg?v=1762365179 | D74: Almendras con chocolate por kilo, una deliciosa combinación para disfrutar. | G74: Verdulería | H74: Kilo | I74: 0.01 | J74: sm
A75: Aloe Vera - Kilo | C75: https://ibb.co/ycgY92GC | D75: Aloe vera por kilo, ideal para preparaciones naturales y consumo específico. | G75: Verdulería | H75: Kilo | I75: 0.01 | J75: sm
A76: Avellanas Europea - Kilo | C76: https://cdn.shopify.com/s/files/1/0733/7318/8148/files/5-avellana-europea3011.jpg?v=1762365142 | D76: Avellanas europeas por kilo, perfectas para repostería y consumo directo. | G76: Verdulería | H76: Kilo | I76: 0.01 | J76: sm
A77: Castañas de Caju - Kilo | C77: https://cdn.shopify.com/s/files/1/0733/7318/8148/files/castanascaju_jpg.jpg?v=1762271831 | D77: Castañas de cajú por kilo, ideales como snack o ingrediente culinario. | G77: Verdulería | H77: Kilo | I77: 0.05 | J77: sm
A78: Chips de Banana - Kilo | C78: https://cdn.shopify.com/s/files/1/0733/7318/8148/files/chipsbanana_jpg.jpg?v=1762365247 | D78: Chips de banana por kilo, un snack crujiente y delicioso. | G78: Verdulería | H78: Kilo | I78: 0.01 | J78: sm
A79: Ciruela Deshidratada - Kilo | C79: https://cdn.shopify.com/s/files/1/0733/7318/8148/files/cirueladeshidratada.jpg-600x503.jpg?v=1762365715 | D79: Ciruela deshidratada por kilo, ideal para colaciones y repostería. | G79: Verdulería | H79: Kilo | I79: 0.01 | J79: sm
A80: Coco en Cubos - Kilo | C80: https://ibb.co/Tx0NwCNN | D80: Coco en cubos por kilo, perfecto para snacks y preparaciones dulces. | G80: Verdulería | H80: Kilo | I80: 0.01 | J80: sm
A81: Coco Laminado - Kilo | C81: https://cdn.shopify.com/s/files/1/0733/7318/8148/files/cocolaminado_jpg.jpg?v=1770819410 | D81: Coco laminado por kilo, ideal para repostería y decoración. | G81: Verdulería | H81: Kilo | I81: 0.01 | J81: sm
A82: Coco Rallado - Kilo | C82: https://cdn.shopify.com/s/files/1/0733/7318/8148/files/cocorallado.jpg?v=1770819461 | D82: Coco rallado por kilo, perfecto para postres y preparaciones caseras. | G82: Verdulería | H82: Kilo | I82: 0.01 | J82: sm
A83: Cranberries - Kilo | C83: https://cdn.shopify.com/s/files/1/0733/7318/8148/files/cramberries_jpg.jpg?v=1762365110 | D83: Cranberries por kilo, ideales para snacks, ensaladas y repostería. | G83: Verdulería | H83: Kilo | I83: 0.01 | J83: sm
A84: Dátiles - Kilo | C84: https://cdn.shopify.com/s/files/1/0733/7318/8148/files/datiles_jpg.jpg?v=1762365547 | D84: Dátiles por kilo, dulces y perfectos para colaciones y recetas saludables. | G84: Verdulería | H84: Kilo | I84: 0.01 | J84: sm
A85: Flor de Hibiscos - Kilo | C85: https://cdn.shopify.com/s/files/1/0733/7318/8148/files/florhibiscos_jpg.jpg?v=1762365517 | D85: Flor de hibiscos por kilo, ideal para infusiones y preparaciones naturales. | G85: Verdulería | H85: Kilo | I85: 0.01 | J85: sm
A86: Goji - Kilo | C86: https://cdn.shopify.com/s/files/1/0733/7318/8148/files/goji.jpg-600x399.jpg?v=1762365073 | D86: Bayas de goji por kilo, perfectas para snacks y mezclas saludables. | G86: Verdulería | H86: Kilo | I86: 0.01 | J86: sm
... A108: Tomate Deshidratado - Kilo | C108: https://cdn.shopify.com/s/files/1/0733/7318/8148/files/tomatedeshidratado_jpg.jpg?v=1770819609 | D108: Tomate deshidratado por kilo, ideal para pastas, ensaladas y aperitivos. | G108: Verdulería | H108: Kilo | I108: 0.1 | J108: sm

Sheet Clasificación
A1: Frutas | B1: Verduras | C1: Frutos secos | D1: Cajas listas para tu semana
A2: Arandano | B2: Acelga | C2: Almendras
A3: Frutillas | B3: Ají amarillo (peruano) | C3: Almendras con chocolate
A4: Kiwi | B4: Ají verde (infierno) | C4: Aloe vera
A5: Limon | B5: Ajo | C5: Avellanas europea
A6: Limón sutil | B6: Albahaca | C6: Castañas de caju
A7: Limon de pica | B7: Apio | C7: Chips de banana
A8: Mandarina | B8: Alcachofas españolas | C8: Ciruela deshidratada
A9: Mango | B9: Berenjena | C9: Coco en cubos
A10: Manzana fuji | B10: Berros | C10: Coco laminado
A11: Manzana verde | B11: Betarraga | C11: Coco rallado
A12: Manzana pink lady | B12: Brocoli | C12: Cranberries
A13: Mancaqui | B13: Bruselas | C13: Dátiles
... A37: Huesillo grande | B37: Pimentón rojo | C37: Tomate deshidratado
A38: Kiwi deshidratado | B38: Pimentón verde
A39: Mango deshidratado | B39: Porotos verdes
A40: Manzana deshidratada | B40: Rabanitos
A41: Nueces | B41: Repollo morado
A42: Papaya deshidratada | B42: Repollo crespo
A43: Pasas con chocolate | B43: Rúcula
A44: Pasas negras | B44: Tomate larga vida
A45: Pasas rubias | B45: Tomate Cherry
A46: Pomelo deshidratado | B46: Tomate pomarola
B47: Zanahoria
B48: Zapallo camote
B49: Zapallo italiano
B50: Aloe vera
B51: Flor de hibiscos
B52: Linaza
B53: Maíz curagua
B54: Maní chocolate
B55: Mani con sal
B56: Maní confitado
B57: Maní japonés natural
B58: Maní Japonés picante
... B63: Tomate deshidratado
